Workbook

Sheet Control
A1: Plan de pruebas — Freelance (rescate)
A2: Una fila por escenario. Las columnas de resultado se calculan desde cada hoja ESC-xx. Llenar en amarillo: Corrida actual y Responsable.
A4: ID | B4: Escenario | C4: Núm. original | D4: Módulo | E4: Objetivo | F4: Dependencias | G4: Sesión | H4: Pasos | I4: Legado Cumple | J4: Legado No cumple | K4: Legado Sin ejecutar | L4: Ejecutados | M4: CUMPLE | N4: % cumplimiento | O4: Estado | P4: Corrida actual | Q4: Hallazgos abiertos | R4: ⚠ Calidad del caso
A5: ESC-01 | B5: Pedido para Metropólitan (Seguridad) - Sin Cancelación | C5: Escenario 1 | D5: Pedidos | E5: Validar el alta completa de un pedido de Seguridad sin cancelación y su detalle, hasta la cancelación del pedido. | F5: — | G5: S01 | H5: 25 | I5: 17 | J5: 8 | K5: 0 | L5: ='ESC-01'!J3 | M5: ='ESC-01'!J4 | N5: ='ESC-01'!J5 | O5: =IF(H5=0,"Por definir",IF(N5=1,"✅ 100%",IF(L5=0,"Sin probar","En ciclo"))) | Q5: =COUNTIFS(Hallazgos!$B:$B,A5,Hallazgos!$M:$M,"<>Cerrado",Hallazgos!$A:$A,"<>") | R5: Paso 13: la descripción (prerellenos) y el esperado (productos de Seguridad) no corresponden.
A6: ESC-02 | B6: Pedido PRG-Producción con complejidad y días show | C6: Escenario 2 | D6: Pedidos | E6: Validar un pedido PRG con complejidad y días de show: personal Staff, bloques por producto y presupuesto ligado a complejidad. | F6: — | G6: S02 | H6: 26 | I6: 13 | J6: 6 | K6: 7 | L6: ='ESC-02'!J3 | M6: ='ESC-02'!J4 | N6: ='ESC-02'!J5 | O6: =IF(H6=0,"Por definir",IF(N6=1,"✅ 100%",IF(L6=0,"Sin probar","En ciclo"))) | P6: R1 | Q6: =COUNTIFS(Hallazgos!$B:$B,A6,Hallazgos!$M:$M,"<>Cerrado",Hallazgos!$A:$A,"<>") | R6: Paso 5 esperado dice 'UN de seguridad' (copiado del Esc. 1). Paso 7 texto corrupto ('movi+E10:F10miento'). Paso 8 es Servicio Interno pero el esperado habla de Pedido. Paso 18: 'nos' probablemente es 'no'.
A7: ESC-03 | B7: Pedido PRG-Producción con complejidad y fase de evento | C7: Escenario 3 | D7: Pedidos | E7: Validar un pedido PRG sin complejidad con varios detalles por fase de evento y arrastre de valores del detalle anterior. | F7: — | G7: S03 | H7: 32 | I7: 18 | J7: 12 | K7: 2 | L7: ='ESC-03'!J3 | M7: ='ESC-03'!J4 | N7: ='ESC-03'!J5 | O7: =IF(H7=0,"Por definir",IF(N7=1,"✅ 100%",IF(L7=0,"Sin probar","En ciclo"))) | Q7: =COUNTIFS(Hallazgos!$B:$B,A7,Hallazgos!$M:$M,"<>Cerrado",Hallazgos!$A:$A,"<>") | R7: Paso 5 marcado Cumple y No cumple a la vez; esperado dice 'UN de seguridad'. Paso 8: Servicio Interno con esperado de Pedido.
A8: ESC-04 | B8: Pedido para Azteca (Seguridad) - Futbol América vs Pumas | C8: Escenario 4 | D8: Pedidos | E8: Validar un pedido de Seguridad de gran volumen (9 productos) con alta repetitiva de detalles. | F8: — | G8: S04 | H8: 106 | I8: 25 | J8: 6 | K8: 75 | L8: ='ESC-04'!J3 | M8: ='ESC-04'!J4 | N8: ='ESC-04'!J5 | O8: =IF(H8=0,"Por definir",IF(N8=1,"✅ 100%",IF(L8=0,"Sin probar","En ciclo"))) | Q8: =COUNTIFS(Hallazgos!$B:$B,A8,Hallazgos!$M:$M,"<>Cerrado",Hallazgos!$A:$A,"<>") | R8: 9 bloques casi idénticos (parametrizable). El paso final 'El pedido debe quedar de la siguiente forma' remite a una imagen del archivo original.
A9: ESC-05 | B9: Seriado con cancelación de un día para que no deje forzar ese día de otro pedido | C9: Escenario 5 | D9: Pedidos / Asignaciones | E9: Validar seriados: bloque semanal, cancelación de un día y que no se pueda forzar ese día desde otro pedido según la propiedad del puesto. | F9: Requiere que un empleado confirme el bloque (portal) | G9: S05 | H9: 48 | I9: 43 | J9: 1 | K9: 4 | L9: ='ESC-05'!J3 | M9: ='ESC-05'!J4 | N9: ='ESC-05'!J5 | O9: =IF(H9=0,"Por definir",IF(N9=1,"✅ 100%",IF(L9=0,"Sin probar","En ciclo"))) | Q9: =COUNTIFS(Hallazgos!$B:$B,A9,Hallazgos!$M:$M,"<>Cerrado",Hallazgos!$A:$A,"<>") | R9: Numeración repetida (varios pasos '13'). Producto de Operaciones Inmuebles con esperado 'catálogo PRG'. Fase: legado observa 'Ninguno' vs 'No aplica'. Variante final sin pasos.
A10: ESC-06 | B10: Pedido de Transporte con empalme de horario | C10: Escenario 6 | D10: Pedidos | E10: Validar la detección de empalme de horarios entre detalles de un pedido de Transporte. | F10: — | G10: S06 | H10: 5 | I10: 2 | J10: 2 | K10: 1 | L10: ='ESC-06'!J3 | M10: ='ESC-06'!J4 | N10: ='ESC-06'!J5 | O10: =IF(H10=0,"Por definir",IF(N10=1,"✅ 100%",IF(L10=0,"Sin probar","En ciclo"))) | Q10: =COUNTIFS(Hallazgos!$B:$B,A10,Hallazgos!$M:$M,"<>Cerrado",Hallazgos!$A:$A,"<>")
A11: ESC-07 | B11: Comprobar fecha y hora de liberación | C11: Escenario 7 | D11: Pedidos | E11: Validar la liberación programada por fecha y hora, y la actualización del semáforo. | F11: Espera de 1 hora real | G11: S06 | H11: 5 | I11: 2 | J11: 0 | K11: 3 | L11: ='ESC-07'!J3 | M11: ='ESC-07'!J4 | N11: ='ESC-07'!J5 | O11: =IF(H11=0,"Por definir",IF(N11=1,"✅ 100%",IF(L11=0,"Sin probar","En ciclo"))) | Q11: =COUNTIFS(Hallazgos!$B:$B,A11,Hallazgos!$M:$M,"<>Cerrado",Hallazgos!$A:$A,"<>") | R11: Requiere esperar la hora programada; considerar mecanismo para simular tiempo.
A12: ESC-08 | B12: Validación de plazas | C12: Escenario 8 | D12: Asignaciones / Nómina | E12: Validar el sueldo según plaza vigente en la fecha del evento y su recálculo al mover la fecha de inicio. | F12: Empleado ID 54943; fechas 2019 | G12: S07 | H12: 13 | I12: 0 | J12: 0 | K12: 13 | L12: ='ESC-08'!J3 | M12: ='ESC-08'!J4 | N12: ='ESC-08'!J5 | O12: =IF(H12=0,"Por definir",IF(N12=1,"✅ 100%",IF(L12=0,"Sin probar","En ciclo"))) | Q12: =COUNTIFS(Hallazgos!$B:$B,A12,Hallazgos!$M:$M,"<>Cerrado",Hallazgos!$A:$A,"<>") | R12: Usa fechas de 2019: confirmar si siguen siendo válidas en el sistema nuevo.
A13: ESC-09 | B13: Validación de certeza valor | C13: Escenario 9 | D13: Asignaciones | E13: Validar que la certeza valor del empleado restringe visibilidad y asignación forzada. | F13: Empleado ID 57231 | G13: S07 | H13: 7 | I13: 0 | J13: 0 | K13: 7 | L13: ='ESC-09'!J3 | M13: ='ESC-09'!J4 | N13: ='ESC-09'!J5 | O13: =IF(H13=0,"Por definir",IF(N13=1,"✅ 100%",IF(L13=0,"Sin probar","En ciclo"))) | Q13: =COUNTIFS(Hallazgos!$B:$B,A13,Hallazgos!$M:$M,"<>Cerrado",Hallazgos!$A:$A,"<>")
A14: ESC-10 | B14: Cancelación de preasignación forzada por no confirmación | C14: Escenario 10 | D14: Asignaciones | E14: Validar el proceso de cancelación de preasignaciones no confirmadas y la visibilidad posterior. | F14: Empleados ID 3891, 16338, 33817, 46486, 54501 | G14: S08 | H14: 7 | I14: 1 | J14: 0 | K14: 6 | L14: ='ESC-10'!J3 | M14: ='ESC-10'!J4 | N14: ='ESC-10'!J5 | O14: =IF(H14=0,"Por definir",IF(N14=1,"✅ 100%",IF(L14=0,"Sin probar","En ciclo"))) | Q14: =COUNTIFS(Hallazgos!$B:$B,A14,Hallazgos!$M:$M,"<>Cerrado",Hallazgos!$A:$A,"<>") | R14: Pide 4 personas pero lista 5 IDs.
A15: ESC-11 | B15: Confirmación de personal sin puesto asignado vigente | C15: Escenario 11 | D15: Asignaciones | E15: Validar que no se permita preasignar a un empleado sin puesto vigente. | F15: Empleado ID 58172 | G15: S07 | H15: 7 | I15: 5 | J15: 0 | K15: 2 | L15: ='ESC-11'!J3 | M15: ='ESC-11'!J4 | N15: ='ESC-11'!J5 | O15: =IF(H15=0,"Por definir",IF(N15=1,"✅ 100%",IF(L15=0,"Sin probar","En ciclo"))) | Q15: =COUNTIFS(Hallazgos!$B:$B,A15,Hallazgos!$M:$M,"<>Cerrado",Hallazgos!$A:$A,"<>") | R15: Legado: los mensajes emergentes no indican qué regla falló.
A16: ESC-12 | B16: Productos similares | C16: Escenario 12 | D16: Asignaciones | E16: Validar la regla de productos similares en asignación y visibilidad. | F16: Al menos un empleado de control de accesos | G16: S08 | H16: 13 | I16: 5 | J16: 0 | K16: 8 | L16: ='ESC-12'!J3 | M16: ='ESC-12'!J4 | N16: ='ESC-12'!J5 | O16: =IF(H16=0,"Por definir",IF(N16=1,"✅ 100%",IF(L16=0,"Sin probar","En ciclo"))) | Q16: =COUNTIFS(Hallazgos!$B:$B,A16,Hallazgos!$M:$M,"<>Cerrado",Hallazgos!$A:$A,"<>")
A17: ESC-13 | B17: Validar que no se puedan cancelar reservaciones | C17: Escenario 13 | D17: Asignaciones | E17: Validar las reglas de cancelación de confirmaciones: pedido/detalle, 72 horas y cambio de horario con aviso. | F17: Varios empleados de seguridad con acceso al portal | G17: S09 | H17: 29 | I17: 0 | J17: 0 | K17: 29 | L17: ='ESC-13'!J3 | M17: ='ESC-13'!J4 | N17: ='ESC-13'!J5 | O17: =IF(H17=0,"Por definir",IF(N17=1,"✅ 100%",IF(L17=0,"Sin probar","En ciclo"))) | Q17: =COUNTIFS(Hallazgos!$B:$B,A17,Hallazgos!$M:$M,"<>Cerrado",Hallazgos!$A:$A,"<>") | R17: Nota: se repetirá cambiando lugar de cita y turnos.
A18: ESC-14 | B18: Pedido de matriciales para validar los sueldos | C18: Escenario 14 | D18: Nómina | E18: Validar el sueldo matricial en el portal del empleado (Saldos / eventos por procesar). | F18: Empleado con puesto Asistente Operador - IN | G18: S12 | H18: 10 | I18: 5 | J18: 0 | K18: 5 | L18: ='ESC-14'!J3 | M18: ='ESC-14'!J4 | N18: ='ESC-14'!J5 | O18: =IF(H18=0,"Por definir",IF(N18=1,"✅ 100%",IF(L18=0,"Sin probar","En ciclo"))) | Q18: =COUNTIFS(Hallazgos!$B:$B,A18,Hallazgos!$M:$M,"<>Cerrado",Hallazgos!$A:$A,"<>")
A19: ESC-15 | B19: Cancelación de asignación forzada | C19: Escenario 15 | D19: Asignaciones | E19: Validar que el empleado no pueda cancelar una asignación forzada. | F19: — | G19: S08 | H19: 8 | I19: 0 | J19: 0 | K19: 8 | L19: ='ESC-15'!J3 | M19: ='ESC-15'!J4 | N19: ='ESC-15'!J5 | O19: =IF(H19=0,"Por definir",IF(N19=1,"✅ 100%",IF(L19=0,"Sin probar","En ciclo"))) | Q19: =COUNTIFS(Hallazgos!$B:$B,A19,Hallazgos!$M:$M,"<>Cerrado",Hallazgos!$A:$A,"<>")
A20: ESC-16 | B20: Disminución de personal solicitado + Certeza valor | C20: Escenario 16 | D20: Asignaciones | E20: Validar que al reducir personal se cancelen primero los de menor certeza valor y luego el último confirmado. | F20: Empleados ID 1, 1962, 2074, 2116, 2790, 2795 | G20: S10 | H20: 17 | I20: 7 | J20: 0 | K20: 10 | L20: ='ESC-16'!J3 | M20: ='ESC-16'!J4 | N20: ='ESC-16'!J5 | O20: =IF(H20=0,"Por definir",IF(N20=1,"✅ 100%",IF(L20=0,"Sin probar","En ciclo"))) | Q20: =COUNTIFS(Hallazgos!$B:$B,A20,Hallazgos!$M:$M,"<>Cerrado",Hallazgos!$A:$A,"<>")
A21: ESC-17A | B21: Prorrateo (PENDIENTE TIGRE) | C21: Escenario 17 (numeración duplicada) | D21: Nómina | E21: Prorrateo (pendiente TIGRE). | F21: — | G21: S12 | H21: 10 | I21: 0 | J21: 0 | K21: 10 | L21: ='ESC-17A'!J3 | M21: ='ESC-17A'!J4 | N21: ='ESC-17A'!J5 | O21: =IF(H21=0,"Por definir",IF(N21=1,"✅ 100%",IF(L21=0,"Sin probar","En ciclo"))) | Q21: =COUNTIFS(Hallazgos!$B:$B,A21,Hallazgos!$M:$M,"<>Cerrado",Hallazgos!$A:$A,"<>") | R21: Contenido idéntico a ESC-14. Confirmar si es duplicado o falta definir los pasos.
A22: ESC-17B | B22: Pedido con 0.25 Turnos | C22: Escenario 17 (numeración duplicada) | D22: Pedidos / Nómina | E22: Validar turnos fraccionados (0.25): costo de nómina y fecha fin calculada. | F22: — | G22: S06 | H22: 7 | I22: 5 | J22: 2 | K22: 0 | L22: ='ESC-17B'!J3 | M22: ='ESC-17B'!J4 | N22: ='ESC-17B'!J5 | O22: =IF(H22=0,"Por definir",IF(N22=1,"✅ 100%",IF(L22=0,"Sin probar","En ciclo"))) | Q22: =COUNTIFS(Hallazgos!$B:$B,A22,Hallazgos!$M:$M,"<>Cerrado",Hallazgos!$A:$A,"<>")
A23: ESC-18 | B23: Lista Negra | C23: Escenario 18 | D23: Asignaciones / Seguridad | E23: Validar la lista negra: permisos de administración y bloqueo del empleado vetado por inmueble. | F23: Usuario con accesos (Arturo Pérez) | G23: S10 | H23: 14 | I23: 0 | J23: 0 | K23: 14 | L23: ='ESC-18'!J3 | M23: ='ESC-18'!J4 | N23: ='ESC-18'!J5 | O23: =IF(H23=0,"Por definir",IF(N23=1,"✅ 100%",IF(L23=0,"Sin probar","En ciclo"))) | Q23: =COUNTIFS(Hallazgos!$B:$B,A23,Hallazgos!$M:$M,"<>Cerrado",Hallazgos!$A:$A,"<>")
A24: ESC-19 | B24: Crear pedidos de fechas pasadas | C24: Escenario 19 | D24: Pedidos / Asignaciones | E24: Validar pedidos con fechas pasadas y el bloqueo por conflicto de asignación. | F24: — | G24: S06 | H24: 10 | I24: 4 | J24: 6 | K24: 0 | L24: ='ESC-19'!J3 | M24: ='ESC-19'!J4 | N24: ='ESC-19'!J5 | O24: =IF(H24=0,"Por definir",IF(N24=1,"✅ 100%",IF(L24=0,"Sin probar","En ciclo"))) | Q24: =COUNTIFS(Hallazgos!$B:$B,A24,Hallazgos!$M:$M,"<>Cerrado",Hallazgos!$A:$A,"<>")
A25: ESC-20 | B25: Relación de contacto-cliente | C25: Escenario 20 | D25: Pedidos | E25: Validar el alta de contactos y su relación con el cliente. | F25: Usuario de Axel | G25: S06 | H25: 8 | I25: 0 | J25: 0 | K25: 8 | L25: ='ESC-20'!J3 | M25: ='ESC-20'!J4 | N25: ='ESC-20'!J5 | O25: =IF(H25=0,"Por definir",IF(N25=1,"✅ 100%",IF(L25=0,"Sin probar","En ciclo"))) | Q25: =COUNTIFS(Hallazgos!$B:$B,A25,Hallazgos!$M:$M,"<>Cerrado",Hallazgos!$A:$A,"<>")
A26: ESC-21 | B26: Validar funcionalidad pantalla interna de reservaciones (Igual a la actual) | C26: Escenario 21 | D26: Reservaciones | E26: Validar la pantalla interna de reservaciones con paridad funcional respecto al legado. | F26: — | G26: S11 | H26: 22 | I26: 0 | J26: 0 | K26: 22 | L26: ='ESC-21'!J3 | M26: ='ESC-21'!J4 | N26: ='ESC-21'!J5 | O26: =IF(H26=0,"Por definir",IF(N26=1,"✅ 100%",IF(L26=0,"Sin probar","En ciclo"))) | Q26: =COUNTIFS(Hallazgos!$B:$B,A26,Hallazgos!$M:$M,"<>Cerrado",Hallazgos!$A:$A,"<>") | R26: El árbol esperado está como imagen en el archivo original.
A27: ESC-22 | B27: Captura de lista manual de asistencia | C27: Escenario 22 | D27: Nómina | E27: Validar la lista manual de asistencia y el cálculo de pagos honorarios (asistencia, falta, retardo) con valores exactos. | F27: Pedido pasado con 10 empleados asignados (forzada) | G27: S13 | H27: 67 | I27: 2 | J27: 0 | K27: 65 | L27: ='ESC-22'!J3 | M27: ='ESC-22'!J4 | N27: ='ESC-22'!J5 | O27: =IF(H27=0,"Por definir",IF(N27=1,"✅ 100%",IF(L27=0,"Sin probar","En ciclo"))) | Q27: =COUNTIFS(Hallazgos!$B:$B,A27,Hallazgos!$M:$M,"<>Cerrado",Hallazgos!$A:$A,"<>") | R27: Combinaciones con 'Penalización Retardo/Falta' mencionadas pero sin pasos.
A28: ESC-23 | B28: Extras | C28: Escenario 23 | D28: Nómina | E28: Validar extras: captura, autorización por perfil, aprobación masiva e impacto en el pago. | F28: ESC-22 | G28: S13 | H28: 17 | I28: 0 | J28: 0 | K28: 17 | L28: ='ESC-23'!J3 | M28: ='ESC-23'!J4 | N28: ='ESC-23'!J5 | O28: =IF(H28=0,"Por definir",IF(N28=1,"✅ 100%",IF(L28=0,"Sin probar","En ciclo"))) | Q28: =COUNTIFS(Hallazgos!$B:$B,A28,Hallazgos!$M:$M,"<>Cerrado",Hallazgos!$A:$A,"<>")
A29: ESC-24 | B29: Dispersión de nómina y Lista de Precauciones | C29: Escenario 24 | D29: Nómina | E29: Validar el cierre de nómina: lista de precauciones y archivo de dispersión. | F29: ESC-22, ESC-23 | G29: S13 | H29: 10 | I29: 0 | J29: 0 | K29: 10 | L29: ='ESC-24'!J3 | M29: ='ESC-24'!J4 | N29: ='ESC-24'!J5 | O29: =IF(H29=0,"Por definir",IF(N29=1,"✅ 100%",IF(L29=0,"Sin probar","En ciclo"))) | Q29: =COUNTIFS(Hallazgos!$B:$B,A29,Hallazgos!$M:$M,"<>Cerrado",Hallazgos!$A:$A,"<>")
A30: ESC-25 | B30: Asignación de folio para empleados con Honorarios Normales | C30: Escenario 25 | D30: Nómina | E30: Validar la asignación de folio fiscal para honorarios normales y su efecto en el importe. | F30: — | G30: S14 | H30: 17 | I30: 0 | J30: 0 | K30: 17 | L30: ='ESC-25'!J3 | M30: ='ESC-25'!J4 | N30: ='ESC-25'!J5 | O30: =IF(H30=0,"Por definir",IF(N30=1,"✅ 100%",IF(L30=0,"Sin probar","En ciclo"))) | Q30: =COUNTIFS(Hallazgos!$B:$B,A30,Hallazgos!$M:$M,"<>Cerrado",Hallazgos!$A:$A,"<>")
A31: ESC-26 | B31: Pedidos de runners para validar los sueldos | C31: Escenario 26 | D31: Nómina | E31: Validar el sueldo de runners por fase y sus impuestos (IVA, RIVA, RISR). | F31: — | G31: S14 | H31: 34 | I31: 0 | J31: 0 | K31: 34 | L31: ='ESC-26'!J3 | M31: ='ESC-26'!J4 | N31: ='ESC-26'!J5 | O31: =IF(H31=0,"Por definir",IF(N31=1,"✅ 100%",IF(L31=0,"Sin probar","En ciclo"))) | Q31: =COUNTIFS(Hallazgos!$B:$B,A31,Hallazgos!$M:$M,"<>Cerrado",Hallazgos!$A:$A,"<>")
A32: ESC-27 | B32: Facturación | C32: Escenario 28 (numeración duplicada) | D32: Facturación | E32: Validar la generación de facturas: folios, partidas, agrupación de rubros y txt a SAP. | F32: ESC-22 | G32: S15 | H32: 16 | I32: 0 | J32: 0 | K32: 16 | L32: ='ESC-27'!J3 | M32: ='ESC-27'!J4 | N32: ='ESC-27'!J5 | O32: =IF(H32=0,"Por definir",IF(N32=1,"✅ 100%",IF(L32=0,"Sin probar","En ciclo"))) | Q32: =COUNTIFS(Hallazgos!$B:$B,A32,Hallazgos!$M:$M,"<>Cerrado",Hallazgos!$A:$A,"<>") | R32: La lista de campos del paso 6 está como imagen en el archivo original.
A33: ESC-28 | B33: Validar que en el txt sólo se generan facturas (Y no servicios internos) | C33: Escenario 28 (numeración duplicada) | D33: Facturación | E33: Validar que los servicios internos no generan txt ni consumen folio consecutivo. | F33: ESC-26 | G33: S15 | H33: 5 | I33: 0 | J33: 0 | K33: 5 | L33: ='ESC-28'!J3 | M33: ='ESC-28'!J4 | N33: ='ESC-28'!J5 | O33: =IF(H33=0,"Por definir",IF(N33=1,"✅ 100%",IF(L33=0,"Sin probar","En ciclo"))) | Q33: =COUNTIFS(Hallazgos!$B:$B,A33,Hallazgos!$M:$M,"<>Cerrado",Hallazgos!$A:$A,"<>")
A34: ESC-29 | B34: Prorrateo de sueldos matriciales | C34: Escenario 29 | D34: Nómina | E34: Validar el prorrateo de sueldo matricial entre varios detalles (100-50-50 repartido). | F34: — | G34: S12 | H34: 8 | I34: 0 | J34: 0 | K34: 8 | L34: ='ESC-29'!J3 | M34: ='ESC-29'!J4 | N34: ='ESC-29'!J5 | O34: =IF(H34=0,"Por definir",IF(N34=1,"✅ 100%",IF(L34=0,"Sin probar","En ciclo"))) | Q34: =COUNTIFS(Hallazgos!$B:$B,A34,Hallazgos!$M:$M,"<>Cerrado",Hallazgos!$A:$A,"<>")
A35: ESC-30 | B35: Validación de Visibilidad por sucursal/puesto | C35: — (nota al pie) | D35: Reservaciones | E35: Validación de visibilidad por sucursal/puesto. | F35: — | G35: S11 | H35: 0 | I35: 0 | J35: 0 | K35: 0 | L35: ='ESC-30'!J3 | M35: ='ESC-30'!J4 | N35: ='ESC-30'!J5 | O35: =IF(H35=0,"Por definir",IF(N35=1,"✅ 100%",IF(L35=0,"Sin probar","En ciclo"))) | Q35: =COUNTIFS(Hallazgos!$B:$B,A35,Hallazgos!$M:$M,"<>Cerrado",Hallazgos!$A:$A,"<>") | R35: Sin pasos en el archivo original.
A36: ESC-31 | B36: Justificación de Faltas (Validar que el porcentaje de asistencia se modifica) | C36: — (nota al pie) | D36: Nómina | E36: Justificación de faltas (validar que el porcentaje de asistencia se modifica). | F36: — | G36: S13 | H36: 0 | I36: 0 | J36: 0 | K36: 0 | L36: ='ESC-31'!J3 | M36: ='ESC-31'!J4 | N36: ='ESC-31'!J5 | O36: =IF(H36=0,"Por definir",IF(N36=1,"✅ 100%",IF(L36=0,"Sin probar","En ciclo"))) | Q36: =COUNTIFS(Hallazgos!$B:$B,A36,Hallazgos!$M:$M,"<>Cerrado",Hallazgos!$A:$A,"<>") | R36: Sin pasos en el archivo original.
A38: TOTAL | H38: =SUM(H5:H36) | I38: =SUM(I5:I36) | J38: =SUM(J5:J36) | K38: =SUM(K5:K36) | L38: =SUM(L5:L36) | M38: =SUM(M5:M36) | N38: =IF(H38=0,0,M38/H38) | Q38: =SUM(Q5:Q36)

Sheet Sesiones
A1: Sesiones de Claude Code — cada sesión cubre un escenario o un grupo que comparte datos
A3: Sesión | B3: Escenarios | C3: Tema | D3: Pasos | E3: Por qué juntos
A4: S01 | B4: ESC-01 | C4: Pedido Seguridad básico | D4: 25 | E4: Base de todos los escenarios de pedidos.
A5: S02 | B5: ESC-02 | C5: PRG con complejidad | D5: 26 | E5: Staff, bloques y presupuesto.
A6: S03 | B6: ESC-03 | C6: PRG por fases | D6: 32 | E6: Múltiples detalles por fase.
A7: S04 | B7: ESC-04 | C7: Pedido masivo Azteca | D7: 106 | E7: Volumen; buen candidato a parametrizar.
A8: S05 | B8: ESC-05 | C8: Seriados | D8: 48 | E8: Requiere confirmación de bloque en portal.
A9: S06 | B9: ESC-06, ESC-07, ESC-17B, ESC-19, ESC-20 | C9: Reglas de pedido | D9: 35 | E9: Escenarios cortos e independientes del módulo de pedidos.
A10: S07 | B10: ESC-08, ESC-09, ESC-11 | C10: Elegibilidad del empleado | D10: 27 | E10: Plaza, certeza valor y puesto vigente.
A11: S08 | B11: ESC-10, ESC-12, ESC-15 | C11: Asignación y preasignación | D11: 28 | E11: Reglas de asignación forzada y preasignada.
A12: S09 | B12: ESC-13 | C12: Cancelaciones | D12: 29 | E12: Escenario largo con varios empleados en portal.
A13: S10 | B13: ESC-16, ESC-18 | C13: Restricciones de asignación | D13: 31 | E13: Certeza en reducción y lista negra.
A14: S11 | B14: ESC-21, ESC-30 | C14: Reservaciones internas | D14: 22 | E14: Paridad con legado y visibilidad.
A15: S12 | B15: ESC-14, ESC-17A, ESC-29 | C15: Sueldos matriciales | D15: 28 | E15: Mismo cálculo de complejidad y prorrateo.
... A18: S15 | B18: ESC-27, ESC-28 | C18: Facturación | D18: 21 | E18: Dependen de ESC-22 y ESC-26.

Sheet Hallazgos
A1: ID | B1: Escenario | C1: Paso # | D1: Corrida detectado | E1: Clasificación | F1: Severidad | G1: Descripción | H1: Evidencia | I1: Causa raíz | J1: Decisión negocio | K1: Corregido (commit) | L1: Verificado en corrida | M1: Estado
A2: H-001 | B2: ESC-01 | C2: 3 | D2: R1 | E2: BUG | F2: Media | G2: Ejemplo — Contacto vacío en la ficha del pedido | H2: corridas/R1/evidencias/ESC-01/P10_despues.png | I2: Ficha lee contacto_nombre; el formulario guarda contacto_id | J2: N/A | K2: abc1234 | L2: R2 | M2: Cerrado
A3: H-002 | B3: ESC-02 | C3: 7-8 | D3: R1 | E3: CAMBIO_NOMENCLATURA | G3: "Tipo de movimiento" real tiene 3 valores (Orden de servicio / Pedido facturable a cliente / Servicio interno); el caso esperaba 2 ("Pedido"/"Servicio Interno") y un campo "Facturable" editable separado que no existe (va embebido en el texto de la opcion). | H3: Tests/corridas/2026-10-10_R1_ESC-02/bitacora.jsonl (pasos 7-8); resumen_ejecucion.md | I3: Nomenclatura de catalogo/UI, no es un defecto de codigo. | J3: Pendiente | M3: Abierto
A4: H-003 | B4: ESC-02 | C4: 13-14 | D4: R1 | E4: CAMBIO_NOMENCLATURA | G4: tc_tipos_personal no usa los textos "Staff"/"Operativo". Usa clave freelance/interno/staff con descripciones "Personal freelance / eventual" / "Personal interno de oficina" / "Personal de planta". La clave staff SI implementa correctamente el gating de negocio (Staff solo visible si el pedido tiene complejidad) -- verificado releyendo codigo y reprobando en vivo tras un primer intento con sustituto incorrecto. | H4: Tests/corridas/2026-10-10_R1_ESC-02/bitacora.jsonl (pasos 13-14); verificacion directa del combo | I4: Nomenclatura de catalogo (tc_tipos_personal.descripcion), no de codigo. | J4: Pendiente: evaluar renombrar descripciones a "Staff"/"Operativo"/"Interno" | M4: Abierto
A5: H-004 | B5: ESC-02 | C5: 13 | D5: R1 | E5: BUG | F5: Baja | G5: tc_tipos_personal tiene 9 filas para solo 3 claves reales (freelance/interno/staff cada una triplicada con IDs distintos). La UI de alta de detalle solo mostro 3 opciones visibles en esta prueba; de cualquier forma la tabla en BD tiene filas redundantes. | H5: Consulta SQL directa a tc_tipos_personal (9 filas, 3 claves) | I5: Dato duplicado en seed/migracion; causa raiz en codigo no investigada (fuera de alcance de esta sesion). | J5: Pendiente: aprobar limpieza (dejar 1 fila por clave) | M5: Abierto
A6: H-005 | B6: ESC-02 | C6: 15-26 | D6: R1 | E6: GAP_MIGRACION | F6: Alta | G6: Ningun puesto matricial de la UN PRG tiene fila en tp_sueldos_matriciales (0 de 6 puestos PRG preexistentes, y tampoco los 2 insertados para esta prueba -- Asistente Operador PRG y Asistente Aux A PRG). Esto deja VACIO el combo de Producto al elegir Tipo de Personal=Staff para cualquier pedido de PRG, bloqueando el alta de todo el bloque de personal Staff de esa unidad de negocio. | H6: SQL (0 filas); capturas del combo vacio; Tests/corridas/2026-10-10_R1_ESC-02/bitacora.jsonl | I6: Migracion de datos incompleta: el legado real (Ocesa03_j_m.accdb) tiene 171 productos reales de PRG y puestos matriciales confirmados, pero el archivo fuente de tarifas (Catalogos Sueldos Matriciales.xlsx, citado en CLAUDE.md migraciones 022/031) no esta presente en este repo para poder sembrar tarifas reales. | J6: Pendiente: conseguir/aprobar fuente real de tarifas matriciales de PRG para poder sembrar tp_sueldos_matriciales | M6: Abierto
A7: H-006 | B7: ESC-02 | C7: colateral | D7: R1 | E7: BUG | F7: Media | G7: Las pantallas "Pedidos y sitios" y "Arbol de reservaciones" no muestran pedidos con fecha_evento antigua (confirmado invisible: pedido #199, fecha_evento=2018-09-01) pese a existir en BD -- aparente corte/limite de carga sin paginacion (se corta alrededor de 2018-09-21 hacia atras, aunque la BD tiene 199+ pedidos). | H7: Tests/corridas/2026-10-10_R1_ESC-02/bitacora.jsonl (paso 0, intentos 1-2); prueba de control con folio 36 (si se encontro) | I7: No investigada en codigo (fuera de alcance de esta sesion de QA). | J7: Pendiente: priorizar investigacion / agregar paginacion a la lista | M7: Abierto

Sheet Instrucciones
A1: CICLO POR SESIÓN
A2: 1. Probar (R1) | B2: qa-tester ejecuta los escenarios de la sesión y llena 'R1 Resultado' y 'R1 Hallazgo / Obs.' con evidencia.
A3: 2. Analizar | B3: qa-analista registra cada resultado distinto de CUMPLE en 'Hallazgos' con ID H-xxx y lo referencia en la columna de observación.
A4: 3. Decidir | B4: Negocio resuelve DISCREPANCIA_NEGOCIO, CAMBIO_NOMENCLATURA y CASO_AMBIGUO en la columna 'Decisión negocio'.
A5: 4. Corregir | B5: qa-corrector corrige solo hallazgos 'Aprobado corregir', un commit por hallazgo; estado → 'Por verificar'.
A6: 5. Re-probar (R2, R3…) | B6: Se re-ejecuta el escenario completo en la siguiente columna Rn. Hallazgos verificados → 'Cerrado'.
A7: 6. Cerrar | B7: El escenario se cierra cuando Control muestra '✅ 100%' y no tiene hallazgos abiertos.
A9: RESULTADO
A10: CUMPLE | B10: Coincide con el esperado, con evidencia.
A11: NO CUMPLE | B11: No coincide con el esperado.
A12: PARCIAL | B12: Existe la funcionalidad pero el dato o comportamiento difiere.
A13: NO EJECUTABLE | B13: No se puede probar (datos, catálogo, precondición).
A14: VERIFICAR | B14: Ejecutado sin evidencia o con juicio a confirmar.
A15: PENDIENTE | B15: No ejecutado.
A17: COMPARATIVO (calculado)
A18: Mejora / Mejora parcial | B18: Fallaba en legado y ahora cumple (total o parcialmente).
A19: Regresión | B19: Cumplía en legado y ahora falla.
A20: Falla nueva | B20: No se ejecutó en legado y falla ahora.
A21: Sigue fallando | B21: Fallaba en legado y sigue fallando.
A22: Se mantiene | B22: Mismo resultado que en legado.
A24: COLORES
A25: Gris | B25: Datos del legado: no editar.
A26: Azul | B26: Columnas del ciclo Claude Code: editables.
A27: Naranja | B27: Problema de calidad del caso: resolver antes de ejecutar ese paso.
A28: Negritas | B28: Fórmulas (Último resultado, Comparativo, resúmenes): no editar.
A30: REGLA | B30: Nunca se edita la descripción ni el resultado esperado. Si negocio cambia un esperado, se anota en Hallazgos como CASO_AMBIGUO con la decisión.

Sheet ESC-01
A1: ESC-01 — Pedido para Metropólitan (Seguridad) - Sin Cancelación
A2: Núm. original | B2: Escenario 1 | I2: Pasos | J2: =COUNT(A13:A38)
A3: Módulo | B3: Pedidos | I3: Ejecutados (último) | J3: =COUNTIF(O13:O38,"?*")
A4: Objetivo (propuesto, validar) | B4: Validar el alta completa de un pedido de Seguridad sin cancelación y su detalle, hasta la cancelación del pedido. | I4: CUMPLE (último) | J4: =COUNTIF(O13:O38,"CUMPLE")
A5: Funcionalidades | B5: Alta de pedido · contactos por cliente · PEP y sociedad pagadora · tipo de movimiento · estatus · catálogo por UN · jornada por turno · validación de fechas · matriz · acciones del detalle · cancelación | I5: % cumplimiento | J5: =IF(J2=0,0,J4/J2)
A6: Dependencias / datos | B6: —
A7: Sesión sugerida | B7: S01
A8: ⚠ Calidad del caso | B8: Paso 13: la descripción (prerellenos) y el esperado (productos de Seguridad) no corresponden.
A9: Notas originales | B9: —
F11: CORRIDA LEGADO (HUMANOS) | I11: CICLO CLAUDE CODE: probar → corregir → re-probar
A12: # | B12: Paso orig. | C12: Descripción | D12: Resultado esperado | E12: ⚠ Calidad | F12: Legado: Resultado | G12: Legado: Observación | H12: Legado: Corrección | I12: R1 Resultado | J12: R1 Hallazgo / Obs. | K12: R2 Resultado | L12: R2 Hallazgo / Obs. | M12: R3 Resultado | N12: R3 Hallazgo / Obs. | O12: Último resultado | P12: Comparativo
A13: 1 | B13: 1 | C13: Crear un nuevo pedido | F13: Cumple | O13: =IF(M13<>"",M13,IF(K13<>"",K13,IF(I13<>"",I13,""))) | P13: =IF(O13="","",IF(O13="PENDIENTE","Pendiente",IF(O13="NO EJECUTABLE","No ejecutable",IF(O13="VERIFICAR","Por verificar",IF(AND(F13="No cumple",O13="CUMPLE"),"Mejora",IF(AND(F13="No cumple",O13="PARCIAL"),"Mejora parcial",IF(AND(OR(F13="Cumple",F13="Sin ejecutar"),OR(O13="NO CUMPLE",O13="PARCIAL")),IF(F13="Cumple","Regresión","Falla nueva"),IF(AND(F13="No cumple",O13="NO CUMPLE"),"Sigue fallando","Se mantiene"))))))))
A14: 2 | B14: 2 | C14: Seleccionar cliente Ocesa | F14: Cumple | O14: =IF(M14<>"",M14,IF(K14<>"",K14,IF(I14<>"",I14,""))) | P14: =IF(O14="","",IF(O14="PENDIENTE","Pendiente",IF(O14="NO EJECUTABLE","No ejecutable",IF(O14="VERIFICAR","Por verificar",IF(AND(F14="No cumple",O14="CUMPLE"),"Mejora",IF(AND(F14="No cumple",O14="PARCIAL"),"Mejora parcial",IF(AND(OR(F14="Cumple",F14="Sin ejecutar"),OR(O14="NO CUMPLE",O14="PARCIAL")),IF(F14="Cumple","Regresión","Falla nueva"),IF(AND(F14="No cumple",O14="NO CUMPLE"),"Sigue fallando","Se mantiene"))))))))
A15: 3 | B15: 3 | C15: Validar lista de contactos | D15: Los contactos mostrados deben pertenecer al cliente Ocesa | F15: Cumple | O15: =IF(M15<>"",M15,IF(K15<>"",K15,IF(I15<>"",I15,""))) | P15: =IF(O15="","",IF(O15="PENDIENTE","Pendiente",IF(O15="NO EJECUTABLE","No ejecutable",IF(O15="VERIFICAR","Por verificar",IF(AND(F15="No cumple",O15="CUMPLE"),"Mejora",IF(AND(F15="No cumple",O15="PARCIAL"),"Mejora parcial",IF(AND(OR(F15="Cumple",F15="Sin ejecutar"),OR(O15="NO CUMPLE",O15="PARCIAL")),IF(F15="Cumple","Regresión","Falla nueva"),IF(AND(F15="No cumple",O15="NO CUMPLE"),"Sigue fallando","Se mantiene"))))))))
A16: 4 | B16: 4 | C16: Seleccionar un evento | F16: Cumple | O16: =IF(M16<>"",M16,IF(K16<>"",K16,IF(I16<>"",I16,""))) | P16: =IF(O16="","",IF(O16="PENDIENTE","Pendiente",IF(O16="NO EJECUTABLE","No ejecutable",IF(O16="VERIFICAR","Por verificar",IF(AND(F16="No cumple",O16="CUMPLE"),"Mejora",IF(AND(F16="No cumple",O16="PARCIAL"),"Mejora parcial",IF(AND(OR(F16="Cumple",F16="Sin ejecutar"),OR(O16="NO CUMPLE",O16="PARCIAL")),IF(F16="Cumple","Regresión","Falla nueva"),IF(AND(F16="No cumple",O16="NO CUMPLE"),"Sigue fallando","Se mantiene"))))))))
A17: 5 | B17: 5 | C17: Seleccionar UN Seguridad | D17: El sistema despliega los PEPS de la UN de seguridad, y la sociedad pagadora (en este caso Lobo) | F17: No cumple | G17: Antes de seleccionar la UN la sociedad pagadora está por default con ID 10 | H17: Corregido | O17: =IF(M17<>"",M17,IF(K17<>"",K17,IF(I17<>"",I17,""))) | P17: =IF(O17="","",IF(O17="PENDIENTE","Pendiente",IF(O17="NO EJECUTABLE","No ejecutable",IF(O17="VERIFICAR","Por verificar",IF(AND(F17="No cumple",O17="CUMPLE"),"Mejora",IF(AND(F17="No cumple",O17="PARCIAL"),"Mejora parcial",IF(AND(OR(F17="Cumple",F17="Sin ejecutar"),OR(O17="NO CUMPLE",O17="PARCIAL")),IF(F17="Cumple","Regresión","Falla nueva"),IF(AND(F17="No cumple",O17="NO CUMPLE"),"Sigue fallando","Se mantiene"))))))))
A18: 6 | B18: 6 | C18: Seleccionar el PEPS asociado a la UN | D18: El sistema me muestra el nombre y la dirección del inmueble | F18: Cumple | O18: =IF(M18<>"",M18,IF(K18<>"",K18,IF(I18<>"",I18,""))) | P18: =IF(O18="","",IF(O18="PENDIENTE","Pendiente",IF(O18="NO EJECUTABLE","No ejecutable",IF(O18="VERIFICAR","Por verificar",IF(AND(F18="No cumple",O18="CUMPLE"),"Mejora",IF(AND(F18="No cumple",O18="PARCIAL"),"Mejora parcial",IF(AND(OR(F18="Cumple",F18="Sin ejecutar"),OR(O18="NO CUMPLE",O18="PARCIAL")),IF(F18="Cumple","Regresión","Falla nueva"),IF(AND(F18="No cumple",O18="NO CUMPLE"),"Sigue fallando","Se mantiene"))))))))
A19: 7 | B19: 7 | C19: Validar tipo de movimiento | D19: El sistema debe mostrar dos tipos de movimiento (Pedido y Servicio Interno) | F19: No cumple | G19: Únicamnete muestra "pedido" | H19: Corregido / Listo | O19: =IF(M19<>"",M19,IF(K19<>"",K19,IF(I19<>"",I19,""))) | P19: =IF(O19="","",IF(O19="PENDIENTE","Pendiente",IF(O19="NO EJECUTABLE","No ejecutable",IF(O19="VERIFICAR","Por verificar",IF(AND(F19="No cumple",O19="CUMPLE"),"Mejora",IF(AND(F19="No cumple",O19="PARCIAL"),"Mejora parcial",IF(AND(OR(F19="Cumple",F19="Sin ejecutar"),OR(O19="NO CUMPLE",O19="PARCIAL")),IF(F19="Cumple","Regresión","Falla nueva"),IF(AND(F19="No cumple",O19="NO CUMPLE"),"Sigue fallando","Se mantiene"))))))))
A20: 8 | B20: 8 | C20: Seleccionar Tipo de movimiento Pedido | D20: EL tipo Pedido se factura (validar posteriormente) | F20: Cumple | O20: =IF(M20<>"",M20,IF(K20<>"",K20,IF(I20<>"",I20,""))) | P20: =IF(O20="","",IF(O20="PENDIENTE","Pendiente",IF(O20="NO EJECUTABLE","No ejecutable",IF(O20="VERIFICAR","Por verificar",IF(AND(F20="No cumple",O20="CUMPLE"),"Mejora",IF(AND(F20="No cumple",O20="PARCIAL"),"Mejora parcial",IF(AND(OR(F20="Cumple",F20="Sin ejecutar"),OR(O20="NO CUMPLE",O20="PARCIAL")),IF(F20="Cumple","Regresión","Falla nueva"),IF(AND(F20="No cumple",O20="NO CUMPLE"),"Sigue fallando","Se mantiene"))))))))
A21: 9 | B21: 9 | C21: En el campo Permitir Cancelar, seleccionar NO | F21: Cumple | O21: =IF(M21<>"",M21,IF(K21<>"",K21,IF(I21<>"",I21,""))) | P21: =IF(O21="","",IF(O21="PENDIENTE","Pendiente",IF(O21="NO EJECUTABLE","No ejecutable",IF(O21="VERIFICAR","Por verificar",IF(AND(F21="No cumple",O21="CUMPLE"),"Mejora",IF(AND(F21="No cumple",O21="PARCIAL"),"Mejora parcial",IF(AND(OR(F21="Cumple",F21="Sin ejecutar"),OR(O21="NO CUMPLE",O21="PARCIAL")),IF(F21="Cumple","Regresión","Falla nueva"),IF(AND(F21="No cumple",O21="NO CUMPLE"),"Sigue fallando","Se mantiene"))))))))
A22: 10 | B22: 10 | C22: Pulsar Aceptar | D22: El sistema genera un número consecutivo de pedido. | F22: Cumple | O22: =IF(M22<>"",M22,IF(K22<>"",K22,IF(I22<>"",I22,""))) | P22: =IF(O22="","",IF(O22="PENDIENTE","Pendiente",IF(O22="NO EJECUTABLE","No ejecutable",IF(O22="VERIFICAR","Por verificar",IF(AND(F22="No cumple",O22="CUMPLE"),"Mejora",IF(AND(F22="No cumple",O22="PARCIAL"),"Mejora parcial",IF(AND(OR(F22="Cumple",F22="Sin ejecutar"),OR(O22="NO CUMPLE",O22="PARCIAL")),IF(F22="Cumple","Regresión","Falla nueva"),IF(AND(F22="No cumple",O22="NO CUMPLE"),"Sigue fallando","Se mantiene"))))))))
C23: Pedido Detalle
A24: 11 | B24: 11 | C24: Validar Estatus del Pedido | D24: Debe estar en estado Normal | F24: No cumple | G24: El estatus del pedido aparece como: NINGUNO | H24: Corregido | O24: =IF(M24<>"",M24,IF(K24<>"",K24,IF(I24<>"",I24,""))) | P24: =IF(O24="","",IF(O24="PENDIENTE","Pendiente",IF(O24="NO EJECUTABLE","No ejecutable",IF(O24="VERIFICAR","Por verificar",IF(AND(F24="No cumple",O24="CUMPLE"),"Mejora",IF(AND(F24="No cumple",O24="PARCIAL"),"Mejora parcial",IF(AND(OR(F24="Cumple",F24="Sin ejecutar"),OR(O24="NO CUMPLE",O24="PARCIAL")),IF(F24="Cumple","Regresión","Falla nueva"),IF(AND(F24="No cumple",O24="NO CUMPLE"),"Sigue fallando","Se mantiene"))))))))
A25: 12 | B25: 12 | C25: Seleccionar Tipo de Personal Operativo | D25: Validar que sólo se muestre Operativo por default ser un pedido de seguridad | F25: Cumple | O25: =IF(M25<>"",M25,IF(K25<>"",K25,IF(I25<>"",I25,""))) | P25: =IF(O25="","",IF(O25="PENDIENTE","Pendiente",IF(O25="NO EJECUTABLE","No ejecutable",IF(O25="VERIFICAR","Por verificar",IF(AND(F25="No cumple",O25="CUMPLE"),"Mejora",IF(AND(F25="No cumple",O25="PARCIAL"),"Mejora parcial",IF(AND(OR(F25="Cumple",F25="Sin ejecutar"),OR(O25="NO CUMPLE",O25="PARCIAL")),IF(F25="Cumple","Regresión","Falla nueva"),IF(AND(F25="No cumple",O25="NO CUMPLE"),"Sigue fallando","Se mantiene"))))))))
A26: 13 | B26: 13 | C26: Validar que Tïtulo, Lugar de Cita, Facturable vienen prerellenos | D26: Validar que se muestran todos los productos de Seguridad | E26: Descripción y esperado no corresponden. | F26: No cumple | G26: Revisar filtros en el catálogo de productos para facilitar la consulta. El campo de facturable no viene prerelleno | H26: Corregido | O26: =IF(M26<>"",M26,IF(K26<>"",K26,IF(I26<>"",I26,""))) | P26: =IF(O26="","",IF(O26="PENDIENTE","Pendiente",IF(O26="NO EJECUTABLE","No ejecutable",IF(O26="VERIFICAR","Por verificar",IF(AND(F26="No cumple",O26="CUMPLE"),"Mejora",IF(AND(F26="No cumple",O26="PARCIAL"),"Mejora parcial",IF(AND(OR(F26="Cumple",F26="Sin ejecutar"),OR(O26="NO CUMPLE",O26="PARCIAL")),IF(F26="Cumple","Regresión","Falla nueva"),IF(AND(F26="No cumple",O26="NO CUMPLE"),"Sigue fallando","Se mantiene"))))))))
A27: 14 | B27: 14 | C27: Seleccionar Producto Seguridad-MA | F27: Cumple | O27: =IF(M27<>"",M27,IF(K27<>"",K27,IF(I27<>"",I27,""))) | P27: =IF(O27="","",IF(O27="PENDIENTE","Pendiente",IF(O27="NO EJECUTABLE","No ejecutable",IF(O27="VERIFICAR","Por verificar",IF(AND(F27="No cumple",O27="CUMPLE"),"Mejora",IF(AND(F27="No cumple",O27="PARCIAL"),"Mejora parcial",IF(AND(OR(F27="Cumple",F27="Sin ejecutar"),OR(O27="NO CUMPLE",O27="PARCIAL")),IF(F27="Cumple","Regresión","Falla nueva"),IF(AND(F27="No cumple",O27="NO CUMPLE"),"Sigue fallando","Se mantiene"))))))))
A28: 15 | B28: 15 | C28: Validar que el sistema muestra las horas por turno de ese producto | D28: Se muestra 1 turno por 8 horas | F28: No cumple | G28: No muestra la infromación | H28: Corregido / Listo | O28: =IF(M28<>"",M28,IF(K28<>"",K28,IF(I28<>"",I28,""))) | P28: =IF(O28="","",IF(O28="PENDIENTE","Pendiente",IF(O28="NO EJECUTABLE","No ejecutable",IF(O28="VERIFICAR","Por verificar",IF(AND(F28="No cumple",O28="CUMPLE"),"Mejora",IF(AND(F28="No cumple",O28="PARCIAL"),"Mejora parcial",IF(AND(OR(F28="Cumple",F28="Sin ejecutar"),OR(O28="NO CUMPLE",O28="PARCIAL")),IF(F28="Cumple","Regresión","Falla nueva"),IF(AND(F28="No cumple",O28="NO CUMPLE"),"Sigue fallando","Se mantiene"))))))))
A29: 16 | B29: 16 | C29: Poner Cantidad 2 y Turnos 3 | F29: Cumple | O29: =IF(M29<>"",M29,IF(K29<>"",K29,IF(I29<>"",I29,""))) | P29: =IF(O29="","",IF(O29="PENDIENTE","Pendiente",IF(O29="NO EJECUTABLE","No ejecutable",IF(O29="VERIFICAR","Por verificar",IF(AND(F29="No cumple",O29="CUMPLE"),"Mejora",IF(AND(F29="No cumple",O29="PARCIAL"),"Mejora parcial",IF(AND(OR(F29="Cumple",F29="Sin ejecutar"),OR(O29="NO CUMPLE",O29="PARCIAL")),IF(F29="Cumple","Regresión","Falla nueva"),IF(AND(F29="No cumple",O29="NO CUMPLE"),"Sigue fallando","Se mantiene"))))))))
A30: 17 | B30: 17 | C30: Seleccionar cualquier Fecha de Cita | F30: Cumple | O30: =IF(M30<>"",M30,IF(K30<>"",K30,IF(I30<>"",I30,""))) | P30: =IF(O30="","",IF(O30="PENDIENTE","Pendiente",IF(O30="NO EJECUTABLE","No ejecutable",IF(O30="VERIFICAR","Por verificar",IF(AND(F30="No cumple",O30="CUMPLE"),"Mejora",IF(AND(F30="No cumple",O30="PARCIAL"),"Mejora parcial",IF(AND(OR(F30="Cumple",F30="Sin ejecutar"),OR(O30="NO CUMPLE",O30="PARCIAL")),IF(F30="Cumple","Regresión","Falla nueva"),IF(AND(F30="No cumple",O30="NO CUMPLE"),"Sigue fallando","Se mantiene"))))))))
A31: 18 | B31: 18 | C31: Seleccionar una fecha de liberación posterior | D31: El sistema debe de mostrar una alerta por que no puede ser la fecha de liberación posterior a la fecha de cita | F31: Cumple | O31: =IF(M31<>"",M31,IF(K31<>"",K31,IF(I31<>"",I31,""))) | P31: =IF(O31="","",IF(O31="PENDIENTE","Pendiente",IF(O31="NO EJECUTABLE","No ejecutable",IF(O31="VERIFICAR","Por verificar",IF(AND(F31="No cumple",O31="CUMPLE"),"Mejora",IF(AND(F31="No cumple",O31="PARCIAL"),"Mejora parcial",IF(AND(OR(F31="Cumple",F31="Sin ejecutar"),OR(O31="NO CUMPLE",O31="PARCIAL")),IF(F31="Cumple","Regresión","Falla nueva"),IF(AND(F31="No cumple",O31="NO CUMPLE"),"Sigue fallando","Se mantiene"))))))))
A32: 19 | B32: 19 | C32: Seleccionar una fecha correcta de liberación | F32: Cumple | O32: =IF(M32<>"",M32,IF(K32<>"",K32,IF(I32<>"",I32,""))) | P32: =IF(O32="","",IF(O32="PENDIENTE","Pendiente",IF(O32="NO EJECUTABLE","No ejecutable",IF(O32="VERIFICAR","Por verificar",IF(AND(F32="No cumple",O32="CUMPLE"),"Mejora",IF(AND(F32="No cumple",O32="PARCIAL"),"Mejora parcial",IF(AND(OR(F32="Cumple",F32="Sin ejecutar"),OR(O32="NO CUMPLE",O32="PARCIAL")),IF(F32="Cumple","Regresión","Falla nueva"),IF(AND(F32="No cumple",O32="NO CUMPLE"),"Sigue fallando","Se mantiene"))))))))
A33: 20 | B33: 20 | C33: En presentación por producto, validar que sólo muentren las de la unidad de negocio | F33: Cumple | O33: =IF(M33<>"",M33,IF(K33<>"",K33,IF(I33<>"",I33,""))) | P33: =IF(O33="","",IF(O33="PENDIENTE","Pendiente",IF(O33="NO EJECUTABLE","No ejecutable",IF(O33="VERIFICAR","Por verificar",IF(AND(F33="No cumple",O33="CUMPLE"),"Mejora",IF(AND(F33="No cumple",O33="PARCIAL"),"Mejora parcial",IF(AND(OR(F33="Cumple",F33="Sin ejecutar"),OR(O33="NO CUMPLE",O33="PARCIAL")),IF(F33="Cumple","Regresión","Falla nueva"),IF(AND(F33="No cumple",O33="NO CUMPLE"),"Sigue fallando","Se mantiene"))))))))
A34: 21 | B34: 21 | C34: Completar con similares - Marcar SI | F34: Cumple | O34: =IF(M34<>"",M34,IF(K34<>"",K34,IF(I34<>"",I34,""))) | P34: =IF(O34="","",IF(O34="PENDIENTE","Pendiente",IF(O34="NO EJECUTABLE","No ejecutable",IF(O34="VERIFICAR","Por verificar",IF(AND(F34="No cumple",O34="CUMPLE"),"Mejora",IF(AND(F34="No cumple",O34="PARCIAL"),"Mejora parcial",IF(AND(OR(F34="Cumple",F34="Sin ejecutar"),OR(O34="NO CUMPLE",O34="PARCIAL")),IF(F34="Cumple","Regresión","Falla nueva"),IF(AND(F34="No cumple",O34="NO CUMPLE"),"Sigue fallando","Se mantiene"))))))))
A35: 22 | B35: 22 | C35: Agregar registro | D35: Validamos que se muestra la Matriz de información (Fecha, hora, productos, Turnos, Totales (personal y monto)) | F35: Cumple | G35: Revisar la validación de turnos por cantidad y si el nombre de producto está en la matriz en la parte de descripción | H35: EN PROCESO | O35: =IF(M35<>"",M35,IF(K35<>"",K35,IF(I35<>"",I35,""))) | P35: =IF(O35="","",IF(O35="PENDIENTE","Pendiente",IF(O35="NO EJECUTABLE","No ejecutable",IF(O35="VERIFICAR","Por verificar",IF(AND(F35="No cumple",O35="CUMPLE"),"Mejora",IF(AND(F35="No cumple",O35="PARCIAL"),"Mejora parcial",IF(AND(OR(F35="Cumple",F35="Sin ejecutar"),OR(O35="NO CUMPLE",O35="PARCIAL")),IF(F35="Cumple","Regresión","Falla nueva"),IF(AND(F35="No cumple",O35="NO CUMPLE"),"Sigue fallando","Se mantiene"))))))))
A36: 23 | B36: 23 | C36: Al posicionarse sobre el producto debe mostrar | D36: ID, Lugar de Cita, Fecha Cita, Fecha Fin Cita, Fecha Liberación, Completar con Similares, Cantidad Reservados, Cantidad Reservados Real, Cantidad Reservados con preasignación, Porcentaje Completo, Fase del Evento, Presentación | F36: No cumple | G36: Revisar que estén en las tres pestañas todos los conceptos mencioandos, algunos los encontré, otros no. | H36: EN PROCESO | O36: =IF(M36<>"",M36,IF(K36<>"",K36,IF(I36<>"",I36,""))) | P36: =IF(O36="","",IF(O36="PENDIENTE","Pendiente",IF(O36="NO EJECUTABLE","No ejecutable",IF(O36="VERIFICAR","Por verificar",IF(AND(F36="No cumple",O36="CUMPLE"),"Mejora",IF(AND(F36="No cumple",O36="PARCIAL"),"Mejora parcial",IF(AND(OR(F36="Cumple",F36="Sin ejecutar"),OR(O36="NO CUMPLE",O36="PARCIAL")),IF(F36="Cumple","Regresión","Falla nueva"),IF(AND(F36="No cumple",O36="NO CUMPLE"),"Sigue fallando","Se mantiene"))))))))
A37: 24 | B37: 24 | C37: En la flecha con los turnos debe mostrar | D37: Editar, Reservaciones, Cancelar y Liberar | F37: No cumple | G37: revisar punto una vez más con ayuda de Leo.. | H37: EN PROCESO | O37: =IF(M37<>"",M37,IF(K37<>"",K37,IF(I37<>"",I37,""))) | P37: =IF(O37="","",IF(O37="PENDIENTE","Pendiente",IF(O37="NO EJECUTABLE","No ejecutable",IF(O37="VERIFICAR","Por verificar",IF(AND(F37="No cumple",O37="CUMPLE"),"Mejora",IF(AND(F37="No cumple",O37="PARCIAL"),"Mejora parcial",IF(AND(OR(F37="Cumple",F37="Sin ejecutar"),OR(O37="NO CUMPLE",O37="PARCIAL")),IF(F37="Cumple","Regresión","Falla nueva"),IF(AND(F37="No cumple",O37="NO CUMPLE"),"Sigue fallando","Se mantiene"))))))))
A38: 25 | B38: 25 | C38: Pulsar sobre Cancelar Pedido | D38: Validar que el estatus pasa a estado Cancelado | F38: No cumple | G38: Se realizó correctamente la cancelación, sin emabrgo, nos mostro un error al querer regresar al menu de pedidos. Favor de revisar. | H38: Corregido | O38: =IF(M38<>"",M38,IF(K38<>"",K38,IF(I38<>"",I38,""))) | P38: =IF(O38="","",IF(O38="PENDIENTE","Pendiente",IF(O38="NO EJECUTABLE","No ejecutable",IF(O38="VERIFICAR","Por verificar",IF(AND(F38="No cumple",O38="CUMPLE"),"Mejora",IF(AND(F38="No cumple",O38="PARCIAL"),"Mejora parcial",IF(AND(OR(F38="Cumple",F38="Sin ejecutar"),OR(O38="NO CUMPLE",O38="PARCIAL")),IF(F38="Cumple","Regresión","Falla nueva"),IF(AND(F38="No cumple",O38="NO CUMPLE"),"Sigue fallando","Se mantiene"))))))))

Sheet ESC-02
A1: ESC-02 — Pedido PRG-Producción con complejidad y días show
A2: Núm. original | B2: Escenario 2 | I2: Pasos | J2: =COUNT(A13:A39)
A3: Módulo | B3: Pedidos | I3: Ejecutados (último) | J3: =COUNTIF(O13:O39,"?*")
A4: Objetivo (propuesto, validar) | B4: Validar un pedido PRG con complejidad y días de show: personal Staff, bloques por producto y presupuesto ligado a complejidad. | I4: CUMPLE (último) | J4: =COUNTIF(O13:O39,"CUMPLE")
A5: Funcionalidades | B5: Complejidad · duración en días de show · tipo de personal Staff · catálogo PRG · jornada · fase de evento · bloques · presupuesto día | I5: % cumplimiento | J5: =IF(J2=0,0,J4/J2)
A6: Dependencias / datos | B6: —
A7: Sesión sugerida | B7: S02
A8: ⚠ Calidad del caso | B8: Paso 5 esperado dice 'UN de seguridad' (copiado del Esc. 1). Paso 7 texto corrupto ('movi+E10:F10miento'). Paso 8 es Servicio Interno pero el esperado habla de Pedido. Paso 18: 'nos' probablemente es 'no'.
A9: Notas originales | B9: —
F11: CORRIDA LEGADO (HUMANOS) | I11: CICLO CLAUDE CODE: probar → corregir → re-probar
A12: # | B12: Paso orig. | C12: Descripción | D12: Resultado esperado | E12: ⚠ Calidad | F12: Legado: Resultado | G12: Legado: Observación | H12: Legado: Corrección | I12: R1 Resultado | J12: R1 Hallazgo / Obs. | K12: R2 Resultado | L12: R2 Hallazgo / Obs. | M12: R3 Resultado | N12: R3 Hallazgo / Obs. | O12: Último resultado | P12: Comparativo
A13: 1 | B13: 1 | C13: Crear un nuevo pedido | F13: Cumple | I13: CUMPLE | O13: =IF(M13<>"",M13,IF(K13<>"",K13,IF(I13<>"",I13,""))) | P13: =IF(O13="","",IF(O13="PENDIENTE","Pendiente",IF(O13="NO EJECUTABLE","No ejecutable",IF(O13="VERIFICAR","Por verificar",IF(AND(F13="No cumple",O13="CUMPLE"),"Mejora",IF(AND(F13="No cumple",O13="PARCIAL"),"Mejora parcial",IF(AND(OR(F13="Cumple",F13="Sin ejecutar"),OR(O13="NO CUMPLE",O13="PARCIAL")),IF(F13="Cumple","Regresión","Falla nueva"),IF(AND(F13="No cumple",O13="NO CUMPLE"),"Sigue fallando","Se mantiene"))))))))
A14: 2 | B14: 2 | C14: Seleccionar cliente Ocesa | F14: Cumple | I14: CUMPLE | O14: =IF(M14<>"",M14,IF(K14<>"",K14,IF(I14<>"",I14,""))) | P14: =IF(O14="","",IF(O14="PENDIENTE","Pendiente",IF(O14="NO EJECUTABLE","No ejecutable",IF(O14="VERIFICAR","Por verificar",IF(AND(F14="No cumple",O14="CUMPLE"),"Mejora",IF(AND(F14="No cumple",O14="PARCIAL"),"Mejora parcial",IF(AND(OR(F14="Cumple",F14="Sin ejecutar"),OR(O14="NO CUMPLE",O14="PARCIAL")),IF(F14="Cumple","Regresión","Falla nueva"),IF(AND(F14="No cumple",O14="NO CUMPLE"),"Sigue fallando","Se mantiene"))))))))
A15: 3 | B15: 3 | C15: Validar lista de contactos | D15: Los contactos mostrados deben pertenecer al cliente Ocesa | F15: Cumple | I15: CUMPLE | J15: Contacto unico verificado en BD (Laura Mendez Ruiz, tc_contactos_cliente) | O15: =IF(M15<>"",M15,IF(K15<>"",K15,IF(I15<>"",I15,""))) | P15: =IF(O15="","",IF(O15="PENDIENTE","Pendiente",IF(O15="NO EJECUTABLE","No ejecutable",IF(O15="VERIFICAR","Por verificar",IF(AND(F15="No cumple",O15="CUMPLE"),"Mejora",IF(AND(F15="No cumple",O15="PARCIAL"),"Mejora parcial",IF(AND(OR(F15="Cumple",F15="Sin ejecutar"),OR(O15="NO CUMPLE",O15="PARCIAL")),IF(F15="Cumple","Regresión","Falla nueva"),IF(AND(F15="No cumple",O15="NO CUMPLE"),"Sigue fallando","Se mantiene"))))))))
A16: 4 | B16: 4 | C16: Seleccionar un evento | F16: Cumple | I16: CUMPLE | J16: Titulo del pedido autocompleta desde el evento y es editable. Fecha del evento NO autocompleta (UX_MENOR); se capturo a mano la fecha real del evento. | O16: =IF(M16<>"",M16,IF(K16<>"",K16,IF(I16<>"",I16,""))) | P16: =IF(O16="","",IF(O16="PENDIENTE","Pendiente",IF(O16="NO EJECUTABLE","No ejecutable",IF(O16="VERIFICAR","Por verificar",IF(AND(F16="No cumple",O16="CUMPLE"),"Mejora",IF(AND(F16="No cumple",O16="PARCIAL"),"Mejora parcial",IF(AND(OR(F16="Cumple",F16="Sin ejecutar"),OR(O16="NO CUMPLE",O16="PARCIAL")),IF(F16="Cumple","Regresión","Falla nueva"),IF(AND(F16="No cumple",O16="NO CUMPLE"),"Sigue fallando","Se mantiene"))))))))
A17: 5 | B17: 5 | C17: Seleccionar UN PRG | D17: El sistema despliega los PEPS de la UN de seguridad, y la sociedad pagadora (en este caso Lobo) | E17: Esperado copiado ('UN de seguridad'). | F17: Cumple | I17: CUMPLE | J17: 9 PEPs reales de PRG mostrados correctamente. Sociedad pagadora no autocompleta (gap ya conocido en CLAUDE.md Sec.11, no es de este caso). | O17: =IF(M17<>"",M17,IF(K17<>"",K17,IF(I17<>"",I17,""))) | P17: =IF(O17="","",IF(O17="PENDIENTE","Pendiente",IF(O17="NO EJECUTABLE","No ejecutable",IF(O17="VERIFICAR","Por verificar",IF(AND(F17="No cumple",O17="CUMPLE"),"Mejora",IF(AND(F17="No cumple",O17="PARCIAL"),"Mejora parcial",IF(AND(OR(F17="Cumple",F17="Sin ejecutar"),OR(O17="NO CUMPLE",O17="PARCIAL")),IF(F17="Cumple","Regresión","Falla nueva"),IF(AND(F17="No cumple",O17="NO CUMPLE"),"Sigue fallando","Se mantiene"))))))))
A18: 6 | B18: 6 | C18: Seleccionar el PEPS asociado a la UN | D18: El sistema me muestra el nombre y la dirección del inmueble | F18: Cumple | I18: PARCIAL | J18: Sitio/Lugar de cita no autocompletan: los 9 PEPs de PRG no tienen sociedad propia ni lugar predeterminado en BD (dato, no codigo). | O18: =IF(M18<>"",M18,IF(K18<>"",K18,IF(I18<>"",I18,""))) | P18: =IF(O18="","",IF(O18="PENDIENTE","Pendiente",IF(O18="NO EJECUTABLE","No ejecutable",IF(O18="VERIFICAR","Por verificar",IF(AND(F18="No cumple",O18="CUMPLE"),"Mejora",IF(AND(F18="No cumple",O18="PARCIAL"),"Mejora parcial",IF(AND(OR(F18="Cumple",F18="Sin ejecutar"),OR(O18="NO CUMPLE",O18="PARCIAL")),IF(F18="Cumple","Regresión","Falla nueva"),IF(AND(F18="No cumple",O18="NO CUMPLE"),"Sigue fallando","Se mantiene"))))))))
A19: 7 | B19: 7 | C19: Validar tipo de movimiento | D19: El sistema debe mostrar dos tipos de movi+E10:F10miento (Pedido y Servicio Interno) | E19: Texto corrupto en el esperado. | F19: No cumple | G19: Únicamnete muestra "pedido" | H19: Corregido | I19: NO CUMPLE | J19: H-002: UI real muestra 3 tipos (Orden de servicio / Pedido facturable a cliente / Servicio interno); ninguno se llama "Pedido" literal. | O19: =IF(M19<>"",M19,IF(K19<>"",K19,IF(I19<>"",I19,""))) | P19: =IF(O19="","",IF(O19="PENDIENTE","Pendiente",IF(O19="NO EJECUTABLE","No ejecutable",IF(O19="VERIFICAR","Por verificar",IF(AND(F19="No cumple",O19="CUMPLE"),"Mejora",IF(AND(F19="No cumple",O19="PARCIAL"),"Mejora parcial",IF(AND(OR(F19="Cumple",F19="Sin ejecutar"),OR(O19="NO CUMPLE",O19="PARCIAL")),IF(F19="Cumple","Regresión","Falla nueva"),IF(AND(F19="No cumple",O19="NO CUMPLE"),"Sigue fallando","Se mantiene"))))))))
A20: 8 | B20: 8 | C20: Seleccionar Tipo de movimiento Servicio Interno | D20: EL tipo Pedido se factura (validar posteriormente) | E20: Servicio Interno con esperado de Pedido. | F20: No cumple | G20: Al no poder seleccionar el tipo de movimiento no sabemos si afecta en el procedimiento. Nos aparece que no es facturable, pero se puede cambiar. | H20: Corregido | I20: PARCIAL | J20: H-002: "Facturable" va embebido en el texto de la opcion elegida; no existe un campo separado editable. | O20: =IF(M20<>"",M20,IF(K20<>"",K20,IF(I20<>"",I20,""))) | P20: =IF(O20="","",IF(O20="PENDIENTE","Pendiente",IF(O20="NO EJECUTABLE","No ejecutable",IF(O20="VERIFICAR","Por verificar",IF(AND(F20="No cumple",O20="CUMPLE"),"Mejora",IF(AND(F20="No cumple",O20="PARCIAL"),"Mejora parcial",IF(AND(OR(F20="Cumple",F20="Sin ejecutar"),OR(O20="NO CUMPLE",O20="PARCIAL")),IF(F20="Cumple","Regresión","Falla nueva"),IF(AND(F20="No cumple",O20="NO CUMPLE"),"Sigue fallando","Se mantiene"))))))))
A21: 9 | B21: 9 | C21: Seleccionar Complejidad Foro Sol - 1 Día de Show | D21: Validar que el sistema sólo muestra las 6 complejidades del catálogo | F21: No cumple | G21: únicamnete muestra 3 opciones del foro sol, y dos son iguales. | H21: Corregido | I21: CUMPLE | J21: 6 complejidades reales confirmadas en combo, sin duplicados. | O21: =IF(M21<>"",M21,IF(K21<>"",K21,IF(I21<>"",I21,""))) | P21: =IF(O21="","",IF(O21="PENDIENTE","Pendiente",IF(O21="NO EJECUTABLE","No ejecutable",IF(O21="VERIFICAR","Por verificar",IF(AND(F21="No cumple",O21="CUMPLE"),"Mejora",IF(AND(F21="No cumple",O21="PARCIAL"),"Mejora parcial",IF(AND(OR(F21="Cumple",F21="Sin ejecutar"),OR(O21="NO CUMPLE",O21="PARCIAL")),IF(F21="Cumple","Regresión","Falla nueva"),IF(AND(F21="No cumple",O21="NO CUMPLE"),"Sigue fallando","Se mantiene"))))))))
A22: 10 | B22: 10 | C22: Indicar 1 día de show en el campo Duración del Evento | F22: Cumple | I22: CUMPLE | J22: Campo es compuesto (Tipo de duracion + Dias), no un unico "Duracion del Evento". Se uso Shows Sueltos + 1 dia. | O22: =IF(M22<>"",M22,IF(K22<>"",K22,IF(I22<>"",I22,""))) | P22: =IF(O22="","",IF(O22="PENDIENTE","Pendiente",IF(O22="NO EJECUTABLE","No ejecutable",IF(O22="VERIFICAR","Por verificar",IF(AND(F22="No cumple",O22="CUMPLE"),"Mejora",IF(AND(F22="No cumple",O22="PARCIAL"),"Mejora parcial",IF(AND(OR(F22="Cumple",F22="Sin ejecutar"),OR(O22="NO CUMPLE",O22="PARCIAL")),IF(F22="Cumple","Regresión","Falla nueva"),IF(AND(F22="No cumple",O22="NO CUMPLE"),"Sigue fallando","Se mantiene"))))))))
A23: 11 | B23: 11 | C23: En el campo Permitir Cancelar, seleccionar NO | F23: Cumple | I23: CUMPLE | J23: Click real en checkbox confirmado. | O23: =IF(M23<>"",M23,IF(K23<>"",K23,IF(I23<>"",I23,""))) | P23: =IF(O23="","",IF(O23="PENDIENTE","Pendiente",IF(O23="NO EJECUTABLE","No ejecutable",IF(O23="VERIFICAR","Por verificar",IF(AND(F23="No cumple",O23="CUMPLE"),"Mejora",IF(AND(F23="No cumple",O23="PARCIAL"),"Mejora parcial",IF(AND(OR(F23="Cumple",F23="Sin ejecutar"),OR(O23="NO CUMPLE",O23="PARCIAL")),IF(F23="Cumple","Regresión","Falla nueva"),IF(AND(F23="No cumple",O23="NO CUMPLE"),"Sigue fallando","Se mantiene"))))))))
A24: 12 | B24: 12 | C24: Pulsar Aceptar | D24: El sistema genera un número consecutivo de pedido. | F24: Cumple | I24: CUMPLE | J24: Precondicion critica VERIFICADA EN BD (pedido #200): tipo_complejidad_id, tipo_duracion_id, duracion_dias=1 y permitir_cancelaciones=false guardados correctamente. | O24: =IF(M24<>"",M24,IF(K24<>"",K24,IF(I24<>"",I24,""))) | P24: =IF(O24="","",IF(O24="PENDIENTE","Pendiente",IF(O24="NO EJECUTABLE","No ejecutable",IF(O24="VERIFICAR","Por verificar",IF(AND(F24="No cumple",O24="CUMPLE"),"Mejora",IF(AND(F24="No cumple",O24="PARCIAL"),"Mejora parcial",IF(AND(OR(F24="Cumple",F24="Sin ejecutar"),OR(O24="NO CUMPLE",O24="PARCIAL")),IF(F24="Cumple","Regresión","Falla nueva"),IF(AND(F24="No cumple",O24="NO CUMPLE"),"Sigue fallando","Se mantiene"))))))))
C25: Pedido Detalle | I25: NO CUMPLE | J25: H-003: no existe texto "Staff"/"Operativo" en ningun campo. Catalogo real tiene 3 categorias (freelance/interno/planta).
A26: 13 | B26: 13 | C26: Tipo de personal | D26: Validar que muestra Staff y Operativo | F26: Cumple | I26: CUMPLE | J26: H-003: "Personal de planta" (clave=staff, el equivalente funcional real de Staff) SI es seleccionable y activa el gating real de negocio -- verificado releyendo el codigo y reprobando en vivo. | O26: =IF(M26<>"",M26,IF(K26<>"",K26,IF(I26<>"",I26,""))) | P26: =IF(O26="","",IF(O26="PENDIENTE","Pendiente",IF(O26="NO EJECUTABLE","No ejecutable",IF(O26="VERIFICAR","Por verificar",IF(AND(F26="No cumple",O26="CUMPLE"),"Mejora",IF(AND(F26="No cumple",O26="PARCIAL"),"Mejora parcial",IF(AND(OR(F26="Cumple",F26="Sin ejecutar"),OR(O26="NO CUMPLE",O26="PARCIAL")),IF(F26="Cumple","Regresión","Falla nueva"),IF(AND(F26="No cumple",O26="NO CUMPLE"),"Sigue fallando","Se mantiene"))))))))
A27: 14 | B27: 14 | C27: Seleccionar Staff como Tipo de Personal | F27: Cumple | I27: NO CUMPLE | J27: H-005: con Staff (clave real) seleccionado, el combo de Producto queda VACIO -- ningun puesto matricial de PRG tiene tarifa en tp_sueldos_matriciales (0 filas confirmadas en BD). | O27: =IF(M27<>"",M27,IF(K27<>"",K27,IF(I27<>"",I27,""))) | P27: =IF(O27="","",IF(O27="PENDIENTE","Pendiente",IF(O27="NO EJECUTABLE","No ejecutable",IF(O27="VERIFICAR","Por verificar",IF(AND(F27="No cumple",O27="CUMPLE"),"Mejora",IF(AND(F27="No cumple",O27="PARCIAL"),"Mejora parcial",IF(AND(OR(F27="Cumple",F27="Sin ejecutar"),OR(O27="NO CUMPLE",O27="PARCIAL")),IF(F27="Cumple","Regresión","Falla nueva"),IF(AND(F27="No cumple",O27="NO CUMPLE"),"Sigue fallando","Se mantiene"))))))))
A28: 15 | B28: 15 | C28: Producto: Asistente Operador PRG - IN | D28: Validar que el catálogo mostrado es el de PRG | F28: No cumple | G28: El producto asistente operador PRG-IN no aparece si tomamos el tipo de personal staff, pero si tomamos el tipo de personal operativo sí aparece la opción | H28: BASE DE DATOS | I28: NO EJECUTABLE | J28: H-005: bloqueado, no hay producto Staff seleccionable para poder validar la jornada. | O28: =IF(M28<>"",M28,IF(K28<>"",K28,IF(I28<>"",I28,""))) | P28: =IF(O28="","",IF(O28="PENDIENTE","Pendiente",IF(O28="NO EJECUTABLE","No ejecutable",IF(O28="VERIFICAR","Por verificar",IF(AND(F28="No cumple",O28="CUMPLE"),"Mejora",IF(AND(F28="No cumple",O28="PARCIAL"),"Mejora parcial",IF(AND(OR(F28="Cumple",F28="Sin ejecutar"),OR(O28="NO CUMPLE",O28="PARCIAL")),IF(F28="Cumple","Regresión","Falla nueva"),IF(AND(F28="No cumple",O28="NO CUMPLE"),"Sigue fallando","Se mantiene"))))))))
A29: 16 | B29: 16 | C29: Validar la jornada | D29: Debe mostrar 1 turno por 12 horas, que es el turno asociado al producto | F29: No cumple | G29: En ninguna parte aparece los turnos y las horas. | H29: Corregido | I29: PARCIAL | J29: H-005: la UI SI acepta fecha de cita y liberacion sin error, pero el renglon nunca se persiste por la causa raiz de H-005. | O29: =IF(M29<>"",M29,IF(K29<>"",K29,IF(I29<>"",I29,""))) | P29: =IF(O29="","",IF(O29="PENDIENTE","Pendiente",IF(O29="NO EJECUTABLE","No ejecutable",IF(O29="VERIFICAR","Por verificar",IF(AND(F29="No cumple",O29="CUMPLE"),"Mejora",IF(AND(F29="No cumple",O29="PARCIAL"),"Mejora parcial",IF(AND(OR(F29="Cumple",F29="Sin ejecutar"),OR(O29="NO CUMPLE",O29="PARCIAL")),IF(F29="Cumple","Regresión","Falla nueva"),IF(AND(F29="No cumple",O29="NO CUMPLE"),"Sigue fallando","Se mantiene"))))))))
A30: 17 | B30: 17 | C30: Seleccionar una fecha de cita y de liberación | F30: Cumple | I30: CUMPLE | J30: Combo Presentacion por producto solo con "-- sin presentacion --", confirmado 2 veces. | O30: =IF(M30<>"",M30,IF(K30<>"",K30,IF(I30<>"",I30,""))) | P30: =IF(O30="","",IF(O30="PENDIENTE","Pendiente",IF(O30="NO EJECUTABLE","No ejecutable",IF(O30="VERIFICAR","Por verificar",IF(AND(F30="No cumple",O30="CUMPLE"),"Mejora",IF(AND(F30="No cumple",O30="PARCIAL"),"Mejora parcial",IF(AND(OR(F30="Cumple",F30="Sin ejecutar"),OR(O30="NO CUMPLE",O30="PARCIAL")),IF(F30="Cumple","Regresión","Falla nueva"),IF(AND(F30="No cumple",O30="NO CUMPLE"),"Sigue fallando","Se mantiene"))))))))
A31: 18 | B31: 18 | C31: Presentación por producto | D31: Validar que nos se muestran presentaciones | E31: 'nos' → probablemente 'no'. | F31: Cumple | G31: Aumo que en vez de "nos" hace referecnia a no | I31: NO EJECUTABLE | J31: H-005: no se pudo probar con un producto Staff real; inconcluso respecto al auto-seleccionado de "No Aplica". | O31: =IF(M31<>"",M31,IF(K31<>"",K31,IF(I31<>"",I31,""))) | P31: =IF(O31="","",IF(O31="PENDIENTE","Pendiente",IF(O31="NO EJECUTABLE","No ejecutable",IF(O31="VERIFICAR","Por verificar",IF(AND(F31="No cumple",O31="CUMPLE"),"Mejora",IF(AND(F31="No cumple",O31="PARCIAL"),"Mejora parcial",IF(AND(OR(F31="Cumple",F31="Sin ejecutar"),OR(O31="NO CUMPLE",O31="PARCIAL")),IF(F31="Cumple","Regresión","Falla nueva"),IF(AND(F31="No cumple",O31="NO CUMPLE"),"Sigue fallando","Se mantiene"))))))))
A32: 19 | B32: 19 | C32: Fase del evento | D32: Al ser Staff con complejidad y días de show debe mostrar No Aplica | F32: No cumple | G32: En efecto noa plica, pero tanto en el escenario 1 y 2 aparecía así. Además se continuó conpersonal operativo y no de staff | H32: EN PROCESO | I32: NO EJECUTABLE | J32: H-005 / H-006 (ver CLAUDE.md Sec.11): con producto sin puesto el sistema SI valida claramente "Elegi un producto (define el puesto)" -- no es falla silenciosa. Con Staff real, el combo esta vacio por H-005. | O32: =IF(M32<>"",M32,IF(K32<>"",K32,IF(I32<>"",I32,""))) | P32: =IF(O32="","",IF(O32="PENDIENTE","Pendiente",IF(O32="NO EJECUTABLE","No ejecutable",IF(O32="VERIFICAR","Por verificar",IF(AND(F32="No cumple",O32="CUMPLE"),"Mejora",IF(AND(F32="No cumple",O32="PARCIAL"),"Mejora parcial",IF(AND(OR(F32="Cumple",F32="Sin ejecutar"),OR(O32="NO CUMPLE",O32="PARCIAL")),IF(F32="Cumple","Regresión","Falla nueva"),IF(AND(F32="No cumple",O32="NO CUMPLE"),"Sigue fallando","Se mantiene"))))))))
A33: 20 | B33: 20 | C33: Agregar Registro | D33: El sistema no lo permite, ya que al ser puestos de Staff, cada producto debe ir en un bloque nuevo | F33: Sin ejecutar | I33: NO EJECUTABLE | J33: No se encontro control de "Bloque" independiente visible (solo "+ Agregar fecha al bloque" dentro del mismo renglon). No se pudo profundizar por H-005. | O33: =IF(M33<>"",M33,IF(K33<>"",K33,IF(I33<>"",I33,""))) | P33: =IF(O33="","",IF(O33="PENDIENTE","Pendiente",IF(O33="NO EJECUTABLE","No ejecutable",IF(O33="VERIFICAR","Por verificar",IF(AND(F33="No cumple",O33="CUMPLE"),"Mejora",IF(AND(F33="No cumple",O33="PARCIAL"),"Mejora parcial",IF(AND(OR(F33="Cumple",F33="Sin ejecutar"),OR(O33="NO CUMPLE",O33="PARCIAL")),IF(F33="Cumple","Regresión","Falla nueva"),IF(AND(F33="No cumple",O33="NO CUMPLE"),"Sigue fallando","Se mantiene"))))))))
A34: 21 | B34: 21 | C34: Seleccionar nuevo Bloque | F34: Sin ejecutar | I34: NO EJECUTABLE | J34: H-005: sin producto Staff seleccionable no hay presupuesto que leer. | O34: =IF(M34<>"",M34,IF(K34<>"",K34,IF(I34<>"",I34,""))) | P34: =IF(O34="","",IF(O34="PENDIENTE","Pendiente",IF(O34="NO EJECUTABLE","No ejecutable",IF(O34="VERIFICAR","Por verificar",IF(AND(F34="No cumple",O34="CUMPLE"),"Mejora",IF(AND(F34="No cumple",O34="PARCIAL"),"Mejora parcial",IF(AND(OR(F34="Cumple",F34="Sin ejecutar"),OR(O34="NO CUMPLE",O34="PARCIAL")),IF(F34="Cumple","Regresión","Falla nueva"),IF(AND(F34="No cumple",O34="NO CUMPLE"),"Sigue fallando","Se mantiene"))))))))
A35: 22 | B35: 22 | C35: Agregar Registro | D35: Validar que el presupuesto día va ligado a la complejidad y los días de show | F35: Sin ejecutar | I35: NO EJECUTABLE | J35: H-005: el modal abre correctamente pero ninguna alta se completa. | O35: =IF(M35<>"",M35,IF(K35<>"",K35,IF(I35<>"",I35,""))) | P35: =IF(O35="","",IF(O35="PENDIENTE","Pendiente",IF(O35="NO EJECUTABLE","No ejecutable",IF(O35="VERIFICAR","Por verificar",IF(AND(F35="No cumple",O35="CUMPLE"),"Mejora",IF(AND(F35="No cumple",O35="PARCIAL"),"Mejora parcial",IF(AND(OR(F35="Cumple",F35="Sin ejecutar"),OR(O35="NO CUMPLE",O35="PARCIAL")),IF(F35="Cumple","Regresión","Falla nueva"),IF(AND(F35="No cumple",O35="NO CUMPLE"),"Sigue fallando","Se mantiene"))))))))
A36: 23 | B36: 23 | C36: Agregar nuevo pedido detalle | F36: Sin ejecutar | I36: NO CUMPLE | J36: H-005: mismo bloqueo con "Asistente Aux A PRG" (confirmado vigente=true, UN=PRG, matricial=true en BD, pero sin tarifa matricial). | O36: =IF(M36<>"",M36,IF(K36<>"",K36,IF(I36<>"",I36,""))) | P36: =IF(O36="","",IF(O36="PENDIENTE","Pendiente",IF(O36="NO EJECUTABLE","No ejecutable",IF(O36="VERIFICAR","Por verificar",IF(AND(F36="No cumple",O36="CUMPLE"),"Mejora",IF(AND(F36="No cumple",O36="PARCIAL"),"Mejora parcial",IF(AND(OR(F36="Cumple",F36="Sin ejecutar"),OR(O36="NO CUMPLE",O36="PARCIAL")),IF(F36="Cumple","Regresión","Falla nueva"),IF(AND(F36="No cumple",O36="NO CUMPLE"),"Sigue fallando","Se mantiene"))))))))
A37: 24 | B37: 24 | C37: Seleccionar producto: Asistente Auxiliar A | F37: Sin ejecutar | I37: NO EJECUTABLE | J37: H-005: mismo hallazgo que paso 21. | O37: =IF(M37<>"",M37,IF(K37<>"",K37,IF(I37<>"",I37,""))) | P37: =IF(O37="","",IF(O37="PENDIENTE","Pendiente",IF(O37="NO EJECUTABLE","No ejecutable",IF(O37="VERIFICAR","Por verificar",IF(AND(F37="No cumple",O37="CUMPLE"),"Mejora",IF(AND(F37="No cumple",O37="PARCIAL"),"Mejora parcial",IF(AND(OR(F37="Cumple",F37="Sin ejecutar"),OR(O37="NO CUMPLE",O37="PARCIAL")),IF(F37="Cumple","Regresión","Falla nueva"),IF(AND(F37="No cumple",O37="NO CUMPLE"),"Sigue fallando","Se mantiene"))))))))
A38: 25 | B38: 25 | C38: Seleccionar nuevo Bloque | F38: Sin ejecutar | I38: NO EJECUTABLE | J38: H-005: VERIFICADO EN BD -- te_pedidos_detalle con 0 filas para folio 200 y folio 199. No hay 2 bloques que comparar. | O38: =IF(M38<>"",M38,IF(K38<>"",K38,IF(I38<>"",I38,""))) | P38: =IF(O38="","",IF(O38="PENDIENTE","Pendiente",IF(O38="NO EJECUTABLE","No ejecutable",IF(O38="VERIFICAR","Por verificar",IF(AND(F38="No cumple",O38="CUMPLE"),"Mejora",IF(AND(F38="No cumple",O38="PARCIAL"),"Mejora parcial",IF(AND(OR(F38="Cumple",F38="Sin ejecutar"),OR(O38="NO CUMPLE",O38="PARCIAL")),IF(F38="Cumple","Regresión","Falla nueva"),IF(AND(F38="No cumple",O38="NO CUMPLE"),"Sigue fallando","Se mantiene"))))))))
A39: 26 | B39: 26 | C39: Agregar Registro | D39: Validar que se ha creado el nuevo bloque con el producto y los montos | F39: Sin ejecutar | O39: =IF(M39<>"",M39,IF(K39<>"",K39,IF(I39<>"",I39,""))) | P39: =IF(O39="","",IF(O39="PENDIENTE","Pendiente",IF(O39="NO EJECUTABLE","No ejecutable",IF(O39="VERIFICAR","Por verificar",IF(AND(F39="No cumple",O39="CUMPLE"),"Mejora",IF(AND(F39="No cumple",O39="PARCIAL"),"Mejora parcial",IF(AND(OR(F39="Cumple",F39="Sin ejecutar"),OR(O39="NO CUMPLE",O39="PARCIAL")),IF(F39="Cumple","Regresión","Falla nueva"),IF(AND(F39="No cumple",O39="NO CUMPLE"),"Sigue fallando","Se mantiene"))))))))

Sheet ESC-03
A1: ESC-03 — Pedido PRG-Producción con complejidad y fase de evento
A2: Núm. original | B2: Escenario 3 | I2: Pasos | J2: =COUNT(A13:A45)
A3: Módulo | B3: Pedidos | I3: Ejecutados (último) | J3: =COUNTIF(O13:O45,"?*")
A4: Objetivo (propuesto, validar) | B4: Validar un pedido PRG sin complejidad con varios detalles por fase de evento y arrastre de valores del detalle anterior. | I4: CUMPLE (último) | J4: =COUNTIF(O13:O45,"CUMPLE")
A5: Funcionalidades | B5: Sin complejidad → solo Operativo · catálogo PRG · fases (Preparación, Montaje, Show, Desmontaje) · nuevo bloque por fase · valores heredados | I5: % cumplimiento | J5: =IF(J2=0,0,J4/J2)
A6: Dependencias / datos | B6: —
A7: Sesión sugerida | B7: S03
A8: ⚠ Calidad del caso | B8: Paso 5 marcado Cumple y No cumple a la vez; esperado dice 'UN de seguridad'. Paso 8: Servicio Interno con esperado de Pedido.
A9: Notas originales | B9: —
F11: CORRIDA LEGADO (HUMANOS) | I11: CICLO CLAUDE CODE: probar → corregir → re-probar
A12: # | B12: Paso orig. | C12: Descripción | D12: Resultado esperado | E12: ⚠ Calidad | F12: Legado: Resultado | G12: Legado: Observación | H12: Legado: Corrección | I12: R1 Resultado | J12: R1 Hallazgo / Obs. | K12: R2 Resultado | L12: R2 Hallazgo / Obs. | M12: R3 Resultado | N12: R3 Hallazgo / Obs. | O12: Último resultado | P12: Comparativo
A13: 1 | B13: 1 | C13: Crear un nuevo pedido | F13: Cumple | O13: =IF(M13<>"",M13,IF(K13<>"",K13,IF(I13<>"",I13,""))) | P13: =IF(O13="","",IF(O13="PENDIENTE","Pendiente",IF(O13="NO EJECUTABLE","No ejecutable",IF(O13="VERIFICAR","Por verificar",IF(AND(F13="No cumple",O13="CUMPLE"),"Mejora",IF(AND(F13="No cumple",O13="PARCIAL"),"Mejora parcial",IF(AND(OR(F13="Cumple",F13="Sin ejecutar"),OR(O13="NO CUMPLE",O13="PARCIAL")),IF(F13="Cumple","Regresión","Falla nueva"),IF(AND(F13="No cumple",O13="NO CUMPLE"),"Sigue fallando","Se mantiene"))))))))
A14: 2 | B14: 2 | C14: Seleccionar cliente Ocesa | F14: Cumple | O14: =IF(M14<>"",M14,IF(K14<>"",K14,IF(I14<>"",I14,""))) | P14: =IF(O14="","",IF(O14="PENDIENTE","Pendiente",IF(O14="NO EJECUTABLE","No ejecutable",IF(O14="VERIFICAR","Por verificar",IF(AND(F14="No cumple",O14="CUMPLE"),"Mejora",IF(AND(F14="No cumple",O14="PARCIAL"),"Mejora parcial",IF(AND(OR(F14="Cumple",F14="Sin ejecutar"),OR(O14="NO CUMPLE",O14="PARCIAL")),IF(F14="Cumple","Regresión","Falla nueva"),IF(AND(F14="No cumple",O14="NO CUMPLE"),"Sigue fallando","Se mantiene"))))))))
A15: 3 | B15: 3 | C15: Validar lista de contactos | D15: Los contactos mostrados deben pertenecer al cliente Ocesa | F15: Cumple | O15: =IF(M15<>"",M15,IF(K15<>"",K15,IF(I15<>"",I15,""))) | P15: =IF(O15="","",IF(O15="PENDIENTE","Pendiente",IF(O15="NO EJECUTABLE","No ejecutable",IF(O15="VERIFICAR","Por verificar",IF(AND(F15="No cumple",O15="CUMPLE"),"Mejora",IF(AND(F15="No cumple",O15="PARCIAL"),"Mejora parcial",IF(AND(OR(F15="Cumple",F15="Sin ejecutar"),OR(O15="NO CUMPLE",O15="PARCIAL")),IF(F15="Cumple","Regresión","Falla nueva"),IF(AND(F15="No cumple",O15="NO CUMPLE"),"Sigue fallando","Se mantiene"))))))))
A16: 4 | B16: 4 | C16: Seleccionar un evento | F16: Cumple | O16: =IF(M16<>"",M16,IF(K16<>"",K16,IF(I16<>"",I16,""))) | P16: =IF(O16="","",IF(O16="PENDIENTE","Pendiente",IF(O16="NO EJECUTABLE","No ejecutable",IF(O16="VERIFICAR","Por verificar",IF(AND(F16="No cumple",O16="CUMPLE"),"Mejora",IF(AND(F16="No cumple",O16="PARCIAL"),"Mejora parcial",IF(AND(OR(F16="Cumple",F16="Sin ejecutar"),OR(O16="NO CUMPLE",O16="PARCIAL")),IF(F16="Cumple","Regresión","Falla nueva"),IF(AND(F16="No cumple",O16="NO CUMPLE"),"Sigue fallando","Se mantiene"))))))))
A17: 5 | B17: 5 | C17: Seleccionar UN PRG | D17: El sistema despliega los PEPS de la UN de seguridad, y la sociedad pagadora (en este caso Lobo) | E17: Marcado Cumple y No cumple; esperado copiado. | F17: Ambos marcados | G17: La sociedad pagadora por dafult está con ID 10 | H17: Corregido | O17: =IF(M17<>"",M17,IF(K17<>"",K17,IF(I17<>"",I17,""))) | P17: =IF(O17="","",IF(O17="PENDIENTE","Pendiente",IF(O17="NO EJECUTABLE","No ejecutable",IF(O17="VERIFICAR","Por verificar",IF(AND(F17="No cumple",O17="CUMPLE"),"Mejora",IF(AND(F17="No cumple",O17="PARCIAL"),"Mejora parcial",IF(AND(OR(F17="Cumple",F17="Sin ejecutar"),OR(O17="NO CUMPLE",O17="PARCIAL")),IF(F17="Cumple","Regresión","Falla nueva"),IF(AND(F17="No cumple",O17="NO CUMPLE"),"Sigue fallando","Se mantiene"))))))))
A18: 6 | B18: 6 | C18: Seleccionar el PEPS asociado a la UN | D18: El sistema me muestra el nombre y la dirección del inmueble | F18: Cumple | O18: =IF(M18<>"",M18,IF(K18<>"",K18,IF(I18<>"",I18,""))) | P18: =IF(O18="","",IF(O18="PENDIENTE","Pendiente",IF(O18="NO EJECUTABLE","No ejecutable",IF(O18="VERIFICAR","Por verificar",IF(AND(F18="No cumple",O18="CUMPLE"),"Mejora",IF(AND(F18="No cumple",O18="PARCIAL"),"Mejora parcial",IF(AND(OR(F18="Cumple",F18="Sin ejecutar"),OR(O18="NO CUMPLE",O18="PARCIAL")),IF(F18="Cumple","Regresión","Falla nueva"),IF(AND(F18="No cumple",O18="NO CUMPLE"),"Sigue fallando","Se mantiene"))))))))
A19: 7 | B19: 7 | C19: Validar tipo de movimiento | D19: El sistema debe mostrar dos tipos de movimiento (Pedido y Servicio Interno) | F19: No cumple | G19: Únicamnete muestra "pedido" | H19: Corregido | O19: =IF(M19<>"",M19,IF(K19<>"",K19,IF(I19<>"",I19,""))) | P19: =IF(O19="","",IF(O19="PENDIENTE","Pendiente",IF(O19="NO EJECUTABLE","No ejecutable",IF(O19="VERIFICAR","Por verificar",IF(AND(F19="No cumple",O19="CUMPLE"),"Mejora",IF(AND(F19="No cumple",O19="PARCIAL"),"Mejora parcial",IF(AND(OR(F19="Cumple",F19="Sin ejecutar"),OR(O19="NO CUMPLE",O19="PARCIAL")),IF(F19="Cumple","Regresión","Falla nueva"),IF(AND(F19="No cumple",O19="NO CUMPLE"),"Sigue fallando","Se mantiene"))))))))
A20: 8 | B20: 8 | C20: Seleccionar Tipo de movimiento Servicio Interno | D20: EL tipo Pedido se factura (validar posteriormente) | E20: Servicio Interno con esperado de Pedido. | F20: No cumple | G20: Factura está determinado como de No por default | H20: Corregido | O20: =IF(M20<>"",M20,IF(K20<>"",K20,IF(I20<>"",I20,""))) | P20: =IF(O20="","",IF(O20="PENDIENTE","Pendiente",IF(O20="NO EJECUTABLE","No ejecutable",IF(O20="VERIFICAR","Por verificar",IF(AND(F20="No cumple",O20="CUMPLE"),"Mejora",IF(AND(F20="No cumple",O20="PARCIAL"),"Mejora parcial",IF(AND(OR(F20="Cumple",F20="Sin ejecutar"),OR(O20="NO CUMPLE",O20="PARCIAL")),IF(F20="Cumple","Regresión","Falla nueva"),IF(AND(F20="No cumple",O20="NO CUMPLE"),"Sigue fallando","Se mantiene"))))))))
A21: 9 | B21: 9 | C21: En complejidad indicar que No Aplica | F21: Cumple | O21: =IF(M21<>"",M21,IF(K21<>"",K21,IF(I21<>"",I21,""))) | P21: =IF(O21="","",IF(O21="PENDIENTE","Pendiente",IF(O21="NO EJECUTABLE","No ejecutable",IF(O21="VERIFICAR","Por verificar",IF(AND(F21="No cumple",O21="CUMPLE"),"Mejora",IF(AND(F21="No cumple",O21="PARCIAL"),"Mejora parcial",IF(AND(OR(F21="Cumple",F21="Sin ejecutar"),OR(O21="NO CUMPLE",O21="PARCIAL")),IF(F21="Cumple","Regresión","Falla nueva"),IF(AND(F21="No cumple",O21="NO CUMPLE"),"Sigue fallando","Se mantiene"))))))))
A22: 10 | B22: 10 | C22: En el campo Permitir Cancelar, seleccionar NO | F22: Sin ejecutar | O22: =IF(M22<>"",M22,IF(K22<>"",K22,IF(I22<>"",I22,""))) | P22: =IF(O22="","",IF(O22="PENDIENTE","Pendiente",IF(O22="NO EJECUTABLE","No ejecutable",IF(O22="VERIFICAR","Por verificar",IF(AND(F22="No cumple",O22="CUMPLE"),"Mejora",IF(AND(F22="No cumple",O22="PARCIAL"),"Mejora parcial",IF(AND(OR(F22="Cumple",F22="Sin ejecutar"),OR(O22="NO CUMPLE",O22="PARCIAL")),IF(F22="Cumple","Regresión","Falla nueva"),IF(AND(F22="No cumple",O22="NO CUMPLE"),"Sigue fallando","Se mantiene"))))))))
A23: 11 | B23: 11 | C23: Pulsar Aceptar | D23: El sistema genera un número consecutivo de pedido. | F23: Cumple | O23: =IF(M23<>"",M23,IF(K23<>"",K23,IF(I23<>"",I23,""))) | P23: =IF(O23="","",IF(O23="PENDIENTE","Pendiente",IF(O23="NO EJECUTABLE","No ejecutable",IF(O23="VERIFICAR","Por verificar",IF(AND(F23="No cumple",O23="CUMPLE"),"Mejora",IF(AND(F23="No cumple",O23="PARCIAL"),"Mejora parcial",IF(AND(OR(F23="Cumple",F23="Sin ejecutar"),OR(O23="NO CUMPLE",O23="PARCIAL")),IF(F23="Cumple","Regresión","Falla nueva"),IF(AND(F23="No cumple",O23="NO CUMPLE"),"Sigue fallando","Se mantiene"))))))))
C24: Pedido Detalle
A25: 12 | B25: 12 | C25: Tipo de personal | D25: Validad que sólo se muestren Operativos al no tener complejidad | F25: Cumple | O25: =IF(M25<>"",M25,IF(K25<>"",K25,IF(I25<>"",I25,""))) | P25: =IF(O25="","",IF(O25="PENDIENTE","Pendiente",IF(O25="NO EJECUTABLE","No ejecutable",IF(O25="VERIFICAR","Por verificar",IF(AND(F25="No cumple",O25="CUMPLE"),"Mejora",IF(AND(F25="No cumple",O25="PARCIAL"),"Mejora parcial",IF(AND(OR(F25="Cumple",F25="Sin ejecutar"),OR(O25="NO CUMPLE",O25="PARCIAL")),IF(F25="Cumple","Regresión","Falla nueva"),IF(AND(F25="No cumple",O25="NO CUMPLE"),"Sigue fallando","Se mantiene"))))))))
A26: 13 | B26: 13 | C26: Seleccionar Operativo | F26: Cumple | O26: =IF(M26<>"",M26,IF(K26<>"",K26,IF(I26<>"",I26,""))) | P26: =IF(O26="","",IF(O26="PENDIENTE","Pendiente",IF(O26="NO EJECUTABLE","No ejecutable",IF(O26="VERIFICAR","Por verificar",IF(AND(F26="No cumple",O26="CUMPLE"),"Mejora",IF(AND(F26="No cumple",O26="PARCIAL"),"Mejora parcial",IF(AND(OR(F26="Cumple",F26="Sin ejecutar"),OR(O26="NO CUMPLE",O26="PARCIAL")),IF(F26="Cumple","Regresión","Falla nueva"),IF(AND(F26="No cumple",O26="NO CUMPLE"),"Sigue fallando","Se mantiene"))))))))
A27: 14 | B27: 14 | C27: Producto: Técnico Audio PRG - IN | D27: Validar que el catálogo mostrado es el de PRG | F27: Cumple | O27: =IF(M27<>"",M27,IF(K27<>"",K27,IF(I27<>"",I27,""))) | P27: =IF(O27="","",IF(O27="PENDIENTE","Pendiente",IF(O27="NO EJECUTABLE","No ejecutable",IF(O27="VERIFICAR","Por verificar",IF(AND(F27="No cumple",O27="CUMPLE"),"Mejora",IF(AND(F27="No cumple",O27="PARCIAL"),"Mejora parcial",IF(AND(OR(F27="Cumple",F27="Sin ejecutar"),OR(O27="NO CUMPLE",O27="PARCIAL")),IF(F27="Cumple","Regresión","Falla nueva"),IF(AND(F27="No cumple",O27="NO CUMPLE"),"Sigue fallando","Se mantiene"))))))))
A28: 15 | B28: 15 | C28: Validar la jornada | D28: Debe mostrar 1 turno por 12 horas | F28: Cumple | O28: =IF(M28<>"",M28,IF(K28<>"",K28,IF(I28<>"",I28,""))) | P28: =IF(O28="","",IF(O28="PENDIENTE","Pendiente",IF(O28="NO EJECUTABLE","No ejecutable",IF(O28="VERIFICAR","Por verificar",IF(AND(F28="No cumple",O28="CUMPLE"),"Mejora",IF(AND(F28="No cumple",O28="PARCIAL"),"Mejora parcial",IF(AND(OR(F28="Cumple",F28="Sin ejecutar"),OR(O28="NO CUMPLE",O28="PARCIAL")),IF(F28="Cumple","Regresión","Falla nueva"),IF(AND(F28="No cumple",O28="NO CUMPLE"),"Sigue fallando","Se mantiene"))))))))
A29: 16 | B29: 16 | C29: Seleccionar una fecha de cita y de liberación | F29: Cumple | O29: =IF(M29<>"",M29,IF(K29<>"",K29,IF(I29<>"",I29,""))) | P29: =IF(O29="","",IF(O29="PENDIENTE","Pendiente",IF(O29="NO EJECUTABLE","No ejecutable",IF(O29="VERIFICAR","Por verificar",IF(AND(F29="No cumple",O29="CUMPLE"),"Mejora",IF(AND(F29="No cumple",O29="PARCIAL"),"Mejora parcial",IF(AND(OR(F29="Cumple",F29="Sin ejecutar"),OR(O29="NO CUMPLE",O29="PARCIAL")),IF(F29="Cumple","Regresión","Falla nueva"),IF(AND(F29="No cumple",O29="NO CUMPLE"),"Sigue fallando","Se mantiene"))))))))
A30: 17 | B30: 17 | C30: Presentación por producto | D30: Validar que nos se muestran presentaciones | E30: 'nos' → probablemente 'no'. | F30: Cumple | O30: =IF(M30<>"",M30,IF(K30<>"",K30,IF(I30<>"",I30,""))) | P30: =IF(O30="","",IF(O30="PENDIENTE","Pendiente",IF(O30="NO EJECUTABLE","No ejecutable",IF(O30="VERIFICAR","Por verificar",IF(AND(F30="No cumple",O30="CUMPLE"),"Mejora",IF(AND(F30="No cumple",O30="PARCIAL"),"Mejora parcial",IF(AND(OR(F30="Cumple",F30="Sin ejecutar"),OR(O30="NO CUMPLE",O30="PARCIAL")),IF(F30="Cumple","Regresión","Falla nueva"),IF(AND(F30="No cumple",O30="NO CUMPLE"),"Sigue fallando","Se mantiene"))))))))
A31: 18 | B31: 18 | C31: Fase del evento | D31: Validar que se muestran todos los valores del catálogo de Fase de evento | F31: Cumple | O31: =IF(M31<>"",M31,IF(K31<>"",K31,IF(I31<>"",I31,""))) | P31: =IF(O31="","",IF(O31="PENDIENTE","Pendiente",IF(O31="NO EJECUTABLE","No ejecutable",IF(O31="VERIFICAR","Por verificar",IF(AND(F31="No cumple",O31="CUMPLE"),"Mejora",IF(AND(F31="No cumple",O31="PARCIAL"),"Mejora parcial",IF(AND(OR(F31="Cumple",F31="Sin ejecutar"),OR(O31="NO CUMPLE",O31="PARCIAL")),IF(F31="Cumple","Regresión","Falla nueva"),IF(AND(F31="No cumple",O31="NO CUMPLE"),"Sigue fallando","Se mantiene"))))))))
A32: 19 | B32: 19 | C32: Seleccionar Preparación como fase de evento | F32: Cumple | O32: =IF(M32<>"",M32,IF(K32<>"",K32,IF(I32<>"",I32,""))) | P32: =IF(O32="","",IF(O32="PENDIENTE","Pendiente",IF(O32="NO EJECUTABLE","No ejecutable",IF(O32="VERIFICAR","Por verificar",IF(AND(F32="No cumple",O32="CUMPLE"),"Mejora",IF(AND(F32="No cumple",O32="PARCIAL"),"Mejora parcial",IF(AND(OR(F32="Cumple",F32="Sin ejecutar"),OR(O32="NO CUMPLE",O32="PARCIAL")),IF(F32="Cumple","Regresión","Falla nueva"),IF(AND(F32="No cumple",O32="NO CUMPLE"),"Sigue fallando","Se mantiene"))))))))
A33: 20 | B33: 20 | C33: Agregar Registro | F33: Cumple | O33: =IF(M33<>"",M33,IF(K33<>"",K33,IF(I33<>"",I33,""))) | P33: =IF(O33="","",IF(O33="PENDIENTE","Pendiente",IF(O33="NO EJECUTABLE","No ejecutable",IF(O33="VERIFICAR","Por verificar",IF(AND(F33="No cumple",O33="CUMPLE"),"Mejora",IF(AND(F33="No cumple",O33="PARCIAL"),"Mejora parcial",IF(AND(OR(F33="Cumple",F33="Sin ejecutar"),OR(O33="NO CUMPLE",O33="PARCIAL")),IF(F33="Cumple","Regresión","Falla nueva"),IF(AND(F33="No cumple",O33="NO CUMPLE"),"Sigue fallando","Se mantiene"))))))))
A34: 21 | B34: 21 | C34: Agregar nuevo pedido detalle | F34: Cumple | O34: =IF(M34<>"",M34,IF(K34<>"",K34,IF(I34<>"",I34,""))) | P34: =IF(O34="","",IF(O34="PENDIENTE","Pendiente",IF(O34="NO EJECUTABLE","No ejecutable",IF(O34="VERIFICAR","Por verificar",IF(AND(F34="No cumple",O34="CUMPLE"),"Mejora",IF(AND(F34="No cumple",O34="PARCIAL"),"Mejora parcial",IF(AND(OR(F34="Cumple",F34="Sin ejecutar"),OR(O34="NO CUMPLE",O34="PARCIAL")),IF(F34="Cumple","Regresión","Falla nueva"),IF(AND(F34="No cumple",O34="NO CUMPLE"),"Sigue fallando","Se mantiene"))))))))
A35: 22 | B35: 22 | C35: Producto: Técnico Audio PRG - IN | D35: El sistema debe guardar el valor introducido anteriormente | F35: Cumple | G35: Se guarda todo, a excepción de los turnos y la cantidad | O35: =IF(M35<>"",M35,IF(K35<>"",K35,IF(I35<>"",I35,""))) | P35: =IF(O35="","",IF(O35="PENDIENTE","Pendiente",IF(O35="NO EJECUTABLE","No ejecutable",IF(O35="VERIFICAR","Por verificar",IF(AND(F35="No cumple",O35="CUMPLE"),"Mejora",IF(AND(F35="No cumple",O35="PARCIAL"),"Mejora parcial",IF(AND(OR(F35="Cumple",F35="Sin ejecutar"),OR(O35="NO CUMPLE",O35="PARCIAL")),IF(F35="Cumple","Regresión","Falla nueva"),IF(AND(F35="No cumple",O35="NO CUMPLE"),"Sigue fallando","Se mantiene"))))))))
A36: 23 | B36: 23 | C36: Fase del evento: Montaje | F36: No cumple | H36: EN PROCESO | O36: =IF(M36<>"",M36,IF(K36<>"",K36,IF(I36<>"",I36,""))) | P36: =IF(O36="","",IF(O36="PENDIENTE","Pendiente",IF(O36="NO EJECUTABLE","No ejecutable",IF(O36="VERIFICAR","Por verificar",IF(AND(F36="No cumple",O36="CUMPLE"),"Mejora",IF(AND(F36="No cumple",O36="PARCIAL"),"Mejora parcial",IF(AND(OR(F36="Cumple",F36="Sin ejecutar"),OR(O36="NO CUMPLE",O36="PARCIAL")),IF(F36="Cumple","Regresión","Falla nueva"),IF(AND(F36="No cumple",O36="NO CUMPLE"),"Sigue fallando","Se mantiene"))))))))
A37: 24 | B37: 24 | C37: Agregar Registro | D37: Validar que se ha creado el nuevo bloque con el producto y los montos | F37: No cumple | H37: EN PROCESO | O37: =IF(M37<>"",M37,IF(K37<>"",K37,IF(I37<>"",I37,""))) | P37: =IF(O37="","",IF(O37="PENDIENTE","Pendiente",IF(O37="NO EJECUTABLE","No ejecutable",IF(O37="VERIFICAR","Por verificar",IF(AND(F37="No cumple",O37="CUMPLE"),"Mejora",IF(AND(F37="No cumple",O37="PARCIAL"),"Mejora parcial",IF(AND(OR(F37="Cumple",F37="Sin ejecutar"),OR(O37="NO CUMPLE",O37="PARCIAL")),IF(F37="Cumple","Regresión","Falla nueva"),IF(AND(F37="No cumple",O37="NO CUMPLE"),"Sigue fallando","Se mantiene"))))))))
A38: 25 | B38: 25 | C38: Agregar nuevo pedido detalle | F38: No cumple | H38: EN PROCESO | O38: =IF(M38<>"",M38,IF(K38<>"",K38,IF(I38<>"",I38,""))) | P38: =IF(O38="","",IF(O38="PENDIENTE","Pendiente",IF(O38="NO EJECUTABLE","No ejecutable",IF(O38="VERIFICAR","Por verificar",IF(AND(F38="No cumple",O38="CUMPLE"),"Mejora",IF(AND(F38="No cumple",O38="PARCIAL"),"Mejora parcial",IF(AND(OR(F38="Cumple",F38="Sin ejecutar"),OR(O38="NO CUMPLE",O38="PARCIAL")),IF(F38="Cumple","Regresión","Falla nueva"),IF(AND(F38="No cumple",O38="NO CUMPLE"),"Sigue fallando","Se mantiene"))))))))
A39: 26 | B39: 26 | C39: Producto: Técnico Audio PRG - IN | D39: El sistema debe guardar el valor introducido anteriormente | F39: No cumple | H39: EN PROCESO | O39: =IF(M39<>"",M39,IF(K39<>"",K39,IF(I39<>"",I39,""))) | P39: =IF(O39="","",IF(O39="PENDIENTE","Pendiente",IF(O39="NO EJECUTABLE","No ejecutable",IF(O39="VERIFICAR","Por verificar",IF(AND(F39="No cumple",O39="CUMPLE"),"Mejora",IF(AND(F39="No cumple",O39="PARCIAL"),"Mejora parcial",IF(AND(OR(F39="Cumple",F39="Sin ejecutar"),OR(O39="NO CUMPLE",O39="PARCIAL")),IF(F39="Cumple","Regresión","Falla nueva"),IF(AND(F39="No cumple",O39="NO CUMPLE"),"Sigue fallando","Se mantiene"))))))))
A40: 27 | B40: 27 | C40: Fase del evento: Show | F40: No cumple | H40: EN PROCESO | O40: =IF(M40<>"",M40,IF(K40<>"",K40,IF(I40<>"",I40,""))) | P40: =IF(O40="","",IF(O40="PENDIENTE","Pendiente",IF(O40="NO EJECUTABLE","No ejecutable",IF(O40="VERIFICAR","Por verificar",IF(AND(F40="No cumple",O40="CUMPLE"),"Mejora",IF(AND(F40="No cumple",O40="PARCIAL"),"Mejora parcial",IF(AND(OR(F40="Cumple",F40="Sin ejecutar"),OR(O40="NO CUMPLE",O40="PARCIAL")),IF(F40="Cumple","Regresión","Falla nueva"),IF(AND(F40="No cumple",O40="NO CUMPLE"),"Sigue fallando","Se mantiene"))))))))
A41: 28 | B41: 28 | C41: Agregar Registro | D41: Validar que se ha creado el nuevo bloque con el producto y los montos | F41: No cumple | H41: EN PROCESO | O41: =IF(M41<>"",M41,IF(K41<>"",K41,IF(I41<>"",I41,""))) | P41: =IF(O41="","",IF(O41="PENDIENTE","Pendiente",IF(O41="NO EJECUTABLE","No ejecutable",IF(O41="VERIFICAR","Por verificar",IF(AND(F41="No cumple",O41="CUMPLE"),"Mejora",IF(AND(F41="No cumple",O41="PARCIAL"),"Mejora parcial",IF(AND(OR(F41="Cumple",F41="Sin ejecutar"),OR(O41="NO CUMPLE",O41="PARCIAL")),IF(F41="Cumple","Regresión","Falla nueva"),IF(AND(F41="No cumple",O41="NO CUMPLE"),"Sigue fallando","Se mantiene"))))))))
A42: 29 | B42: 29 | C42: Agregar nuevo pedido detalle | F42: No cumple | H42: EN PROCESO | O42: =IF(M42<>"",M42,IF(K42<>"",K42,IF(I42<>"",I42,""))) | P42: =IF(O42="","",IF(O42="PENDIENTE","Pendiente",IF(O42="NO EJECUTABLE","No ejecutable",IF(O42="VERIFICAR","Por verificar",IF(AND(F42="No cumple",O42="CUMPLE"),"Mejora",IF(AND(F42="No cumple",O42="PARCIAL"),"Mejora parcial",IF(AND(OR(F42="Cumple",F42="Sin ejecutar"),OR(O42="NO CUMPLE",O42="PARCIAL")),IF(F42="Cumple","Regresión","Falla nueva"),IF(AND(F42="No cumple",O42="NO CUMPLE"),"Sigue fallando","Se mantiene"))))))))
A43: 30 | B43: 30 | C43: Producto: Técnico Audio PRG - IN | D43: El sistema debe guardar el valor introducido anteriormente | F43: No cumple | H43: EN PROCESO | O43: =IF(M43<>"",M43,IF(K43<>"",K43,IF(I43<>"",I43,""))) | P43: =IF(O43="","",IF(O43="PENDIENTE","Pendiente",IF(O43="NO EJECUTABLE","No ejecutable",IF(O43="VERIFICAR","Por verificar",IF(AND(F43="No cumple",O43="CUMPLE"),"Mejora",IF(AND(F43="No cumple",O43="PARCIAL"),"Mejora parcial",IF(AND(OR(F43="Cumple",F43="Sin ejecutar"),OR(O43="NO CUMPLE",O43="PARCIAL")),IF(F43="Cumple","Regresión","Falla nueva"),IF(AND(F43="No cumple",O43="NO CUMPLE"),"Sigue fallando","Se mantiene"))))))))
A44: 31 | B44: 31 | C44: Fase del evento: Desmontaje | F44: No cumple | H44: EN PROCESO | O44: =IF(M44<>"",M44,IF(K44<>"",K44,IF(I44<>"",I44,""))) | P44: =IF(O44="","",IF(O44="PENDIENTE","Pendiente",IF(O44="NO EJECUTABLE","No ejecutable",IF(O44="VERIFICAR","Por verificar",IF(AND(F44="No cumple",O44="CUMPLE"),"Mejora",IF(AND(F44="No cumple",O44="PARCIAL"),"Mejora parcial",IF(AND(OR(F44="Cumple",F44="Sin ejecutar"),OR(O44="NO CUMPLE",O44="PARCIAL")),IF(F44="Cumple","Regresión","Falla nueva"),IF(AND(F44="No cumple",O44="NO CUMPLE"),"Sigue fallando","Se mantiene"))))))))
A45: 32 | B45: 32 | C45: Agregar Registro | D45: Validar que se ha creado el nuevo bloque con el producto y los montos | F45: No cumple | H45: EN PROCESO | O45: =IF(M45<>"",M45,IF(K45<>"",K45,IF(I45<>"",I45,""))) | P45: =IF(O45="","",IF(O45="PENDIENTE","Pendiente",IF(O45="NO EJECUTABLE","No ejecutable",IF(O45="VERIFICAR","Por verificar",IF(AND(F45="No cumple",O45="CUMPLE"),"Mejora",IF(AND(F45="No cumple",O45="PARCIAL"),"Mejora parcial",IF(AND(OR(F45="Cumple",F45="Sin ejecutar"),OR(O45="NO CUMPLE",O45="PARCIAL")),IF(F45="Cumple","Regresión","Falla nueva"),IF(AND(F45="No cumple",O45="NO CUMPLE"),"Sigue fallando","Se mantiene"))))))))

Sheet ESC-04
A1: ESC-04 — Pedido para Azteca (Seguridad) - Futbol América vs Pumas
A2: Núm. original | B2: Escenario 4 | I2: Pasos | J2: =COUNT(A13:A119)
A3: Módulo | B3: Pedidos | I3: Ejecutados (último) | J3: =COUNTIF(O13:O119,"?*")
A4: Objetivo (propuesto, validar) | B4: Validar un pedido de Seguridad de gran volumen (9 productos) con alta repetitiva de detalles. | I4: CUMPLE (último) | J4: =COUNTIF(O13:O119,"CUMPLE")
A5: Funcionalidades | B5: Edición de título · horas por turno por producto · validación de fechas · presentaciones por UN · completar similares NO · ID de detalle · matriz | I5: % cumplimiento | J5: =IF(J2=0,0,J4/J2)
A6: Dependencias / datos | B6: —
A7: Sesión sugerida | B7: S04
A8: ⚠ Calidad del caso | B8: 9 bloques casi idénticos (parametrizable). El paso final 'El pedido debe quedar de la siguiente forma' remite a una imagen del archivo original.
A9: Notas originales | B9: —
F11: CORRIDA LEGADO (HUMANOS) | I11: CICLO CLAUDE CODE: probar → corregir → re-probar
A12: # | B12: Paso orig. | C12: Descripción | D12: Resultado esperado | E12: ⚠ Calidad | F12: Legado: Resultado | G12: Legado: Observación | H12: Legado: Corrección | I12: R1 Resultado | J12: R1 Hallazgo / Obs. | K12: R2 Resultado | L12: R2 Hallazgo / Obs. | M12: R3 Resultado | N12: R3 Hallazgo / Obs. | O12: Último resultado | P12: Comparativo
A13: 1 | B13: 1 | C13: Crear un nuevo pedido | F13: Cumple | O13: =IF(M13<>"",M13,IF(K13<>"",K13,IF(I13<>"",I13,""))) | P13: =IF(O13="","",IF(O13="PENDIENTE","Pendiente",IF(O13="NO EJECUTABLE","No ejecutable",IF(O13="VERIFICAR","Por verificar",IF(AND(F13="No cumple",O13="CUMPLE"),"Mejora",IF(AND(F13="No cumple",O13="PARCIAL"),"Mejora parcial",IF(AND(OR(F13="Cumple",F13="Sin ejecutar"),OR(O13="NO CUMPLE",O13="PARCIAL")),IF(F13="Cumple","Regresión","Falla nueva"),IF(AND(F13="No cumple",O13="NO CUMPLE"),"Sigue fallando","Se mantiene"))))))))
A14: 2 | B14: 2 | C14: Seleccionar cliente Coisa Consultores Industriales | F14: Cumple | O14: =IF(M14<>"",M14,IF(K14<>"",K14,IF(I14<>"",I14,""))) | P14: =IF(O14="","",IF(O14="PENDIENTE","Pendiente",IF(O14="NO EJECUTABLE","No ejecutable",IF(O14="VERIFICAR","Por verificar",IF(AND(F14="No cumple",O14="CUMPLE"),"Mejora",IF(AND(F14="No cumple",O14="PARCIAL"),"Mejora parcial",IF(AND(OR(F14="Cumple",F14="Sin ejecutar"),OR(O14="NO CUMPLE",O14="PARCIAL")),IF(F14="Cumple","Regresión","Falla nueva"),IF(AND(F14="No cumple",O14="NO CUMPLE"),"Sigue fallando","Se mantiene"))))))))
A15: 3 | B15: 3 | C15: Validar lista de contactos | D15: Los contactos mostrados deben pertenecer al cliente | F15: Cumple | O15: =IF(M15<>"",M15,IF(K15<>"",K15,IF(I15<>"",I15,""))) | P15: =IF(O15="","",IF(O15="PENDIENTE","Pendiente",IF(O15="NO EJECUTABLE","No ejecutable",IF(O15="VERIFICAR","Por verificar",IF(AND(F15="No cumple",O15="CUMPLE"),"Mejora",IF(AND(F15="No cumple",O15="PARCIAL"),"Mejora parcial",IF(AND(OR(F15="Cumple",F15="Sin ejecutar"),OR(O15="NO CUMPLE",O15="PARCIAL")),IF(F15="Cumple","Regresión","Falla nueva"),IF(AND(F15="No cumple",O15="NO CUMPLE"),"Sigue fallando","Se mantiene"))))))))
A16: 4 | B16: 4 | C16: Seleccionar un evento (Si no está crear uno) | F16: Cumple | O16: =IF(M16<>"",M16,IF(K16<>"",K16,IF(I16<>"",I16,""))) | P16: =IF(O16="","",IF(O16="PENDIENTE","Pendiente",IF(O16="NO EJECUTABLE","No ejecutable",IF(O16="VERIFICAR","Por verificar",IF(AND(F16="No cumple",O16="CUMPLE"),"Mejora",IF(AND(F16="No cumple",O16="PARCIAL"),"Mejora parcial",IF(AND(OR(F16="Cumple",F16="Sin ejecutar"),OR(O16="NO CUMPLE",O16="PARCIAL")),IF(F16="Cumple","Regresión","Falla nueva"),IF(AND(F16="No cumple",O16="NO CUMPLE"),"Sigue fallando","Se mantiene"))))))))
A17: 5 | B17: 5 | C17: Seleccionar UN Seguridad | D17: El sistema despliega los PEPS de la UN de seguridad, y la sociedad pagadora | F17: Cumple | O17: =IF(M17<>"",M17,IF(K17<>"",K17,IF(I17<>"",I17,""))) | P17: =IF(O17="","",IF(O17="PENDIENTE","Pendiente",IF(O17="NO EJECUTABLE","No ejecutable",IF(O17="VERIFICAR","Por verificar",IF(AND(F17="No cumple",O17="CUMPLE"),"Mejora",IF(AND(F17="No cumple",O17="PARCIAL"),"Mejora parcial",IF(AND(OR(F17="Cumple",F17="Sin ejecutar"),OR(O17="NO CUMPLE",O17="PARCIAL")),IF(F17="Cumple","Regresión","Falla nueva"),IF(AND(F17="No cumple",O17="NO CUMPLE"),"Sigue fallando","Se mantiene"))))))))
A18: 6 | B18: 6 | C18: Seleccionar el PEPS LT-AZ-2018-01-01N085LT-A | D18: El sistema me muestra el nombre y la dirección del inmueble. Validar también que el lugar de cita es el Estadio Azteca | F18: Cumple | O18: =IF(M18<>"",M18,IF(K18<>"",K18,IF(I18<>"",I18,""))) | P18: =IF(O18="","",IF(O18="PENDIENTE","Pendiente",IF(O18="NO EJECUTABLE","No ejecutable",IF(O18="VERIFICAR","Por verificar",IF(AND(F18="No cumple",O18="CUMPLE"),"Mejora",IF(AND(F18="No cumple",O18="PARCIAL"),"Mejora parcial",IF(AND(OR(F18="Cumple",F18="Sin ejecutar"),OR(O18="NO CUMPLE",O18="PARCIAL")),IF(F18="Cumple","Regresión","Falla nueva"),IF(AND(F18="No cumple",O18="NO CUMPLE"),"Sigue fallando","Se mantiene"))))))))
A19: 7 | B19: 7 | C19: Validar tipo de movimiento | D19: El sistema debe mostrar dos tipos de movimiento (Pedido y Servicio Interno) | F19: No cumple | H19: Corregido | O19: =IF(M19<>"",M19,IF(K19<>"",K19,IF(I19<>"",I19,""))) | P19: =IF(O19="","",IF(O19="PENDIENTE","Pendiente",IF(O19="NO EJECUTABLE","No ejecutable",IF(O19="VERIFICAR","Por verificar",IF(AND(F19="No cumple",O19="CUMPLE"),"Mejora",IF(AND(F19="No cumple",O19="PARCIAL"),"Mejora parcial",IF(AND(OR(F19="Cumple",F19="Sin ejecutar"),OR(O19="NO CUMPLE",O19="PARCIAL")),IF(F19="Cumple","Regresión","Falla nueva"),IF(AND(F19="No cumple",O19="NO CUMPLE"),"Sigue fallando","Se mantiene"))))))))
A20: 8 | B20: 8 | C20: Seleccionar Tipo de movimiento Pedido | D20: EL tipo Pedido se factura (validar posteriormente) | F20: No cumple | G20: Factura está determinado como de No por default | H20: Corregido | O20: =IF(M20<>"",M20,IF(K20<>"",K20,IF(I20<>"",I20,""))) | P20: =IF(O20="","",IF(O20="PENDIENTE","Pendiente",IF(O20="NO EJECUTABLE","No ejecutable",IF(O20="VERIFICAR","Por verificar",IF(AND(F20="No cumple",O20="CUMPLE"),"Mejora",IF(AND(F20="No cumple",O20="PARCIAL"),"Mejora parcial",IF(AND(OR(F20="Cumple",F20="Sin ejecutar"),OR(O20="NO CUMPLE",O20="PARCIAL")),IF(F20="Cumple","Regresión","Falla nueva"),IF(AND(F20="No cumple",O20="NO CUMPLE"),"Sigue fallando","Se mantiene"))))))))
A21: 9 | B21: 9 | C21: En el campo Permitir Cancelar, seleccionar NO | F21: Cumple | O21: =IF(M21<>"",M21,IF(K21<>"",K21,IF(I21<>"",I21,""))) | P21: =IF(O21="","",IF(O21="PENDIENTE","Pendiente",IF(O21="NO EJECUTABLE","No ejecutable",IF(O21="VERIFICAR","Por verificar",IF(AND(F21="No cumple",O21="CUMPLE"),"Mejora",IF(AND(F21="No cumple",O21="PARCIAL"),"Mejora parcial",IF(AND(OR(F21="Cumple",F21="Sin ejecutar"),OR(O21="NO CUMPLE",O21="PARCIAL")),IF(F21="Cumple","Regresión","Falla nueva"),IF(AND(F21="No cumple",O21="NO CUMPLE"),"Sigue fallando","Se mantiene"))))))))
A22: 10 | B22: 10 | C22: Incluir un Responsable del Pedido | F22: Cumple | O22: =IF(M22<>"",M22,IF(K22<>"",K22,IF(I22<>"",I22,""))) | P22: =IF(O22="","",IF(O22="PENDIENTE","Pendiente",IF(O22="NO EJECUTABLE","No ejecutable",IF(O22="VERIFICAR","Por verificar",IF(AND(F22="No cumple",O22="CUMPLE"),"Mejora",IF(AND(F22="No cumple",O22="PARCIAL"),"Mejora parcial",IF(AND(OR(F22="Cumple",F22="Sin ejecutar"),OR(O22="NO CUMPLE",O22="PARCIAL")),IF(F22="Cumple","Regresión","Falla nueva"),IF(AND(F22="No cumple",O22="NO CUMPLE"),"Sigue fallando","Se mantiene"))))))))
A23: 11 | B23: 11 | C23: Pulsar Aceptar | D23: El sistema genera un número consecutivo de pedido. | F23: Cumple | O23: =IF(M23<>"",M23,IF(K23<>"",K23,IF(I23<>"",I23,""))) | P23: =IF(O23="","",IF(O23="PENDIENTE","Pendiente",IF(O23="NO EJECUTABLE","No ejecutable",IF(O23="VERIFICAR","Por verificar",IF(AND(F23="No cumple",O23="CUMPLE"),"Mejora",IF(AND(F23="No cumple",O23="PARCIAL"),"Mejora parcial",IF(AND(OR(F23="Cumple",F23="Sin ejecutar"),OR(O23="NO CUMPLE",O23="PARCIAL")),IF(F23="Cumple","Regresión","Falla nueva"),IF(AND(F23="No cumple",O23="NO CUMPLE"),"Sigue fallando","Se mantiene"))))))))
C24: Pedido Detalle
A25: 12 | B25: 12 | C25: Validar Estatus del Pedido | D25: Debe estar en estado Normal | F25: No cumple | H25: Corregido | O25: =IF(M25<>"",M25,IF(K25<>"",K25,IF(I25<>"",I25,""))) | P25: =IF(O25="","",IF(O25="PENDIENTE","Pendiente",IF(O25="NO EJECUTABLE","No ejecutable",IF(O25="VERIFICAR","Por verificar",IF(AND(F25="No cumple",O25="CUMPLE"),"Mejora",IF(AND(F25="No cumple",O25="PARCIAL"),"Mejora parcial",IF(AND(OR(F25="Cumple",F25="Sin ejecutar"),OR(O25="NO CUMPLE",O25="PARCIAL")),IF(F25="Cumple","Regresión","Falla nueva"),IF(AND(F25="No cumple",O25="NO CUMPLE"),"Sigue fallando","Se mantiene"))))))))
A26: 13 | B26: 13 | C26: Seleccionar Tipo de Personal Operativo | D26: Validar que sólo se muestre Operativo por default ser un pedido de seguridad | F26: Cumple | O26: =IF(M26<>"",M26,IF(K26<>"",K26,IF(I26<>"",I26,""))) | P26: =IF(O26="","",IF(O26="PENDIENTE","Pendiente",IF(O26="NO EJECUTABLE","No ejecutable",IF(O26="VERIFICAR","Por verificar",IF(AND(F26="No cumple",O26="CUMPLE"),"Mejora",IF(AND(F26="No cumple",O26="PARCIAL"),"Mejora parcial",IF(AND(OR(F26="Cumple",F26="Sin ejecutar"),OR(O26="NO CUMPLE",O26="PARCIAL")),IF(F26="Cumple","Regresión","Falla nueva"),IF(AND(F26="No cumple",O26="NO CUMPLE"),"Sigue fallando","Se mantiene"))))))))
A27: 14 | B27: 14 | C27: Validar que Tïtulo, Lugar de Cita, Facturable vienen prerellenos | D27: Validar que se muestran todos los productos de Seguridad | F27: Cumple | O27: =IF(M27<>"",M27,IF(K27<>"",K27,IF(I27<>"",I27,""))) | P27: =IF(O27="","",IF(O27="PENDIENTE","Pendiente",IF(O27="NO EJECUTABLE","No ejecutable",IF(O27="VERIFICAR","Por verificar",IF(AND(F27="No cumple",O27="CUMPLE"),"Mejora",IF(AND(F27="No cumple",O27="PARCIAL"),"Mejora parcial",IF(AND(OR(F27="Cumple",F27="Sin ejecutar"),OR(O27="NO CUMPLE",O27="PARCIAL")),IF(F27="Cumple","Regresión","Falla nueva"),IF(AND(F27="No cumple",O27="NO CUMPLE"),"Sigue fallando","Se mantiene"))))))))
A28: 15 | B28: 15 | C28: Editar el Título | D28: Validar que se puda editar el Título | F28: Cumple | O28: =IF(M28<>"",M28,IF(K28<>"",K28,IF(I28<>"",I28,""))) | P28: =IF(O28="","",IF(O28="PENDIENTE","Pendiente",IF(O28="NO EJECUTABLE","No ejecutable",IF(O28="VERIFICAR","Por verificar",IF(AND(F28="No cumple",O28="CUMPLE"),"Mejora",IF(AND(F28="No cumple",O28="PARCIAL"),"Mejora parcial",IF(AND(OR(F28="Cumple",F28="Sin ejecutar"),OR(O28="NO CUMPLE",O28="PARCIAL")),IF(F28="Cumple","Regresión","Falla nueva"),IF(AND(F28="No cumple",O28="NO CUMPLE"),"Sigue fallando","Se mantiene"))))))))
A29: 16 | B29: 16 | C29: Seleccionar Producto Anfitrion-IN | F29: No cumple | G29: Se seleccionó Anfitrión incluyente-IN | O29: =IF(M29<>"",M29,IF(K29<>"",K29,IF(I29<>"",I29,""))) | P29: =IF(O29="","",IF(O29="PENDIENTE","Pendiente",IF(O29="NO EJECUTABLE","No ejecutable",IF(O29="VERIFICAR","Por verificar",IF(AND(F29="No cumple",O29="CUMPLE"),"Mejora",IF(AND(F29="No cumple",O29="PARCIAL"),"Mejora parcial",IF(AND(OR(F29="Cumple",F29="Sin ejecutar"),OR(O29="NO CUMPLE",O29="PARCIAL")),IF(F29="Cumple","Regresión","Falla nueva"),IF(AND(F29="No cumple",O29="NO CUMPLE"),"Sigue fallando","Se mantiene"))))))))
A30: 17 | B30: 17 | C30: Validar que el sistema muestra las horas por turno de ese producto | D30: Se muestra 1 turno por 8 horas | F30: No cumple | G30: En ningún momento se muestra esa información | H30: Corregido | O30: =IF(M30<>"",M30,IF(K30<>"",K30,IF(I30<>"",I30,""))) | P30: =IF(O30="","",IF(O30="PENDIENTE","Pendiente",IF(O30="NO EJECUTABLE","No ejecutable",IF(O30="VERIFICAR","Por verificar",IF(AND(F30="No cumple",O30="CUMPLE"),"Mejora",IF(AND(F30="No cumple",O30="PARCIAL"),"Mejora parcial",IF(AND(OR(F30="Cumple",F30="Sin ejecutar"),OR(O30="NO CUMPLE",O30="PARCIAL")),IF(F30="Cumple","Regresión","Falla nueva"),IF(AND(F30="No cumple",O30="NO CUMPLE"),"Sigue fallando","Se mantiene"))))))))
A31: 18 | B31: 18 | C31: Poner Cantidad 40 y Turnos 1 | F31: Cumple | O31: =IF(M31<>"",M31,IF(K31<>"",K31,IF(I31<>"",I31,""))) | P31: =IF(O31="","",IF(O31="PENDIENTE","Pendiente",IF(O31="NO EJECUTABLE","No ejecutable",IF(O31="VERIFICAR","Por verificar",IF(AND(F31="No cumple",O31="CUMPLE"),"Mejora",IF(AND(F31="No cumple",O31="PARCIAL"),"Mejora parcial",IF(AND(OR(F31="Cumple",F31="Sin ejecutar"),OR(O31="NO CUMPLE",O31="PARCIAL")),IF(F31="Cumple","Regresión","Falla nueva"),IF(AND(F31="No cumple",O31="NO CUMPLE"),"Sigue fallando","Se mantiene"))))))))
A32: 19 | B32: 19 | C32: Seleccionar cualquier Fecha de Cita | F32: Cumple | O32: =IF(M32<>"",M32,IF(K32<>"",K32,IF(I32<>"",I32,""))) | P32: =IF(O32="","",IF(O32="PENDIENTE","Pendiente",IF(O32="NO EJECUTABLE","No ejecutable",IF(O32="VERIFICAR","Por verificar",IF(AND(F32="No cumple",O32="CUMPLE"),"Mejora",IF(AND(F32="No cumple",O32="PARCIAL"),"Mejora parcial",IF(AND(OR(F32="Cumple",F32="Sin ejecutar"),OR(O32="NO CUMPLE",O32="PARCIAL")),IF(F32="Cumple","Regresión","Falla nueva"),IF(AND(F32="No cumple",O32="NO CUMPLE"),"Sigue fallando","Se mantiene"))))))))
A33: 20 | B33: 20 | C33: Seleccionar una fecha de liberación posterior | D33: El sistema debe de mostrar una alerta por que no puede ser la fecha de liberación posterior a la fecha de cita | F33: Cumple | O33: =IF(M33<>"",M33,IF(K33<>"",K33,IF(I33<>"",I33,""))) | P33: =IF(O33="","",IF(O33="PENDIENTE","Pendiente",IF(O33="NO EJECUTABLE","No ejecutable",IF(O33="VERIFICAR","Por verificar",IF(AND(F33="No cumple",O33="CUMPLE"),"Mejora",IF(AND(F33="No cumple",O33="PARCIAL"),"Mejora parcial",IF(AND(OR(F33="Cumple",F33="Sin ejecutar"),OR(O33="NO CUMPLE",O33="PARCIAL")),IF(F33="Cumple","Regresión","Falla nueva"),IF(AND(F33="No cumple",O33="NO CUMPLE"),"Sigue fallando","Se mantiene"))))))))
A34: 21 | B34: 21 | C34: Seleccionar una fecha correcta de liberación | F34: Cumple | O34: =IF(M34<>"",M34,IF(K34<>"",K34,IF(I34<>"",I34,""))) | P34: =IF(O34="","",IF(O34="PENDIENTE","Pendiente",IF(O34="NO EJECUTABLE","No ejecutable",IF(O34="VERIFICAR","Por verificar",IF(AND(F34="No cumple",O34="CUMPLE"),"Mejora",IF(AND(F34="No cumple",O34="PARCIAL"),"Mejora parcial",IF(AND(OR(F34="Cumple",F34="Sin ejecutar"),OR(O34="NO CUMPLE",O34="PARCIAL")),IF(F34="Cumple","Regresión","Falla nueva"),IF(AND(F34="No cumple",O34="NO CUMPLE"),"Sigue fallando","Se mantiene"))))))))
A35: 22 | B35: 22 | C35: En presentación por producto, validar que sólo muentren las de la unidad de negocio | F35: Cumple | O35: =IF(M35<>"",M35,IF(K35<>"",K35,IF(I35<>"",I35,""))) | P35: =IF(O35="","",IF(O35="PENDIENTE","Pendiente",IF(O35="NO EJECUTABLE","No ejecutable",IF(O35="VERIFICAR","Por verificar",IF(AND(F35="No cumple",O35="CUMPLE"),"Mejora",IF(AND(F35="No cumple",O35="PARCIAL"),"Mejora parcial",IF(AND(OR(F35="Cumple",F35="Sin ejecutar"),OR(O35="NO CUMPLE",O35="PARCIAL")),IF(F35="Cumple","Regresión","Falla nueva"),IF(AND(F35="No cumple",O35="NO CUMPLE"),"Sigue fallando","Se mantiene"))))))))
A36: 23 | B36: 23 | C36: Completar con similares - Marcar NO | F36: Cumple | O36: =IF(M36<>"",M36,IF(K36<>"",K36,IF(I36<>"",I36,""))) | P36: =IF(O36="","",IF(O36="PENDIENTE","Pendiente",IF(O36="NO EJECUTABLE","No ejecutable",IF(O36="VERIFICAR","Por verificar",IF(AND(F36="No cumple",O36="CUMPLE"),"Mejora",IF(AND(F36="No cumple",O36="PARCIAL"),"Mejora parcial",IF(AND(OR(F36="Cumple",F36="Sin ejecutar"),OR(O36="NO CUMPLE",O36="PARCIAL")),IF(F36="Cumple","Regresión","Falla nueva"),IF(AND(F36="No cumple",O36="NO CUMPLE"),"Sigue fallando","Se mantiene"))))))))
A37: 24 | B37: 24 | C37: Agregar registro | D37: Validamos que se muestra la Matriz de información (Fecha, hora, productos, Turnos, Totales (personal y monto)) Validar el ID del Detalle del pedido | F37: Cumple | O37: =IF(M37<>"",M37,IF(K37<>"",K37,IF(I37<>"",I37,""))) | P37: =IF(O37="","",IF(O37="PENDIENTE","Pendiente",IF(O37="NO EJECUTABLE","No ejecutable",IF(O37="VERIFICAR","Por verificar",IF(AND(F37="No cumple",O37="CUMPLE"),"Mejora",IF(AND(F37="No cumple",O37="PARCIAL"),"Mejora parcial",IF(AND(OR(F37="Cumple",F37="Sin ejecutar"),OR(O37="NO CUMPLE",O37="PARCIAL")),IF(F37="Cumple","Regresión","Falla nueva"),IF(AND(F37="No cumple",O37="NO CUMPLE"),"Sigue fallando","Se mantiene"))))))))
A38: 25 | B38: 25 | C38: Seleccionar Producto Anfitrion Uncluyente-IN | F38: Sin ejecutar | O38: =IF(M38<>"",M38,IF(K38<>"",K38,IF(I38<>"",I38,""))) | P38: =IF(O38="","",IF(O38="PENDIENTE","Pendiente",IF(O38="NO EJECUTABLE","No ejecutable",IF(O38="VERIFICAR","Por verificar",IF(AND(F38="No cumple",O38="CUMPLE"),"Mejora",IF(AND(F38="No cumple",O38="PARCIAL"),"Mejora parcial",IF(AND(OR(F38="Cumple",F38="Sin ejecutar"),OR(O38="NO CUMPLE",O38="PARCIAL")),IF(F38="Cumple","Regresión","Falla nueva"),IF(AND(F38="No cumple",O38="NO CUMPLE"),"Sigue fallando","Se mantiene"))))))))
A39: 26 | B39: 26 | C39: Validar que el sistema muestra las horas por turno de ese producto | D39: Se muestra 1 turno por 8 horas | F39: No cumple | O39: =IF(M39<>"",M39,IF(K39<>"",K39,IF(I39<>"",I39,""))) | P39: =IF(O39="","",IF(O39="PENDIENTE","Pendiente",IF(O39="NO EJECUTABLE","No ejecutable",IF(O39="VERIFICAR","Por verificar",IF(AND(F39="No cumple",O39="CUMPLE"),"Mejora",IF(AND(F39="No cumple",O39="PARCIAL"),"Mejora parcial",IF(AND(OR(F39="Cumple",F39="Sin ejecutar"),OR(O39="NO CUMPLE",O39="PARCIAL")),IF(F39="Cumple","Regresión","Falla nueva"),IF(AND(F39="No cumple",O39="NO CUMPLE"),"Sigue fallando","Se mantiene"))))))))
A40: 27 | B40: 27 | C40: Poner Cantidad 40 y Turnos 1 | F40: Cumple | O40: =IF(M40<>"",M40,IF(K40<>"",K40,IF(I40<>"",I40,""))) | P40: =IF(O40="","",IF(O40="PENDIENTE","Pendiente",IF(O40="NO EJECUTABLE","No ejecutable",IF(O40="VERIFICAR","Por verificar",IF(AND(F40="No cumple",O40="CUMPLE"),"Mejora",IF(AND(F40="No cumple",O40="PARCIAL"),"Mejora parcial",IF(AND(OR(F40="Cumple",F40="Sin ejecutar"),OR(O40="NO CUMPLE",O40="PARCIAL")),IF(F40="Cumple","Regresión","Falla nueva"),IF(AND(F40="No cumple",O40="NO CUMPLE"),"Sigue fallando","Se mantiene"))))))))
A41: 28 | B41: 28 | C41: Seleccionar La misma fecha de cita que en el caso anterior | F41: Cumple | O41: =IF(M41<>"",M41,IF(K41<>"",K41,IF(I41<>"",I41,""))) | P41: =IF(O41="","",IF(O41="PENDIENTE","Pendiente",IF(O41="NO EJECUTABLE","No ejecutable",IF(O41="VERIFICAR","Por verificar",IF(AND(F41="No cumple",O41="CUMPLE"),"Mejora",IF(AND(F41="No cumple",O41="PARCIAL"),"Mejora parcial",IF(AND(OR(F41="Cumple",F41="Sin ejecutar"),OR(O41="NO CUMPLE",O41="PARCIAL")),IF(F41="Cumple","Regresión","Falla nueva"),IF(AND(F41="No cumple",O41="NO CUMPLE"),"Sigue fallando","Se mantiene"))))))))
A42: 29 | B42: 29 | C42: Seleccionar una fecha de liberación posterior | D42: El sistema debe de mostrar una alerta por que no puede ser la fecha de liberación posterior a la fecha de cita | F42: Cumple | O42: =IF(M42<>"",M42,IF(K42<>"",K42,IF(I42<>"",I42,""))) | P42: =IF(O42="","",IF(O42="PENDIENTE","Pendiente",IF(O42="NO EJECUTABLE","No ejecutable",IF(O42="VERIFICAR","Por verificar",IF(AND(F42="No cumple",O42="CUMPLE"),"Mejora",IF(AND(F42="No cumple",O42="PARCIAL"),"Mejora parcial",IF(AND(OR(F42="Cumple",F42="Sin ejecutar"),OR(O42="NO CUMPLE",O42="PARCIAL")),IF(F42="Cumple","Regresión","Falla nueva"),IF(AND(F42="No cumple",O42="NO CUMPLE"),"Sigue fallando","Se mantiene"))))))))
A43: 30 | B43: 30 | C43: Seleccionar una fecha correcta de liberación | F43: Cumple | O43: =IF(M43<>"",M43,IF(K43<>"",K43,IF(I43<>"",I43,""))) | P43: =IF(O43="","",IF(O43="PENDIENTE","Pendiente",IF(O43="NO EJECUTABLE","No ejecutable",IF(O43="VERIFICAR","Por verificar",IF(AND(F43="No cumple",O43="CUMPLE"),"Mejora",IF(AND(F43="No cumple",O43="PARCIAL"),"Mejora parcial",IF(AND(OR(F43="Cumple",F43="Sin ejecutar"),OR(O43="NO CUMPLE",O43="PARCIAL")),IF(F43="Cumple","Regresión","Falla nueva"),IF(AND(F43="No cumple",O43="NO CUMPLE"),"Sigue fallando","Se mantiene"))))))))
A44: 31 | B44: 31 | C44: En presentación por producto, validar que sólo muentren las de la unidad de negocio | F44: Cumple | O44: =IF(M44<>"",M44,IF(K44<>"",K44,IF(I44<>"",I44,""))) | P44: =IF(O44="","",IF(O44="PENDIENTE","Pendiente",IF(O44="NO EJECUTABLE","No ejecutable",IF(O44="VERIFICAR","Por verificar",IF(AND(F44="No cumple",O44="CUMPLE"),"Mejora",IF(AND(F44="No cumple",O44="PARCIAL"),"Mejora parcial",IF(AND(OR(F44="Cumple",F44="Sin ejecutar"),OR(O44="NO CUMPLE",O44="PARCIAL")),IF(F44="Cumple","Regresión","Falla nueva"),IF(AND(F44="No cumple",O44="NO CUMPLE"),"Sigue fallando","Se mantiene"))))))))
A45: 32 | B45: 32 | C45: Completar con similares - Marcar NO | F45: Cumple | O45: =IF(M45<>"",M45,IF(K45<>"",K45,IF(I45<>"",I45,""))) | P45: =IF(O45="","",IF(O45="PENDIENTE","Pendiente",IF(O45="NO EJECUTABLE","No ejecutable",IF(O45="VERIFICAR","Por verificar",IF(AND(F45="No cumple",O45="CUMPLE"),"Mejora",IF(AND(F45="No cumple",O45="PARCIAL"),"Mejora parcial",IF(AND(OR(F45="Cumple",F45="Sin ejecutar"),OR(O45="NO CUMPLE",O45="PARCIAL")),IF(F45="Cumple","Regresión","Falla nueva"),IF(AND(F45="No cumple",O45="NO CUMPLE"),"Sigue fallando","Se mantiene"))))))))
A46: 33 | B46: 33 | C46: Agregar registro | D46: Validamos que se muestra la Matriz de información (Fecha, hora, productos, Turnos, Totales (personal y monto)) Validar el ID del Detalle del pedido | F46: Sin ejecutar | O46: =IF(M46<>"",M46,IF(K46<>"",K46,IF(I46<>"",I46,""))) | P46: =IF(O46="","",IF(O46="PENDIENTE","Pendiente",IF(O46="NO EJECUTABLE","No ejecutable",IF(O46="VERIFICAR","Por verificar",IF(AND(F46="No cumple",O46="CUMPLE"),"Mejora",IF(AND(F46="No cumple",O46="PARCIAL"),"Mejora parcial",IF(AND(OR(F46="Cumple",F46="Sin ejecutar"),OR(O46="NO CUMPLE",O46="PARCIAL")),IF(F46="Cumple","Regresión","Falla nueva"),IF(AND(F46="No cumple",O46="NO CUMPLE"),"Sigue fallando","Se mantiene"))))))))
A47: 34 | B47: 34 | C47: Seleccionar Producto Control de Accesos - FE | F47: Sin ejecutar | O47: =IF(M47<>"",M47,IF(K47<>"",K47,IF(I47<>"",I47,""))) | P47: =IF(O47="","",IF(O47="PENDIENTE","Pendiente",IF(O47="NO EJECUTABLE","No ejecutable",IF(O47="VERIFICAR","Por verificar",IF(AND(F47="No cumple",O47="CUMPLE"),"Mejora",IF(AND(F47="No cumple",O47="PARCIAL"),"Mejora parcial",IF(AND(OR(F47="Cumple",F47="Sin ejecutar"),OR(O47="NO CUMPLE",O47="PARCIAL")),IF(F47="Cumple","Regresión","Falla nueva"),IF(AND(F47="No cumple",O47="NO CUMPLE"),"Sigue fallando","Se mantiene"))))))))
A48: 35 | B48: 35 | C48: Validar que el sistema muestra las horas por turno de ese producto | D48: Se muestra 1 turno por 8 horas | F48: Sin ejecutar | O48: =IF(M48<>"",M48,IF(K48<>"",K48,IF(I48<>"",I48,""))) | P48: =IF(O48="","",IF(O48="PENDIENTE","Pendiente",IF(O48="NO EJECUTABLE","No ejecutable",IF(O48="VERIFICAR","Por verificar",IF(AND(F48="No cumple",O48="CUMPLE"),"Mejora",IF(AND(F48="No cumple",O48="PARCIAL"),"Mejora parcial",IF(AND(OR(F48="Cumple",F48="Sin ejecutar"),OR(O48="NO CUMPLE",O48="PARCIAL")),IF(F48="Cumple","Regresión","Falla nueva"),IF(AND(F48="No cumple",O48="NO CUMPLE"),"Sigue fallando","Se mantiene"))))))))
A49: 36 | B49: 36 | C49: Poner Cantidad 30 y Turnos 1 | F49: Sin ejecutar | O49: =IF(M49<>"",M49,IF(K49<>"",K49,IF(I49<>"",I49,""))) | P49: =IF(O49="","",IF(O49="PENDIENTE","Pendiente",IF(O49="NO EJECUTABLE","No ejecutable",IF(O49="VERIFICAR","Por verificar",IF(AND(F49="No cumple",O49="CUMPLE"),"Mejora",IF(AND(F49="No cumple",O49="PARCIAL"),"Mejora parcial",IF(AND(OR(F49="Cumple",F49="Sin ejecutar"),OR(O49="NO CUMPLE",O49="PARCIAL")),IF(F49="Cumple","Regresión","Falla nueva"),IF(AND(F49="No cumple",O49="NO CUMPLE"),"Sigue fallando","Se mantiene"))))))))
A50: 37 | B50: 37 | C50: Seleccionar La misma fecha de cita que en el caso anterior | F50: Sin ejecutar | O50: =IF(M50<>"",M50,IF(K50<>"",K50,IF(I50<>"",I50,""))) | P50: =IF(O50="","",IF(O50="PENDIENTE","Pendiente",IF(O50="NO EJECUTABLE","No ejecutable",IF(O50="VERIFICAR","Por verificar",IF(AND(F50="No cumple",O50="CUMPLE"),"Mejora",IF(AND(F50="No cumple",O50="PARCIAL"),"Mejora parcial",IF(AND(OR(F50="Cumple",F50="Sin ejecutar"),OR(O50="NO CUMPLE",O50="PARCIAL")),IF(F50="Cumple","Regresión","Falla nueva"),IF(AND(F50="No cumple",O50="NO CUMPLE"),"Sigue fallando","Se mantiene"))))))))
A51: 38 | B51: 38 | C51: Seleccionar una fecha de liberación posterior | D51: El sistema debe de mostrar una alerta por que no puede ser la fecha de liberación posterior a la fecha de cita | F51: Sin ejecutar | O51: =IF(M51<>"",M51,IF(K51<>"",K51,IF(I51<>"",I51,""))) | P51: =IF(O51="","",IF(O51="PENDIENTE","Pendiente",IF(O51="NO EJECUTABLE","No ejecutable",IF(O51="VERIFICAR","Por verificar",IF(AND(F51="No cumple",O51="CUMPLE"),"Mejora",IF(AND(F51="No cumple",O51="PARCIAL"),"Mejora parcial",IF(AND(OR(F51="Cumple",F51="Sin ejecutar"),OR(O51="NO CUMPLE",O51="PARCIAL")),IF(F51="Cumple","Regresión","Falla nueva"),IF(AND(F51="No cumple",O51="NO CUMPLE"),"Sigue fallando","Se mantiene"))))))))
A52: 39 | B52: 39 | C52: Seleccionar una fecha correcta de liberación | F52: Sin ejecutar | O52: =IF(M52<>"",M52,IF(K52<>"",K52,IF(I52<>"",I52,""))) | P52: =IF(O52="","",IF(O52="PENDIENTE","Pendiente",IF(O52="NO EJECUTABLE","No ejecutable",IF(O52="VERIFICAR","Por verificar",IF(AND(F52="No cumple",O52="CUMPLE"),"Mejora",IF(AND(F52="No cumple",O52="PARCIAL"),"Mejora parcial",IF(AND(OR(F52="Cumple",F52="Sin ejecutar"),OR(O52="NO CUMPLE",O52="PARCIAL")),IF(F52="Cumple","Regresión","Falla nueva"),IF(AND(F52="No cumple",O52="NO CUMPLE"),"Sigue fallando","Se mantiene"))))))))
A53: 40 | B53: 40 | C53: En presentación por producto, validar que sólo muentren las de la unidad de negocio | F53: Sin ejecutar | O53: =IF(M53<>"",M53,IF(K53<>"",K53,IF(I53<>"",I53,""))) | P53: =IF(O53="","",IF(O53="PENDIENTE","Pendiente",IF(O53="NO EJECUTABLE","No ejecutable",IF(O53="VERIFICAR","Por verificar",IF(AND(F53="No cumple",O53="CUMPLE"),"Mejora",IF(AND(F53="No cumple",O53="PARCIAL"),"Mejora parcial",IF(AND(OR(F53="Cumple",F53="Sin ejecutar"),OR(O53="NO CUMPLE",O53="PARCIAL")),IF(F53="Cumple","Regresión","Falla nueva"),IF(AND(F53="No cumple",O53="NO CUMPLE"),"Sigue fallando","Se mantiene"))))))))
A54: 41 | B54: 41 | C54: Completar con similares - Marcar NO | F54: Sin ejecutar | O54: =IF(M54<>"",M54,IF(K54<>"",K54,IF(I54<>"",I54,""))) | P54: =IF(O54="","",IF(O54="PENDIENTE","Pendiente",IF(O54="NO EJECUTABLE","No ejecutable",IF(O54="VERIFICAR","Por verificar",IF(AND(F54="No cumple",O54="CUMPLE"),"Mejora",IF(AND(F54="No cumple",O54="PARCIAL"),"Mejora parcial",IF(AND(OR(F54="Cumple",F54="Sin ejecutar"),OR(O54="NO CUMPLE",O54="PARCIAL")),IF(F54="Cumple","Regresión","Falla nueva"),IF(AND(F54="No cumple",O54="NO CUMPLE"),"Sigue fallando","Se mantiene"))))))))
A55: 42 | B55: 42 | C55: Agregar registro | D55: Validamos que se muestra la Matriz de información (Fecha, hora, productos, Turnos, Totales (personal y monto)) Validar el ID del Detalle del pedido | F55: Sin ejecutar | O55: =IF(M55<>"",M55,IF(K55<>"",K55,IF(I55<>"",I55,""))) | P55: =IF(O55="","",IF(O55="PENDIENTE","Pendiente",IF(O55="NO EJECUTABLE","No ejecutable",IF(O55="VERIFICAR","Por verificar",IF(AND(F55="No cumple",O55="CUMPLE"),"Mejora",IF(AND(F55="No cumple",O55="PARCIAL"),"Mejora parcial",IF(AND(OR(F55="Cumple",F55="Sin ejecutar"),OR(O55="NO CUMPLE",O55="PARCIAL")),IF(F55="Cumple","Regresión","Falla nueva"),IF(AND(F55="No cumple",O55="NO CUMPLE"),"Sigue fallando","Se mantiene"))))))))
A56: 43 | B56: 43 | C56: Seleccionar Producto Control de Accesos - MA | F56: Sin ejecutar | O56: =IF(M56<>"",M56,IF(K56<>"",K56,IF(I56<>"",I56,""))) | P56: =IF(O56="","",IF(O56="PENDIENTE","Pendiente",IF(O56="NO EJECUTABLE","No ejecutable",IF(O56="VERIFICAR","Por verificar",IF(AND(F56="No cumple",O56="CUMPLE"),"Mejora",IF(AND(F56="No cumple",O56="PARCIAL"),"Mejora parcial",IF(AND(OR(F56="Cumple",F56="Sin ejecutar"),OR(O56="NO CUMPLE",O56="PARCIAL")),IF(F56="Cumple","Regresión","Falla nueva"),IF(AND(F56="No cumple",O56="NO CUMPLE"),"Sigue fallando","Se mantiene"))))))))
A57: 44 | B57: 44 | C57: Validar que el sistema muestra las horas por turno de ese producto | D57: Se muestra 1 turno por 8 horas | F57: Sin ejecutar | O57: =IF(M57<>"",M57,IF(K57<>"",K57,IF(I57<>"",I57,""))) | P57: =IF(O57="","",IF(O57="PENDIENTE","Pendiente",IF(O57="NO EJECUTABLE","No ejecutable",IF(O57="VERIFICAR","Por verificar",IF(AND(F57="No cumple",O57="CUMPLE"),"Mejora",IF(AND(F57="No cumple",O57="PARCIAL"),"Mejora parcial",IF(AND(OR(F57="Cumple",F57="Sin ejecutar"),OR(O57="NO CUMPLE",O57="PARCIAL")),IF(F57="Cumple","Regresión","Falla nueva"),IF(AND(F57="No cumple",O57="NO CUMPLE"),"Sigue fallando","Se mantiene"))))))))
A58: 45 | B58: 45 | C58: Poner Cantidad 30 y Turnos 1 | F58: Sin ejecutar | O58: =IF(M58<>"",M58,IF(K58<>"",K58,IF(I58<>"",I58,""))) | P58: =IF(O58="","",IF(O58="PENDIENTE","Pendiente",IF(O58="NO EJECUTABLE","No ejecutable",IF(O58="VERIFICAR","Por verificar",IF(AND(F58="No cumple",O58="CUMPLE"),"Mejora",IF(AND(F58="No cumple",O58="PARCIAL"),"Mejora parcial",IF(AND(OR(F58="Cumple",F58="Sin ejecutar"),OR(O58="NO CUMPLE",O58="PARCIAL")),IF(F58="Cumple","Regresión","Falla nueva"),IF(AND(F58="No cumple",O58="NO CUMPLE"),"Sigue fallando","Se mantiene"))))))))
A59: 46 | B59: 46 | C59: Seleccionar La misma fecha de cita que en el caso anterior | F59: Sin ejecutar | O59: =IF(M59<>"",M59,IF(K59<>"",K59,IF(I59<>"",I59,""))) | P59: =IF(O59="","",IF(O59="PENDIENTE","Pendiente",IF(O59="NO EJECUTABLE","No ejecutable",IF(O59="VERIFICAR","Por verificar",IF(AND(F59="No cumple",O59="CUMPLE"),"Mejora",IF(AND(F59="No cumple",O59="PARCIAL"),"Mejora parcial",IF(AND(OR(F59="Cumple",F59="Sin ejecutar"),OR(O59="NO CUMPLE",O59="PARCIAL")),IF(F59="Cumple","Regresión","Falla nueva"),IF(AND(F59="No cumple",O59="NO CUMPLE"),"Sigue fallando","Se mantiene"))))))))
A60: 47 | B60: 47 | C60: Seleccionar una fecha de liberación posterior | D60: El sistema debe de mostrar una alerta por que no puede ser la fecha de liberación posterior a la fecha de cita | F60: Sin ejecutar | O60: =IF(M60<>"",M60,IF(K60<>"",K60,IF(I60<>"",I60,""))) | P60: =IF(O60="","",IF(O60="PENDIENTE","Pendiente",IF(O60="NO EJECUTABLE","No ejecutable",IF(O60="VERIFICAR","Por verificar",IF(AND(F60="No cumple",O60="CUMPLE"),"Mejora",IF(AND(F60="No cumple",O60="PARCIAL"),"Mejora parcial",IF(AND(OR(F60="Cumple",F60="Sin ejecutar"),OR(O60="NO CUMPLE",O60="PARCIAL")),IF(F60="Cumple","Regresión","Falla nueva"),IF(AND(F60="No cumple",O60="NO CUMPLE"),"Sigue fallando","Se mantiene"))))))))
A61: 48 | B61: 48 | C61: Seleccionar una fecha correcta de liberación | F61: Sin ejecutar | O61: =IF(M61<>"",M61,IF(K61<>"",K61,IF(I61<>"",I61,""))) | P61: =IF(O61="","",IF(O61="PENDIENTE","Pendiente",IF(O61="NO EJECUTABLE","No ejecutable",IF(O61="VERIFICAR","Por verificar",IF(AND(F61="No cumple",O61="CUMPLE"),"Mejora",IF(AND(F61="No cumple",O61="PARCIAL"),"Mejora parcial",IF(AND(OR(F61="Cumple",F61="Sin ejecutar"),OR(O61="NO CUMPLE",O61="PARCIAL")),IF(F61="Cumple","Regresión","Falla nueva"),IF(AND(F61="No cumple",O61="NO CUMPLE"),"Sigue fallando","Se mantiene"))))))))
A62: 49 | B62: 49 | C62: En presentación por producto, validar que sólo muentren las de la unidad de negocio | F62: Sin ejecutar | O62: =IF(M62<>"",M62,IF(K62<>"",K62,IF(I62<>"",I62,""))) | P62: =IF(O62="","",IF(O62="PENDIENTE","Pendiente",IF(O62="NO EJECUTABLE","No ejecutable",IF(O62="VERIFICAR","Por verificar",IF(AND(F62="No cumple",O62="CUMPLE"),"Mejora",IF(AND(F62="No cumple",O62="PARCIAL"),"Mejora parcial",IF(AND(OR(F62="Cumple",F62="Sin ejecutar"),OR(O62="NO CUMPLE",O62="PARCIAL")),IF(F62="Cumple","Regresión","Falla nueva"),IF(AND(F62="No cumple",O62="NO CUMPLE"),"Sigue fallando","Se mantiene"))))))))
A63: 50 | B63: 50 | C63: Completar con similares - Marcar NO | F63: Sin ejecutar | O63: =IF(M63<>"",M63,IF(K63<>"",K63,IF(I63<>"",I63,""))) | P63: =IF(O63="","",IF(O63="PENDIENTE","Pendiente",IF(O63="NO EJECUTABLE","No ejecutable",IF(O63="VERIFICAR","Por verificar",IF(AND(F63="No cumple",O63="CUMPLE"),"Mejora",IF(AND(F63="No cumple",O63="PARCIAL"),"Mejora parcial",IF(AND(OR(F63="Cumple",F63="Sin ejecutar"),OR(O63="NO CUMPLE",O63="PARCIAL")),IF(F63="Cumple","Regresión","Falla nueva"),IF(AND(F63="No cumple",O63="NO CUMPLE"),"Sigue fallando","Se mantiene"))))))))
A64: 51 | B64: 51 | C64: Agregar registro | D64: Validamos que se muestra la Matriz de información (Fecha, hora, productos, Turnos, Totales (personal y monto)) Validar el ID del Detalle del pedido | F64: Sin ejecutar | O64: =IF(M64<>"",M64,IF(K64<>"",K64,IF(I64<>"",I64,""))) | P64: =IF(O64="","",IF(O64="PENDIENTE","Pendiente",IF(O64="NO EJECUTABLE","No ejecutable",IF(O64="VERIFICAR","Por verificar",IF(AND(F64="No cumple",O64="CUMPLE"),"Mejora",IF(AND(F64="No cumple",O64="PARCIAL"),"Mejora parcial",IF(AND(OR(F64="Cumple",F64="Sin ejecutar"),OR(O64="NO CUMPLE",O64="PARCIAL")),IF(F64="Cumple","Regresión","Falla nueva"),IF(AND(F64="No cumple",O64="NO CUMPLE"),"Sigue fallando","Se mantiene"))))))))
A65: 52 | B65: 52 | C65: Seleccionar Producto Local Crew - FE | F65: Sin ejecutar | O65: =IF(M65<>"",M65,IF(K65<>"",K65,IF(I65<>"",I65,""))) | P65: =IF(O65="","",IF(O65="PENDIENTE","Pendiente",IF(O65="NO EJECUTABLE","No ejecutable",IF(O65="VERIFICAR","Por verificar",IF(AND(F65="No cumple",O65="CUMPLE"),"Mejora",IF(AND(F65="No cumple",O65="PARCIAL"),"Mejora parcial",IF(AND(OR(F65="Cumple",F65="Sin ejecutar"),OR(O65="NO CUMPLE",O65="PARCIAL")),IF(F65="Cumple","Regresión","Falla nueva"),IF(AND(F65="No cumple",O65="NO CUMPLE"),"Sigue fallando","Se mantiene"))))))))
A66: 53 | B66: 53 | C66: Validar que el sistema muestra las horas por turno de ese producto | D66: Se muestra 1 turno por 8 horas | F66: Sin ejecutar | O66: =IF(M66<>"",M66,IF(K66<>"",K66,IF(I66<>"",I66,""))) | P66: =IF(O66="","",IF(O66="PENDIENTE","Pendiente",IF(O66="NO EJECUTABLE","No ejecutable",IF(O66="VERIFICAR","Por verificar",IF(AND(F66="No cumple",O66="CUMPLE"),"Mejora",IF(AND(F66="No cumple",O66="PARCIAL"),"Mejora parcial",IF(AND(OR(F66="Cumple",F66="Sin ejecutar"),OR(O66="NO CUMPLE",O66="PARCIAL")),IF(F66="Cumple","Regresión","Falla nueva"),IF(AND(F66="No cumple",O66="NO CUMPLE"),"Sigue fallando","Se mantiene"))))))))
A67: 54 | B67: 54 | C67: Poner Cantidad 40 y Turnos 1 | F67: Sin ejecutar | O67: =IF(M67<>"",M67,IF(K67<>"",K67,IF(I67<>"",I67,""))) | P67: =IF(O67="","",IF(O67="PENDIENTE","Pendiente",IF(O67="NO EJECUTABLE","No ejecutable",IF(O67="VERIFICAR","Por verificar",IF(AND(F67="No cumple",O67="CUMPLE"),"Mejora",IF(AND(F67="No cumple",O67="PARCIAL"),"Mejora parcial",IF(AND(OR(F67="Cumple",F67="Sin ejecutar"),OR(O67="NO CUMPLE",O67="PARCIAL")),IF(F67="Cumple","Regresión","Falla nueva"),IF(AND(F67="No cumple",O67="NO CUMPLE"),"Sigue fallando","Se mantiene"))))))))
A68: 55 | B68: 55 | C68: Seleccionar La misma fecha de cita que en el caso anterior | F68: Sin ejecutar | O68: =IF(M68<>"",M68,IF(K68<>"",K68,IF(I68<>"",I68,""))) | P68: =IF(O68="","",IF(O68="PENDIENTE","Pendiente",IF(O68="NO EJECUTABLE","No ejecutable",IF(O68="VERIFICAR","Por verificar",IF(AND(F68="No cumple",O68="CUMPLE"),"Mejora",IF(AND(F68="No cumple",O68="PARCIAL"),"Mejora parcial",IF(AND(OR(F68="Cumple",F68="Sin ejecutar"),OR(O68="NO CUMPLE",O68="PARCIAL")),IF(F68="Cumple","Regresión","Falla nueva"),IF(AND(F68="No cumple",O68="NO CUMPLE"),"Sigue fallando","Se mantiene"))))))))
A69: 56 | B69: 56 | C69: Seleccionar una fecha de liberación posterior | D69: El sistema debe de mostrar una alerta por que no puede ser la fecha de liberación posterior a la fecha de cita | F69: Sin ejecutar | O69: =IF(M69<>"",M69,IF(K69<>"",K69,IF(I69<>"",I69,""))) | P69: =IF(O69="","",IF(O69="PENDIENTE","Pendiente",IF(O69="NO EJECUTABLE","No ejecutable",IF(O69="VERIFICAR","Por verificar",IF(AND(F69="No cumple",O69="CUMPLE"),"Mejora",IF(AND(F69="No cumple",O69="PARCIAL"),"Mejora parcial",IF(AND(OR(F69="Cumple",F69="Sin ejecutar"),OR(O69="NO CUMPLE",O69="PARCIAL")),IF(F69="Cumple","Regresión","Falla nueva"),IF(AND(F69="No cumple",O69="NO CUMPLE"),"Sigue fallando","Se mantiene"))))))))
A70: 57 | B70: 57 | C70: Seleccionar una fecha correcta de liberación | F70: Sin ejecutar | O70: =IF(M70<>"",M70,IF(K70<>"",K70,IF(I70<>"",I70,""))) | P70: =IF(O70="","",IF(O70="PENDIENTE","Pendiente",IF(O70="NO EJECUTABLE","No ejecutable",IF(O70="VERIFICAR","Por verificar",IF(AND(F70="No cumple",O70="CUMPLE"),"Mejora",IF(AND(F70="No cumple",O70="PARCIAL"),"Mejora parcial",IF(AND(OR(F70="Cumple",F70="Sin ejecutar"),OR(O70="NO CUMPLE",O70="PARCIAL")),IF(F70="Cumple","Regresión","Falla nueva"),IF(AND(F70="No cumple",O70="NO CUMPLE"),"Sigue fallando","Se mantiene"))))))))
A71: 58 | B71: 58 | C71: En presentación por producto, validar que sólo muentren las de la unidad de negocio | F71: Sin ejecutar | O71: =IF(M71<>"",M71,IF(K71<>"",K71,IF(I71<>"",I71,""))) | P71: =IF(O71="","",IF(O71="PENDIENTE","Pendiente",IF(O71="NO EJECUTABLE","No ejecutable",IF(O71="VERIFICAR","Por verificar",IF(AND(F71="No cumple",O71="CUMPLE"),"Mejora",IF(AND(F71="No cumple",O71="PARCIAL"),"Mejora parcial",IF(AND(OR(F71="Cumple",F71="Sin ejecutar"),OR(O71="NO CUMPLE",O71="PARCIAL")),IF(F71="Cumple","Regresión","Falla nueva"),IF(AND(F71="No cumple",O71="NO CUMPLE"),"Sigue fallando","Se mantiene"))))))))
A72: 59 | B72: 59 | C72: Completar con similares - Marcar NO | F72: Sin ejecutar | O72: =IF(M72<>"",M72,IF(K72<>"",K72,IF(I72<>"",I72,""))) | P72: =IF(O72="","",IF(O72="PENDIENTE","Pendiente",IF(O72="NO EJECUTABLE","No ejecutable",IF(O72="VERIFICAR","Por verificar",IF(AND(F72="No cumple",O72="CUMPLE"),"Mejora",IF(AND(F72="No cumple",O72="PARCIAL"),"Mejora parcial",IF(AND(OR(F72="Cumple",F72="Sin ejecutar"),OR(O72="NO CUMPLE",O72="PARCIAL")),IF(F72="Cumple","Regresión","Falla nueva"),IF(AND(F72="No cumple",O72="NO CUMPLE"),"Sigue fallando","Se mantiene"))))))))
A73: 60 | B73: 60 | C73: Agregar registro | D73: Validamos que se muestra la Matriz de información (Fecha, hora, productos, Turnos, Totales (personal y monto)) Validar el ID del Detalle del pedido | F73: Sin ejecutar | O73: =IF(M73<>"",M73,IF(K73<>"",K73,IF(I73<>"",I73,""))) | P73: =IF(O73="","",IF(O73="PENDIENTE","Pendiente",IF(O73="NO EJECUTABLE","No ejecutable",IF(O73="VERIFICAR","Por verificar",IF(AND(F73="No cumple",O73="CUMPLE"),"Mejora",IF(AND(F73="No cumple",O73="PARCIAL"),"Mejora parcial",IF(AND(OR(F73="Cumple",F73="Sin ejecutar"),OR(O73="NO CUMPLE",O73="PARCIAL")),IF(F73="Cumple","Regresión","Falla nueva"),IF(AND(F73="No cumple",O73="NO CUMPLE"),"Sigue fallando","Se mantiene"))))))))
A74: 61 | B74: 61 | C74: Seleccionar Producto Local Crew - MA | F74: Sin ejecutar | O74: =IF(M74<>"",M74,IF(K74<>"",K74,IF(I74<>"",I74,""))) | P74: =IF(O74="","",IF(O74="PENDIENTE","Pendiente",IF(O74="NO EJECUTABLE","No ejecutable",IF(O74="VERIFICAR","Por verificar",IF(AND(F74="No cumple",O74="CUMPLE"),"Mejora",IF(AND(F74="No cumple",O74="PARCIAL"),"Mejora parcial",IF(AND(OR(F74="Cumple",F74="Sin ejecutar"),OR(O74="NO CUMPLE",O74="PARCIAL")),IF(F74="Cumple","Regresión","Falla nueva"),IF(AND(F74="No cumple",O74="NO CUMPLE"),"Sigue fallando","Se mantiene"))))))))
A75: 62 | B75: 62 | C75: Validar que el sistema muestra las horas por turno de ese producto | D75: Se muestra 1 turno por 8 horas | F75: Sin ejecutar | O75: =IF(M75<>"",M75,IF(K75<>"",K75,IF(I75<>"",I75,""))) | P75: =IF(O75="","",IF(O75="PENDIENTE","Pendiente",IF(O75="NO EJECUTABLE","No ejecutable",IF(O75="VERIFICAR","Por verificar",IF(AND(F75="No cumple",O75="CUMPLE"),"Mejora",IF(AND(F75="No cumple",O75="PARCIAL"),"Mejora parcial",IF(AND(OR(F75="Cumple",F75="Sin ejecutar"),OR(O75="NO CUMPLE",O75="PARCIAL")),IF(F75="Cumple","Regresión","Falla nueva"),IF(AND(F75="No cumple",O75="NO CUMPLE"),"Sigue fallando","Se mantiene"))))))))
A76: 63 | B76: 63 | C76: Poner Cantidad 100 y Turnos 1 | F76: Sin ejecutar | O76: =IF(M76<>"",M76,IF(K76<>"",K76,IF(I76<>"",I76,""))) | P76: =IF(O76="","",IF(O76="PENDIENTE","Pendiente",IF(O76="NO EJECUTABLE","No ejecutable",IF(O76="VERIFICAR","Por verificar",IF(AND(F76="No cumple",O76="CUMPLE"),"Mejora",IF(AND(F76="No cumple",O76="PARCIAL"),"Mejora parcial",IF(AND(OR(F76="Cumple",F76="Sin ejecutar"),OR(O76="NO CUMPLE",O76="PARCIAL")),IF(F76="Cumple","Regresión","Falla nueva"),IF(AND(F76="No cumple",O76="NO CUMPLE"),"Sigue fallando","Se mantiene"))))))))
A77: 64 | B77: 64 | C77: Seleccionar La misma fecha de cita que en el caso anterior | F77: Sin ejecutar | O77: =IF(M77<>"",M77,IF(K77<>"",K77,IF(I77<>"",I77,""))) | P77: =IF(O77="","",IF(O77="PENDIENTE","Pendiente",IF(O77="NO EJECUTABLE","No ejecutable",IF(O77="VERIFICAR","Por verificar",IF(AND(F77="No cumple",O77="CUMPLE"),"Mejora",IF(AND(F77="No cumple",O77="PARCIAL"),"Mejora parcial",IF(AND(OR(F77="Cumple",F77="Sin ejecutar"),OR(O77="NO CUMPLE",O77="PARCIAL")),IF(F77="Cumple","Regresión","Falla nueva"),IF(AND(F77="No cumple",O77="NO CUMPLE"),"Sigue fallando","Se mantiene"))))))))
A78: 65 | B78: 65 | C78: Seleccionar una fecha de liberación posterior | D78: El sistema debe de mostrar una alerta por que no puede ser la fecha de liberación posterior a la fecha de cita | F78: Sin ejecutar | O78: =IF(M78<>"",M78,IF(K78<>"",K78,IF(I78<>"",I78,""))) | P78: =IF(O78="","",IF(O78="PENDIENTE","Pendiente",IF(O78="NO EJECUTABLE","No ejecutable",IF(O78="VERIFICAR","Por verificar",IF(AND(F78="No cumple",O78="CUMPLE"),"Mejora",IF(AND(F78="No cumple",O78="PARCIAL"),"Mejora parcial",IF(AND(OR(F78="Cumple",F78="Sin ejecutar"),OR(O78="NO CUMPLE",O78="PARCIAL")),IF(F78="Cumple","Regresión","Falla nueva"),IF(AND(F78="No cumple",O78="NO CUMPLE"),"Sigue fallando","Se mantiene"))))))))
A79: 66 | B79: 66 | C79: Seleccionar una fecha correcta de liberación | F79: Sin ejecutar | O79: =IF(M79<>"",M79,IF(K79<>"",K79,IF(I79<>"",I79,""))) | P79: =IF(O79="","",IF(O79="PENDIENTE","Pendiente",IF(O79="NO EJECUTABLE","No ejecutable",IF(O79="VERIFICAR","Por verificar",IF(AND(F79="No cumple",O79="CUMPLE"),"Mejora",IF(AND(F79="No cumple",O79="PARCIAL"),"Mejora parcial",IF(AND(OR(F79="Cumple",F79="Sin ejecutar"),OR(O79="NO CUMPLE",O79="PARCIAL")),IF(F79="Cumple","Regresión","Falla nueva"),IF(AND(F79="No cumple",O79="NO CUMPLE"),"Sigue fallando","Se mantiene"))))))))
A80: 67 | B80: 67 | C80: En presentación por producto, validar que sólo muentren las de la unidad de negocio | F80: Sin ejecutar | O80: =IF(M80<>"",M80,IF(K80<>"",K80,IF(I80<>"",I80,""))) | P80: =IF(O80="","",IF(O80="PENDIENTE","Pendiente",IF(O80="NO EJECUTABLE","No ejecutable",IF(O80="VERIFICAR","Por verificar",IF(AND(F80="No cumple",O80="CUMPLE"),"Mejora",IF(AND(F80="No cumple",O80="PARCIAL"),"Mejora parcial",IF(AND(OR(F80="Cumple",F80="Sin ejecutar"),OR(O80="NO CUMPLE",O80="PARCIAL")),IF(F80="Cumple","Regresión","Falla nueva"),IF(AND(F80="No cumple",O80="NO CUMPLE"),"Sigue fallando","Se mantiene"))))))))
A81: 68 | B81: 68 | C81: Completar con similares - Marcar NO | F81: Sin ejecutar | O81: =IF(M81<>"",M81,IF(K81<>"",K81,IF(I81<>"",I81,""))) | P81: =IF(O81="","",IF(O81="PENDIENTE","Pendiente",IF(O81="NO EJECUTABLE","No ejecutable",IF(O81="VERIFICAR","Por verificar",IF(AND(F81="No cumple",O81="CUMPLE"),"Mejora",IF(AND(F81="No cumple",O81="PARCIAL"),"Mejora parcial",IF(AND(OR(F81="Cumple",F81="Sin ejecutar"),OR(O81="NO CUMPLE",O81="PARCIAL")),IF(F81="Cumple","Regresión","Falla nueva"),IF(AND(F81="No cumple",O81="NO CUMPLE"),"Sigue fallando","Se mantiene"))))))))
A82: 69 | B82: 69 | C82: Agregar registro | D82: Validamos que se muestra la Matriz de información (Fecha, hora, productos, Turnos, Totales (personal y monto)) Validar el ID del Detalle del pedido | F82: Sin ejecutar | O82: =IF(M82<>"",M82,IF(K82<>"",K82,IF(I82<>"",I82,""))) | P82: =IF(O82="","",IF(O82="PENDIENTE","Pendiente",IF(O82="NO EJECUTABLE","No ejecutable",IF(O82="VERIFICAR","Por verificar",IF(AND(F82="No cumple",O82="CUMPLE"),"Mejora",IF(AND(F82="No cumple",O82="PARCIAL"),"Mejora parcial",IF(AND(OR(F82="Cumple",F82="Sin ejecutar"),OR(O82="NO CUMPLE",O82="PARCIAL")),IF(F82="Cumple","Regresión","Falla nueva"),IF(AND(F82="No cumple",O82="NO CUMPLE"),"Sigue fallando","Se mantiene"))))))))
A83: 70 | B83: 70 | C83: Seleccionar Producto Seguridad - FE | F83: Sin ejecutar | O83: =IF(M83<>"",M83,IF(K83<>"",K83,IF(I83<>"",I83,""))) | P83: =IF(O83="","",IF(O83="PENDIENTE","Pendiente",IF(O83="NO EJECUTABLE","No ejecutable",IF(O83="VERIFICAR","Por verificar",IF(AND(F83="No cumple",O83="CUMPLE"),"Mejora",IF(AND(F83="No cumple",O83="PARCIAL"),"Mejora parcial",IF(AND(OR(F83="Cumple",F83="Sin ejecutar"),OR(O83="NO CUMPLE",O83="PARCIAL")),IF(F83="Cumple","Regresión","Falla nueva"),IF(AND(F83="No cumple",O83="NO CUMPLE"),"Sigue fallando","Se mantiene"))))))))
A84: 71 | B84: 71 | C84: Validar que el sistema muestra las horas por turno de ese producto | D84: Se muestra 1 turno por 8 horas | F84: Sin ejecutar | O84: =IF(M84<>"",M84,IF(K84<>"",K84,IF(I84<>"",I84,""))) | P84: =IF(O84="","",IF(O84="PENDIENTE","Pendiente",IF(O84="NO EJECUTABLE","No ejecutable",IF(O84="VERIFICAR","Por verificar",IF(AND(F84="No cumple",O84="CUMPLE"),"Mejora",IF(AND(F84="No cumple",O84="PARCIAL"),"Mejora parcial",IF(AND(OR(F84="Cumple",F84="Sin ejecutar"),OR(O84="NO CUMPLE",O84="PARCIAL")),IF(F84="Cumple","Regresión","Falla nueva"),IF(AND(F84="No cumple",O84="NO CUMPLE"),"Sigue fallando","Se mantiene"))))))))
A85: 72 | B85: 72 | C85: Poner Cantidad 50 y Turnos 1 | F85: Sin ejecutar | O85: =IF(M85<>"",M85,IF(K85<>"",K85,IF(I85<>"",I85,""))) | P85: =IF(O85="","",IF(O85="PENDIENTE","Pendiente",IF(O85="NO EJECUTABLE","No ejecutable",IF(O85="VERIFICAR","Por verificar",IF(AND(F85="No cumple",O85="CUMPLE"),"Mejora",IF(AND(F85="No cumple",O85="PARCIAL"),"Mejora parcial",IF(AND(OR(F85="Cumple",F85="Sin ejecutar"),OR(O85="NO CUMPLE",O85="PARCIAL")),IF(F85="Cumple","Regresión","Falla nueva"),IF(AND(F85="No cumple",O85="NO CUMPLE"),"Sigue fallando","Se mantiene"))))))))
A86: 73 | B86: 73 | C86: Seleccionar La misma fecha de cita que en el caso anterior | F86: Sin ejecutar | O86: =IF(M86<>"",M86,IF(K86<>"",K86,IF(I86<>"",I86,""))) | P86: =IF(O86="","",IF(O86="PENDIENTE","Pendiente",IF(O86="NO EJECUTABLE","No ejecutable",IF(O86="VERIFICAR","Por verificar",IF(AND(F86="No cumple",O86="CUMPLE"),"Mejora",IF(AND(F86="No cumple",O86="PARCIAL"),"Mejora parcial",IF(AND(OR(F86="Cumple",F86="Sin ejecutar"),OR(O86="NO CUMPLE",O86="PARCIAL")),IF(F86="Cumple","Regresión","Falla nueva"),IF(AND(F86="No cumple",O86="NO CUMPLE"),"Sigue fallando","Se mantiene"))))))))
A87: 74 | B87: 74 | C87: Seleccionar una fecha de liberación posterior | D87: El sistema debe de mostrar una alerta por que no puede ser la fecha de liberación posterior a la fecha de cita | F87: Sin ejecutar | O87: =IF(M87<>"",M87,IF(K87<>"",K87,IF(I87<>"",I87,""))) | P87: =IF(O87="","",IF(O87="PENDIENTE","Pendiente",IF(O87="NO EJECUTABLE","No ejecutable",IF(O87="VERIFICAR","Por verificar",IF(AND(F87="No cumple",O87="CUMPLE"),"Mejora",IF(AND(F87="No cumple",O87="PARCIAL"),"Mejora parcial",IF(AND(OR(F87="Cumple",F87="Sin ejecutar"),OR(O87="NO CUMPLE",O87="PARCIAL")),IF(F87="Cumple","Regresión","Falla nueva"),IF(AND(F87="No cumple",O87="NO CUMPLE"),"Sigue fallando","Se mantiene"))))))))
A88: 75 | B88: 75 | C88: Seleccionar una fecha correcta de liberación | F88: Sin ejecutar | O88: =IF(M88<>"",M88,IF(K88<>"",K88,IF(I88<>"",I88,""))) | P88: =IF(O88="","",IF(O88="PENDIENTE","Pendiente",IF(O88="NO EJECUTABLE","No ejecutable",IF(O88="VERIFICAR","Por verificar",IF(AND(F88="No cumple",O88="CUMPLE"),"Mejora",IF(AND(F88="No cumple",O88="PARCIAL"),"Mejora parcial",IF(AND(OR(F88="Cumple",F88="Sin ejecutar"),OR(O88="NO CUMPLE",O88="PARCIAL")),IF(F88="Cumple","Regresión","Falla nueva"),IF(AND(F88="No cumple",O88="NO CUMPLE"),"Sigue fallando","Se mantiene"))))))))
A89: 76 | B89: 76 | C89: En presentación por producto, validar que sólo muentren las de la unidad de negocio | F89: Sin ejecutar | O89: =IF(M89<>"",M89,IF(K89<>"",K89,IF(I89<>"",I89,""))) | P89: =IF(O89="","",IF(O89="PENDIENTE","Pendiente",IF(O89="NO EJECUTABLE","No ejecutable",IF(O89="VERIFICAR","Por verificar",IF(AND(F89="No cumple",O89="CUMPLE"),"Mejora",IF(AND(F89="No cumple",O89="PARCIAL"),"Mejora parcial",IF(AND(OR(F89="Cumple",F89="Sin ejecutar"),OR(O89="NO CUMPLE",O89="PARCIAL")),IF(F89="Cumple","Regresión","Falla nueva"),IF(AND(F89="No cumple",O89="NO CUMPLE"),"Sigue fallando","Se mantiene"))))))))
A90: 77 | B90: 77 | C90: Completar con similares - Marcar NO | F90: Sin ejecutar | O90: =IF(M90<>"",M90,IF(K90<>"",K90,IF(I90<>"",I90,""))) | P90: =IF(O90="","",IF(O90="PENDIENTE","Pendiente",IF(O90="NO EJECUTABLE","No ejecutable",IF(O90="VERIFICAR","Por verificar",IF(AND(F90="No cumple",O90="CUMPLE"),"Mejora",IF(AND(F90="No cumple",O90="PARCIAL"),"Mejora parcial",IF(AND(OR(F90="Cumple",F90="Sin ejecutar"),OR(O90="NO CUMPLE",O90="PARCIAL")),IF(F90="Cumple","Regresión","Falla nueva"),IF(AND(F90="No cumple",O90="NO CUMPLE"),"Sigue fallando","Se mantiene"))))))))
A91: 78 | B91: 78 | C91: Agregar registro | D91: Validamos que se muestra la Matriz de información (Fecha, hora, productos, Turnos, Totales (personal y monto)) Validar el ID del Detalle del pedido | F91: Sin ejecutar | O91: =IF(M91<>"",M91,IF(K91<>"",K91,IF(I91<>"",I91,""))) | P91: =IF(O91="","",IF(O91="PENDIENTE","Pendiente",IF(O91="NO EJECUTABLE","No ejecutable",IF(O91="VERIFICAR","Por verificar",IF(AND(F91="No cumple",O91="CUMPLE"),"Mejora",IF(AND(F91="No cumple",O91="PARCIAL"),"Mejora parcial",IF(AND(OR(F91="Cumple",F91="Sin ejecutar"),OR(O91="NO CUMPLE",O91="PARCIAL")),IF(F91="Cumple","Regresión","Falla nueva"),IF(AND(F91="No cumple",O91="NO CUMPLE"),"Sigue fallando","Se mantiene"))))))))
A92: 79 | B92: 79 | C92: Seleccionar Producto Seguridad - MA | F92: Sin ejecutar | O92: =IF(M92<>"",M92,IF(K92<>"",K92,IF(I92<>"",I92,""))) | P92: =IF(O92="","",IF(O92="PENDIENTE","Pendiente",IF(O92="NO EJECUTABLE","No ejecutable",IF(O92="VERIFICAR","Por verificar",IF(AND(F92="No cumple",O92="CUMPLE"),"Mejora",IF(AND(F92="No cumple",O92="PARCIAL"),"Mejora parcial",IF(AND(OR(F92="Cumple",F92="Sin ejecutar"),OR(O92="NO CUMPLE",O92="PARCIAL")),IF(F92="Cumple","Regresión","Falla nueva"),IF(AND(F92="No cumple",O92="NO CUMPLE"),"Sigue fallando","Se mantiene"))))))))
A93: 80 | B93: 80 | C93: Validar que el sistema muestra las horas por turno de ese producto | D93: Se muestra 1 turno por 8 horas | F93: Sin ejecutar | O93: =IF(M93<>"",M93,IF(K93<>"",K93,IF(I93<>"",I93,""))) | P93: =IF(O93="","",IF(O93="PENDIENTE","Pendiente",IF(O93="NO EJECUTABLE","No ejecutable",IF(O93="VERIFICAR","Por verificar",IF(AND(F93="No cumple",O93="CUMPLE"),"Mejora",IF(AND(F93="No cumple",O93="PARCIAL"),"Mejora parcial",IF(AND(OR(F93="Cumple",F93="Sin ejecutar"),OR(O93="NO CUMPLE",O93="PARCIAL")),IF(F93="Cumple","Regresión","Falla nueva"),IF(AND(F93="No cumple",O93="NO CUMPLE"),"Sigue fallando","Se mantiene"))))))))
A94: 81 | B94: 81 | C94: Poner Cantidad 70 y Turnos 1 | F94: Sin ejecutar | O94: =IF(M94<>"",M94,IF(K94<>"",K94,IF(I94<>"",I94,""))) | P94: =IF(O94="","",IF(O94="PENDIENTE","Pendiente",IF(O94="NO EJECUTABLE","No ejecutable",IF(O94="VERIFICAR","Por verificar",IF(AND(F94="No cumple",O94="CUMPLE"),"Mejora",IF(AND(F94="No cumple",O94="PARCIAL"),"Mejora parcial",IF(AND(OR(F94="Cumple",F94="Sin ejecutar"),OR(O94="NO CUMPLE",O94="PARCIAL")),IF(F94="Cumple","Regresión","Falla nueva"),IF(AND(F94="No cumple",O94="NO CUMPLE"),"Sigue fallando","Se mantiene"))))))))
A95: 82 | B95: 82 | C95: Seleccionar La misma fecha de cita que en el caso anterior | F95: Sin ejecutar | O95: =IF(M95<>"",M95,IF(K95<>"",K95,IF(I95<>"",I95,""))) | P95: =IF(O95="","",IF(O95="PENDIENTE","Pendiente",IF(O95="NO EJECUTABLE","No ejecutable",IF(O95="VERIFICAR","Por verificar",IF(AND(F95="No cumple",O95="CUMPLE"),"Mejora",IF(AND(F95="No cumple",O95="PARCIAL"),"Mejora parcial",IF(AND(OR(F95="Cumple",F95="Sin ejecutar"),OR(O95="NO CUMPLE",O95="PARCIAL")),IF(F95="Cumple","Regresión","Falla nueva"),IF(AND(F95="No cumple",O95="NO CUMPLE"),"Sigue fallando","Se mantiene"))))))))
A96: 83 | B96: 83 | C96: Seleccionar una fecha de liberación posterior | D96: El sistema debe de mostrar una alerta por que no puede ser la fecha de liberación posterior a la fecha de cita | F96: Sin ejecutar | O96: =IF(M96<>"",M96,IF(K96<>"",K96,IF(I96<>"",I96,""))) | P96: =IF(O96="","",IF(O96="PENDIENTE","Pendiente",IF(O96="NO EJECUTABLE","No ejecutable",IF(O96="VERIFICAR","Por verificar",IF(AND(F96="No cumple",O96="CUMPLE"),"Mejora",IF(AND(F96="No cumple",O96="PARCIAL"),"Mejora parcial",IF(AND(OR(F96="Cumple",F96="Sin ejecutar"),OR(O96="NO CUMPLE",O96="PARCIAL")),IF(F96="Cumple","Regresión","Falla nueva"),IF(AND(F96="No cumple",O96="NO CUMPLE"),"Sigue fallando","Se mantiene"))))))))
A97: 84 | B97: 84 | C97: Seleccionar una fecha correcta de liberación | F97: Sin ejecutar | O97: =IF(M97<>"",M97,IF(K97<>"",K97,IF(I97<>"",I97,""))) | P97: =IF(O97="","",IF(O97="PENDIENTE","Pendiente",IF(O97="NO EJECUTABLE","No ejecutable",IF(O97="VERIFICAR","Por verificar",IF(AND(F97="No cumple",O97="CUMPLE"),"Mejora",IF(AND(F97="No cumple",O97="PARCIAL"),"Mejora parcial",IF(AND(OR(F97="Cumple",F97="Sin ejecutar"),OR(O97="NO CUMPLE",O97="PARCIAL")),IF(F97="Cumple","Regresión","Falla nueva"),IF(AND(F97="No cumple",O97="NO CUMPLE"),"Sigue fallando","Se mantiene"))))))))
A98: 85 | B98: 85 | C98: En presentación por producto, validar que sólo muentren las de la unidad de negocio | F98: Sin ejecutar | O98: =IF(M98<>"",M98,IF(K98<>"",K98,IF(I98<>"",I98,""))) | P98: =IF(O98="","",IF(O98="PENDIENTE","Pendiente",IF(O98="NO EJECUTABLE","No ejecutable",IF(O98="VERIFICAR","Por verificar",IF(AND(F98="No cumple",O98="CUMPLE"),"Mejora",IF(AND(F98="No cumple",O98="PARCIAL"),"Mejora parcial",IF(AND(OR(F98="Cumple",F98="Sin ejecutar"),OR(O98="NO CUMPLE",O98="PARCIAL")),IF(F98="Cumple","Regresión","Falla nueva"),IF(AND(F98="No cumple",O98="NO CUMPLE"),"Sigue fallando","Se mantiene"))))))))
A99: 86 | B99: 86 | C99: Completar con similares - Marcar NO | F99: Sin ejecutar | O99: =IF(M99<>"",M99,IF(K99<>"",K99,IF(I99<>"",I99,""))) | P99: =IF(O99="","",IF(O99="PENDIENTE","Pendiente",IF(O99="NO EJECUTABLE","No ejecutable",IF(O99="VERIFICAR","Por verificar",IF(AND(F99="No cumple",O99="CUMPLE"),"Mejora",IF(AND(F99="No cumple",O99="PARCIAL"),"Mejora parcial",IF(AND(OR(F99="Cumple",F99="Sin ejecutar"),OR(O99="NO CUMPLE",O99="PARCIAL")),IF(F99="Cumple","Regresión","Falla nueva"),IF(AND(F99="No cumple",O99="NO CUMPLE"),"Sigue fallando","Se mantiene"))))))))
A100: 87 | B100: 87 | C100: Agregar registro | D100: Validamos que se muestra la Matriz de información (Fecha, hora, productos, Turnos, Totales (personal y monto)) Validar el ID del Detalle del pedido | F100: Sin ejecutar | O100: =IF(M100<>"",M100,IF(K100<>"",K100,IF(I100<>"",I100,""))) | P100: =IF(O100="","",IF(O100="PENDIENTE","Pendiente",IF(O100="NO EJECUTABLE","No ejecutable",IF(O100="VERIFICAR","Por verificar",IF(AND(F100="No cumple",O100="CUMPLE"),"Mejora",IF(AND(F100="No cumple",O100="PARCIAL"),"Mejora parcial",IF(AND(OR(F100="Cumple",F100="Sin ejecutar"),OR(O100="NO CUMPLE",O100="PARCIAL")),IF(F100="Cumple","Regresión","Falla nueva"),IF(AND(F100="No cumple",O100="NO CUMPLE"),"Sigue fallando","Se mantiene"))))))))
A101: 88 | B101: 88 | C101: Seleccionar Producto Seguridad Coordinador - MA | F101: Sin ejecutar | O101: =IF(M101<>"",M101,IF(K101<>"",K101,IF(I101<>"",I101,""))) | P101: =IF(O101="","",IF(O101="PENDIENTE","Pendiente",IF(O101="NO EJECUTABLE","No ejecutable",IF(O101="VERIFICAR","Por verificar",IF(AND(F101="No cumple",O101="CUMPLE"),"Mejora",IF(AND(F101="No cumple",O101="PARCIAL"),"Mejora parcial",IF(AND(OR(F101="Cumple",F101="Sin ejecutar"),OR(O101="NO CUMPLE",O101="PARCIAL")),IF(F101="Cumple","Regresión","Falla nueva"),IF(AND(F101="No cumple",O101="NO CUMPLE"),"Sigue fallando","Se mantiene"))))))))
...

Sheet ESC-05
A1: ESC-05 — Seriado con cancelación de un día para que no deje forzar ese día de otro pedido
A2: Núm. original | B2: Escenario 5 | I2: Pasos | J2: =COUNT(A13:A62)
A3: Módulo | B3: Pedidos / Asignaciones | I3: Ejecutados (último) | J3: =COUNTIF(O13:O62,"?*")
A4: Objetivo (propuesto, validar) | B4: Validar seriados: bloque semanal, cancelación de un día y que no se pueda forzar ese día desde otro pedido según la propiedad del puesto. | I4: CUMPLE (último) | J4: =COUNTIF(O13:O62,"CUMPLE")
A5: Funcionalidades | B5: PEP temporal (Z-PEP) · bloques · seriado semanal · cancelación de un detalle · regla de confirmación entre seriados | I5: % cumplimiento | J5: =IF(J2=0,0,J4/J2)
A6: Dependencias / datos | B6: Requiere que un empleado confirme el bloque (portal)
A7: Sesión sugerida | B7: S05
A8: ⚠ Calidad del caso | B8: Numeración repetida (varios pasos '13'). Producto de Operaciones Inmuebles con esperado 'catálogo PRG'. Fase: legado observa 'Ninguno' vs 'No aplica'. Variante final sin pasos.
A9: Notas originales | B9: —
F11: CORRIDA LEGADO (HUMANOS) | I11: CICLO CLAUDE CODE: probar → corregir → re-probar
A12: # | B12: Paso orig. | C12: Descripción | D12: Resultado esperado | E12: ⚠ Calidad | F12: Legado: Resultado | G12: Legado: Observación | H12: Legado: Corrección | I12: R1 Resultado | J12: R1 Hallazgo / Obs. | K12: R2 Resultado | L12: R2 Hallazgo / Obs. | M12: R3 Resultado | N12: R3 Hallazgo / Obs. | O12: Último resultado | P12: Comparativo
A13: 1 | B13: 1 | C13: Crear un nuevo pedido | F13: Cumple | O13: =IF(M13<>"",M13,IF(K13<>"",K13,IF(I13<>"",I13,""))) | P13: =IF(O13="","",IF(O13="PENDIENTE","Pendiente",IF(O13="NO EJECUTABLE","No ejecutable",IF(O13="VERIFICAR","Por verificar",IF(AND(F13="No cumple",O13="CUMPLE"),"Mejora",IF(AND(F13="No cumple",O13="PARCIAL"),"Mejora parcial",IF(AND(OR(F13="Cumple",F13="Sin ejecutar"),OR(O13="NO CUMPLE",O13="PARCIAL")),IF(F13="Cumple","Regresión","Falla nueva"),IF(AND(F13="No cumple",O13="NO CUMPLE"),"Sigue fallando","Se mantiene"))))))))
A14: 2 | B14: 2 | C14: Seleccionar cliente Ocesa | F14: Cumple | O14: =IF(M14<>"",M14,IF(K14<>"",K14,IF(I14<>"",I14,""))) | P14: =IF(O14="","",IF(O14="PENDIENTE","Pendiente",IF(O14="NO EJECUTABLE","No ejecutable",IF(O14="VERIFICAR","Por verificar",IF(AND(F14="No cumple",O14="CUMPLE"),"Mejora",IF(AND(F14="No cumple",O14="PARCIAL"),"Mejora parcial",IF(AND(OR(F14="Cumple",F14="Sin ejecutar"),OR(O14="NO CUMPLE",O14="PARCIAL")),IF(F14="Cumple","Regresión","Falla nueva"),IF(AND(F14="No cumple",O14="NO CUMPLE"),"Sigue fallando","Se mantiene"))))))))
A15: 3 | B15: 3 | C15: Validar lista de contactos | D15: Los contactos mostrados deben pertenecer al cliente Ocesa | F15: Cumple | O15: =IF(M15<>"",M15,IF(K15<>"",K15,IF(I15<>"",I15,""))) | P15: =IF(O15="","",IF(O15="PENDIENTE","Pendiente",IF(O15="NO EJECUTABLE","No ejecutable",IF(O15="VERIFICAR","Por verificar",IF(AND(F15="No cumple",O15="CUMPLE"),"Mejora",IF(AND(F15="No cumple",O15="PARCIAL"),"Mejora parcial",IF(AND(OR(F15="Cumple",F15="Sin ejecutar"),OR(O15="NO CUMPLE",O15="PARCIAL")),IF(F15="Cumple","Regresión","Falla nueva"),IF(AND(F15="No cumple",O15="NO CUMPLE"),"Sigue fallando","Se mantiene"))))))))
A16: 4 | B16: 4 | C16: Seleccionar un evento | F16: Cumple | O16: =IF(M16<>"",M16,IF(K16<>"",K16,IF(I16<>"",I16,""))) | P16: =IF(O16="","",IF(O16="PENDIENTE","Pendiente",IF(O16="NO EJECUTABLE","No ejecutable",IF(O16="VERIFICAR","Por verificar",IF(AND(F16="No cumple",O16="CUMPLE"),"Mejora",IF(AND(F16="No cumple",O16="PARCIAL"),"Mejora parcial",IF(AND(OR(F16="Cumple",F16="Sin ejecutar"),OR(O16="NO CUMPLE",O16="PARCIAL")),IF(F16="Cumple","Regresión","Falla nueva"),IF(AND(F16="No cumple",O16="NO CUMPLE"),"Sigue fallando","Se mantiene"))))))))
A17: 5 | B17: 5 | C17: Seleccionar UN Operaciones Inmuebles | D17: El sistema despliega los PEPS de la UN de seguridad, y la sociedad pagadora | E17: Esperado copiado ('UN de seguridad'). | F17: Cumple | O17: =IF(M17<>"",M17,IF(K17<>"",K17,IF(I17<>"",I17,""))) | P17: =IF(O17="","",IF(O17="PENDIENTE","Pendiente",IF(O17="NO EJECUTABLE","No ejecutable",IF(O17="VERIFICAR","Por verificar",IF(AND(F17="No cumple",O17="CUMPLE"),"Mejora",IF(AND(F17="No cumple",O17="PARCIAL"),"Mejora parcial",IF(AND(OR(F17="Cumple",F17="Sin ejecutar"),OR(O17="NO CUMPLE",O17="PARCIAL")),IF(F17="Cumple","Regresión","Falla nueva"),IF(AND(F17="No cumple",O17="NO CUMPLE"),"Sigue fallando","Se mantiene"))))))))
A18: 6 | B18: 6 | C18: Seleccionar un PEP Temporal (Se identifican con Z-PEP) | D18: Validar que el sistema por defecto no trae lugar de cita, ni inmueble | F18: Cumple | O18: =IF(M18<>"",M18,IF(K18<>"",K18,IF(I18<>"",I18,""))) | P18: =IF(O18="","",IF(O18="PENDIENTE","Pendiente",IF(O18="NO EJECUTABLE","No ejecutable",IF(O18="VERIFICAR","Por verificar",IF(AND(F18="No cumple",O18="CUMPLE"),"Mejora",IF(AND(F18="No cumple",O18="PARCIAL"),"Mejora parcial",IF(AND(OR(F18="Cumple",F18="Sin ejecutar"),OR(O18="NO CUMPLE",O18="PARCIAL")),IF(F18="Cumple","Regresión","Falla nueva"),IF(AND(F18="No cumple",O18="NO CUMPLE"),"Sigue fallando","Se mantiene"))))))))
A19: 7 | B19: 7 | C19: Seleccionar un Lugar de Cita | F19: Cumple | O19: =IF(M19<>"",M19,IF(K19<>"",K19,IF(I19<>"",I19,""))) | P19: =IF(O19="","",IF(O19="PENDIENTE","Pendiente",IF(O19="NO EJECUTABLE","No ejecutable",IF(O19="VERIFICAR","Por verificar",IF(AND(F19="No cumple",O19="CUMPLE"),"Mejora",IF(AND(F19="No cumple",O19="PARCIAL"),"Mejora parcial",IF(AND(OR(F19="Cumple",F19="Sin ejecutar"),OR(O19="NO CUMPLE",O19="PARCIAL")),IF(F19="Cumple","Regresión","Falla nueva"),IF(AND(F19="No cumple",O19="NO CUMPLE"),"Sigue fallando","Se mantiene"))))))))
A20: 8 | B20: 8 | C20: Validar tipo de movimiento | D20: El sistema debe mostrar dos tipos de movimiento (Pedido y Servicio Interno) | F20: Cumple | O20: =IF(M20<>"",M20,IF(K20<>"",K20,IF(I20<>"",I20,""))) | P20: =IF(O20="","",IF(O20="PENDIENTE","Pendiente",IF(O20="NO EJECUTABLE","No ejecutable",IF(O20="VERIFICAR","Por verificar",IF(AND(F20="No cumple",O20="CUMPLE"),"Mejora",IF(AND(F20="No cumple",O20="PARCIAL"),"Mejora parcial",IF(AND(OR(F20="Cumple",F20="Sin ejecutar"),OR(O20="NO CUMPLE",O20="PARCIAL")),IF(F20="Cumple","Regresión","Falla nueva"),IF(AND(F20="No cumple",O20="NO CUMPLE"),"Sigue fallando","Se mantiene"))))))))
A21: 9 | B21: 9 | C21: Seleccionar Tipo de movimiento Servicio Interno | D21: EL tipo Pedido se factura (validar posteriormente) | E21: Servicio Interno con esperado de Pedido. | F21: Cumple | O21: =IF(M21<>"",M21,IF(K21<>"",K21,IF(I21<>"",I21,""))) | P21: =IF(O21="","",IF(O21="PENDIENTE","Pendiente",IF(O21="NO EJECUTABLE","No ejecutable",IF(O21="VERIFICAR","Por verificar",IF(AND(F21="No cumple",O21="CUMPLE"),"Mejora",IF(AND(F21="No cumple",O21="PARCIAL"),"Mejora parcial",IF(AND(OR(F21="Cumple",F21="Sin ejecutar"),OR(O21="NO CUMPLE",O21="PARCIAL")),IF(F21="Cumple","Regresión","Falla nueva"),IF(AND(F21="No cumple",O21="NO CUMPLE"),"Sigue fallando","Se mantiene"))))))))
A22: 10 | B22: 10 | C22: En complejidad indicar que No Aplica | D22: Validar que para esta UN no aplica Complejidad (sólo muestra esa opción) | F22: Cumple | O22: =IF(M22<>"",M22,IF(K22<>"",K22,IF(I22<>"",I22,""))) | P22: =IF(O22="","",IF(O22="PENDIENTE","Pendiente",IF(O22="NO EJECUTABLE","No ejecutable",IF(O22="VERIFICAR","Por verificar",IF(AND(F22="No cumple",O22="CUMPLE"),"Mejora",IF(AND(F22="No cumple",O22="PARCIAL"),"Mejora parcial",IF(AND(OR(F22="Cumple",F22="Sin ejecutar"),OR(O22="NO CUMPLE",O22="PARCIAL")),IF(F22="Cumple","Regresión","Falla nueva"),IF(AND(F22="No cumple",O22="NO CUMPLE"),"Sigue fallando","Se mantiene"))))))))
A23: 11 | B23: 11 | C23: En el campo Permitir Cancelar, seleccionar NO | F23: Cumple | O23: =IF(M23<>"",M23,IF(K23<>"",K23,IF(I23<>"",I23,""))) | P23: =IF(O23="","",IF(O23="PENDIENTE","Pendiente",IF(O23="NO EJECUTABLE","No ejecutable",IF(O23="VERIFICAR","Por verificar",IF(AND(F23="No cumple",O23="CUMPLE"),"Mejora",IF(AND(F23="No cumple",O23="PARCIAL"),"Mejora parcial",IF(AND(OR(F23="Cumple",F23="Sin ejecutar"),OR(O23="NO CUMPLE",O23="PARCIAL")),IF(F23="Cumple","Regresión","Falla nueva"),IF(AND(F23="No cumple",O23="NO CUMPLE"),"Sigue fallando","Se mantiene"))))))))
A24: 12 | B24: 12 | C24: Pulsar Aceptar | D24: El sistema genera un número consecutivo de pedido. | F24: Cumple | O24: =IF(M24<>"",M24,IF(K24<>"",K24,IF(I24<>"",I24,""))) | P24: =IF(O24="","",IF(O24="PENDIENTE","Pendiente",IF(O24="NO EJECUTABLE","No ejecutable",IF(O24="VERIFICAR","Por verificar",IF(AND(F24="No cumple",O24="CUMPLE"),"Mejora",IF(AND(F24="No cumple",O24="PARCIAL"),"Mejora parcial",IF(AND(OR(F24="Cumple",F24="Sin ejecutar"),OR(O24="NO CUMPLE",O24="PARCIAL")),IF(F24="Cumple","Regresión","Falla nueva"),IF(AND(F24="No cumple",O24="NO CUMPLE"),"Sigue fallando","Se mantiene"))))))))
C25: Pedido Detalle
A26: 13 | B26: 13 | C26: Tipo de personal | D26: Validad que sólo se muestren Operativos al no tener complejidad | F26: Cumple | O26: =IF(M26<>"",M26,IF(K26<>"",K26,IF(I26<>"",I26,""))) | P26: =IF(O26="","",IF(O26="PENDIENTE","Pendiente",IF(O26="NO EJECUTABLE","No ejecutable",IF(O26="VERIFICAR","Por verificar",IF(AND(F26="No cumple",O26="CUMPLE"),"Mejora",IF(AND(F26="No cumple",O26="PARCIAL"),"Mejora parcial",IF(AND(OR(F26="Cumple",F26="Sin ejecutar"),OR(O26="NO CUMPLE",O26="PARCIAL")),IF(F26="Cumple","Regresión","Falla nueva"),IF(AND(F26="No cumple",O26="NO CUMPLE"),"Sigue fallando","Se mantiene"))))))))
A27: 14 | B27: 13 | C27: Seleccionar Operativo | F27: Cumple | O27: =IF(M27<>"",M27,IF(K27<>"",K27,IF(I27<>"",I27,""))) | P27: =IF(O27="","",IF(O27="PENDIENTE","Pendiente",IF(O27="NO EJECUTABLE","No ejecutable",IF(O27="VERIFICAR","Por verificar",IF(AND(F27="No cumple",O27="CUMPLE"),"Mejora",IF(AND(F27="No cumple",O27="PARCIAL"),"Mejora parcial",IF(AND(OR(F27="Cumple",F27="Sin ejecutar"),OR(O27="NO CUMPLE",O27="PARCIAL")),IF(F27="Cumple","Regresión","Falla nueva"),IF(AND(F27="No cumple",O27="NO CUMPLE"),"Sigue fallando","Se mantiene"))))))))
A28: 15 | B28: 13 | C28: Producto: Especialistas Estructuras Inmuebles - IN | D28: Validar que el catálogo mostrado es el de PRG | F28: Cumple | O28: =IF(M28<>"",M28,IF(K28<>"",K28,IF(I28<>"",I28,""))) | P28: =IF(O28="","",IF(O28="PENDIENTE","Pendiente",IF(O28="NO EJECUTABLE","No ejecutable",IF(O28="VERIFICAR","Por verificar",IF(AND(F28="No cumple",O28="CUMPLE"),"Mejora",IF(AND(F28="No cumple",O28="PARCIAL"),"Mejora parcial",IF(AND(OR(F28="Cumple",F28="Sin ejecutar"),OR(O28="NO CUMPLE",O28="PARCIAL")),IF(F28="Cumple","Regresión","Falla nueva"),IF(AND(F28="No cumple",O28="NO CUMPLE"),"Sigue fallando","Se mantiene"))))))))
A29: 16 | C29: Cantidad 1 - Turno 1 | F29: Cumple | O29: =IF(M29<>"",M29,IF(K29<>"",K29,IF(I29<>"",I29,""))) | P29: =IF(O29="","",IF(O29="PENDIENTE","Pendiente",IF(O29="NO EJECUTABLE","No ejecutable",IF(O29="VERIFICAR","Por verificar",IF(AND(F29="No cumple",O29="CUMPLE"),"Mejora",IF(AND(F29="No cumple",O29="PARCIAL"),"Mejora parcial",IF(AND(OR(F29="Cumple",F29="Sin ejecutar"),OR(O29="NO CUMPLE",O29="PARCIAL")),IF(F29="Cumple","Regresión","Falla nueva"),IF(AND(F29="No cumple",O29="NO CUMPLE"),"Sigue fallando","Se mantiene"))))))))
A30: 17 | B30: 13 | C30: Validar la jornada | D30: Debe mostrar 1 turno por 12 horas | F30: No cumple | O30: =IF(M30<>"",M30,IF(K30<>"",K30,IF(I30<>"",I30,""))) | P30: =IF(O30="","",IF(O30="PENDIENTE","Pendiente",IF(O30="NO EJECUTABLE","No ejecutable",IF(O30="VERIFICAR","Por verificar",IF(AND(F30="No cumple",O30="CUMPLE"),"Mejora",IF(AND(F30="No cumple",O30="PARCIAL"),"Mejora parcial",IF(AND(OR(F30="Cumple",F30="Sin ejecutar"),OR(O30="NO CUMPLE",O30="PARCIAL")),IF(F30="Cumple","Regresión","Falla nueva"),IF(AND(F30="No cumple",O30="NO CUMPLE"),"Sigue fallando","Se mantiene"))))))))
A31: 18 | B31: 13 | C31: Seleccionar una fecha de cita (debe ser un lunes) y de liberación | F31: Cumple | O31: =IF(M31<>"",M31,IF(K31<>"",K31,IF(I31<>"",I31,""))) | P31: =IF(O31="","",IF(O31="PENDIENTE","Pendiente",IF(O31="NO EJECUTABLE","No ejecutable",IF(O31="VERIFICAR","Por verificar",IF(AND(F31="No cumple",O31="CUMPLE"),"Mejora",IF(AND(F31="No cumple",O31="PARCIAL"),"Mejora parcial",IF(AND(OR(F31="Cumple",F31="Sin ejecutar"),OR(O31="NO CUMPLE",O31="PARCIAL")),IF(F31="Cumple","Regresión","Falla nueva"),IF(AND(F31="No cumple",O31="NO CUMPLE"),"Sigue fallando","Se mantiene"))))))))
A32: 19 | B32: 13 | C32: Presentación por producto | D32: Validar que nos se muestran presentaciones | F32: Cumple | O32: =IF(M32<>"",M32,IF(K32<>"",K32,IF(I32<>"",I32,""))) | P32: =IF(O32="","",IF(O32="PENDIENTE","Pendiente",IF(O32="NO EJECUTABLE","No ejecutable",IF(O32="VERIFICAR","Por verificar",IF(AND(F32="No cumple",O32="CUMPLE"),"Mejora",IF(AND(F32="No cumple",O32="PARCIAL"),"Mejora parcial",IF(AND(OR(F32="Cumple",F32="Sin ejecutar"),OR(O32="NO CUMPLE",O32="PARCIAL")),IF(F32="Cumple","Regresión","Falla nueva"),IF(AND(F32="No cumple",O32="NO CUMPLE"),"Sigue fallando","Se mantiene"))))))))
A33: 20 | B33: 13 | C33: Fase del evento | D33: Por Default pone No Aplica debido a la UN | F33: Cumple | G33: El campo dice "Ninguno" en vez de "No aplica" | O33: =IF(M33<>"",M33,IF(K33<>"",K33,IF(I33<>"",I33,""))) | P33: =IF(O33="","",IF(O33="PENDIENTE","Pendiente",IF(O33="NO EJECUTABLE","No ejecutable",IF(O33="VERIFICAR","Por verificar",IF(AND(F33="No cumple",O33="CUMPLE"),"Mejora",IF(AND(F33="No cumple",O33="PARCIAL"),"Mejora parcial",IF(AND(OR(F33="Cumple",F33="Sin ejecutar"),OR(O33="NO CUMPLE",O33="PARCIAL")),IF(F33="Cumple","Regresión","Falla nueva"),IF(AND(F33="No cumple",O33="NO CUMPLE"),"Sigue fallando","Se mantiene"))))))))
A34: 21 | C34: En Bloque por Producto seleccionar Nuevo Bloque | F34: Cumple | O34: =IF(M34<>"",M34,IF(K34<>"",K34,IF(I34<>"",I34,""))) | P34: =IF(O34="","",IF(O34="PENDIENTE","Pendiente",IF(O34="NO EJECUTABLE","No ejecutable",IF(O34="VERIFICAR","Por verificar",IF(AND(F34="No cumple",O34="CUMPLE"),"Mejora",IF(AND(F34="No cumple",O34="PARCIAL"),"Mejora parcial",IF(AND(OR(F34="Cumple",F34="Sin ejecutar"),OR(O34="NO CUMPLE",O34="PARCIAL")),IF(F34="Cumple","Regresión","Falla nueva"),IF(AND(F34="No cumple",O34="NO CUMPLE"),"Sigue fallando","Se mantiene"))))))))
A35: 22 | C35: Agregar Registro | F35: Cumple | O35: =IF(M35<>"",M35,IF(K35<>"",K35,IF(I35<>"",I35,""))) | P35: =IF(O35="","",IF(O35="PENDIENTE","Pendiente",IF(O35="NO EJECUTABLE","No ejecutable",IF(O35="VERIFICAR","Por verificar",IF(AND(F35="No cumple",O35="CUMPLE"),"Mejora",IF(AND(F35="No cumple",O35="PARCIAL"),"Mejora parcial",IF(AND(OR(F35="Cumple",F35="Sin ejecutar"),OR(O35="NO CUMPLE",O35="PARCIAL")),IF(F35="Cumple","Regresión","Falla nueva"),IF(AND(F35="No cumple",O35="NO CUMPLE"),"Sigue fallando","Se mantiene"))))))))
A36: 23 | C36: Incluir 4 detalles de pedido adicionales para completar la semana con las mismas caraterísticas | D36: Confirmar que se crea todo en el mismo bloque | F36: Cumple | O36: =IF(M36<>"",M36,IF(K36<>"",K36,IF(I36<>"",I36,""))) | P36: =IF(O36="","",IF(O36="PENDIENTE","Pendiente",IF(O36="NO EJECUTABLE","No ejecutable",IF(O36="VERIFICAR","Por verificar",IF(AND(F36="No cumple",O36="CUMPLE"),"Mejora",IF(AND(F36="No cumple",O36="PARCIAL"),"Mejora parcial",IF(AND(OR(F36="Cumple",F36="Sin ejecutar"),OR(O36="NO CUMPLE",O36="PARCIAL")),IF(F36="Cumple","Regresión","Falla nueva"),IF(AND(F36="No cumple",O36="NO CUMPLE"),"Sigue fallando","Se mantiene"))))))))
A37: 24 | C37: Será necesario liberar el pedido y que alguien confirme el bloque para el escenario | F37: Sin ejecutar | O37: =IF(M37<>"",M37,IF(K37<>"",K37,IF(I37<>"",I37,""))) | P37: =IF(O37="","",IF(O37="PENDIENTE","Pendiente",IF(O37="NO EJECUTABLE","No ejecutable",IF(O37="VERIFICAR","Por verificar",IF(AND(F37="No cumple",O37="CUMPLE"),"Mejora",IF(AND(F37="No cumple",O37="PARCIAL"),"Mejora parcial",IF(AND(OR(F37="Cumple",F37="Sin ejecutar"),OR(O37="NO CUMPLE",O37="PARCIAL")),IF(F37="Cumple","Regresión","Falla nueva"),IF(AND(F37="No cumple",O37="NO CUMPLE"),"Sigue fallando","Se mantiene"))))))))
A38: 25 | C38: Cancelar el detalle de pedido del miércoles | D38: El bloque sigue existiendo, solo que ahora tiene 4 días (lunes, martes, jueves y viernes) | F38: Sin ejecutar | O38: =IF(M38<>"",M38,IF(K38<>"",K38,IF(I38<>"",I38,""))) | P38: =IF(O38="","",IF(O38="PENDIENTE","Pendiente",IF(O38="NO EJECUTABLE","No ejecutable",IF(O38="VERIFICAR","Por verificar",IF(AND(F38="No cumple",O38="CUMPLE"),"Mejora",IF(AND(F38="No cumple",O38="PARCIAL"),"Mejora parcial",IF(AND(OR(F38="Cumple",F38="Sin ejecutar"),OR(O38="NO CUMPLE",O38="PARCIAL")),IF(F38="Cumple","Regresión","Falla nueva"),IF(AND(F38="No cumple",O38="NO CUMPLE"),"Sigue fallando","Se mantiene"))))))))
A39: 26 | B39: 1 | C39: Crear un nuevo pedido | F39: Cumple | O39: =IF(M39<>"",M39,IF(K39<>"",K39,IF(I39<>"",I39,""))) | P39: =IF(O39="","",IF(O39="PENDIENTE","Pendiente",IF(O39="NO EJECUTABLE","No ejecutable",IF(O39="VERIFICAR","Por verificar",IF(AND(F39="No cumple",O39="CUMPLE"),"Mejora",IF(AND(F39="No cumple",O39="PARCIAL"),"Mejora parcial",IF(AND(OR(F39="Cumple",F39="Sin ejecutar"),OR(O39="NO CUMPLE",O39="PARCIAL")),IF(F39="Cumple","Regresión","Falla nueva"),IF(AND(F39="No cumple",O39="NO CUMPLE"),"Sigue fallando","Se mantiene"))))))))
A40: 27 | B40: 2 | C40: Seleccionar cliente Ocesa | F40: Cumple | O40: =IF(M40<>"",M40,IF(K40<>"",K40,IF(I40<>"",I40,""))) | P40: =IF(O40="","",IF(O40="PENDIENTE","Pendiente",IF(O40="NO EJECUTABLE","No ejecutable",IF(O40="VERIFICAR","Por verificar",IF(AND(F40="No cumple",O40="CUMPLE"),"Mejora",IF(AND(F40="No cumple",O40="PARCIAL"),"Mejora parcial",IF(AND(OR(F40="Cumple",F40="Sin ejecutar"),OR(O40="NO CUMPLE",O40="PARCIAL")),IF(F40="Cumple","Regresión","Falla nueva"),IF(AND(F40="No cumple",O40="NO CUMPLE"),"Sigue fallando","Se mantiene"))))))))
A41: 28 | B41: 3 | C41: Validar lista de contactos | D41: Los contactos mostrados deben pertenecer al cliente Ocesa | F41: Cumple | O41: =IF(M41<>"",M41,IF(K41<>"",K41,IF(I41<>"",I41,""))) | P41: =IF(O41="","",IF(O41="PENDIENTE","Pendiente",IF(O41="NO EJECUTABLE","No ejecutable",IF(O41="VERIFICAR","Por verificar",IF(AND(F41="No cumple",O41="CUMPLE"),"Mejora",IF(AND(F41="No cumple",O41="PARCIAL"),"Mejora parcial",IF(AND(OR(F41="Cumple",F41="Sin ejecutar"),OR(O41="NO CUMPLE",O41="PARCIAL")),IF(F41="Cumple","Regresión","Falla nueva"),IF(AND(F41="No cumple",O41="NO CUMPLE"),"Sigue fallando","Se mantiene"))))))))
A42: 29 | B42: 4 | C42: Seleccionar un evento | F42: Cumple | O42: =IF(M42<>"",M42,IF(K42<>"",K42,IF(I42<>"",I42,""))) | P42: =IF(O42="","",IF(O42="PENDIENTE","Pendiente",IF(O42="NO EJECUTABLE","No ejecutable",IF(O42="VERIFICAR","Por verificar",IF(AND(F42="No cumple",O42="CUMPLE"),"Mejora",IF(AND(F42="No cumple",O42="PARCIAL"),"Mejora parcial",IF(AND(OR(F42="Cumple",F42="Sin ejecutar"),OR(O42="NO CUMPLE",O42="PARCIAL")),IF(F42="Cumple","Regresión","Falla nueva"),IF(AND(F42="No cumple",O42="NO CUMPLE"),"Sigue fallando","Se mantiene"))))))))
A43: 30 | B43: 5 | C43: Seleccionar UN PRG | D43: El sistema despliega los PEPS de la UN de seguridad, y la sociedad pagadora | E43: Esperado copiado ('UN de seguridad'). | F43: Cumple | O43: =IF(M43<>"",M43,IF(K43<>"",K43,IF(I43<>"",I43,""))) | P43: =IF(O43="","",IF(O43="PENDIENTE","Pendiente",IF(O43="NO EJECUTABLE","No ejecutable",IF(O43="VERIFICAR","Por verificar",IF(AND(F43="No cumple",O43="CUMPLE"),"Mejora",IF(AND(F43="No cumple",O43="PARCIAL"),"Mejora parcial",IF(AND(OR(F43="Cumple",F43="Sin ejecutar"),OR(O43="NO CUMPLE",O43="PARCIAL")),IF(F43="Cumple","Regresión","Falla nueva"),IF(AND(F43="No cumple",O43="NO CUMPLE"),"Sigue fallando","Se mantiene"))))))))
A44: 31 | B44: 6 | C44: Seleccionar un PEP Temporal (Se identifican con Z-PEP) | D44: Validar que el sistema por defecto no trae lugar de cita, ni inmueble | F44: Cumple | O44: =IF(M44<>"",M44,IF(K44<>"",K44,IF(I44<>"",I44,""))) | P44: =IF(O44="","",IF(O44="PENDIENTE","Pendiente",IF(O44="NO EJECUTABLE","No ejecutable",IF(O44="VERIFICAR","Por verificar",IF(AND(F44="No cumple",O44="CUMPLE"),"Mejora",IF(AND(F44="No cumple",O44="PARCIAL"),"Mejora parcial",IF(AND(OR(F44="Cumple",F44="Sin ejecutar"),OR(O44="NO CUMPLE",O44="PARCIAL")),IF(F44="Cumple","Regresión","Falla nueva"),IF(AND(F44="No cumple",O44="NO CUMPLE"),"Sigue fallando","Se mantiene"))))))))
A45: 32 | B45: 7 | C45: Seleccionar un Lugar de Cita | F45: Cumple | O45: =IF(M45<>"",M45,IF(K45<>"",K45,IF(I45<>"",I45,""))) | P45: =IF(O45="","",IF(O45="PENDIENTE","Pendiente",IF(O45="NO EJECUTABLE","No ejecutable",IF(O45="VERIFICAR","Por verificar",IF(AND(F45="No cumple",O45="CUMPLE"),"Mejora",IF(AND(F45="No cumple",O45="PARCIAL"),"Mejora parcial",IF(AND(OR(F45="Cumple",F45="Sin ejecutar"),OR(O45="NO CUMPLE",O45="PARCIAL")),IF(F45="Cumple","Regresión","Falla nueva"),IF(AND(F45="No cumple",O45="NO CUMPLE"),"Sigue fallando","Se mantiene"))))))))
A46: 33 | B46: 8 | C46: Validar tipo de movimiento | D46: El sistema debe mostrar dos tipos de movimiento (Pedido y Servicio Interno) | F46: Cumple | O46: =IF(M46<>"",M46,IF(K46<>"",K46,IF(I46<>"",I46,""))) | P46: =IF(O46="","",IF(O46="PENDIENTE","Pendiente",IF(O46="NO EJECUTABLE","No ejecutable",IF(O46="VERIFICAR","Por verificar",IF(AND(F46="No cumple",O46="CUMPLE"),"Mejora",IF(AND(F46="No cumple",O46="PARCIAL"),"Mejora parcial",IF(AND(OR(F46="Cumple",F46="Sin ejecutar"),OR(O46="NO CUMPLE",O46="PARCIAL")),IF(F46="Cumple","Regresión","Falla nueva"),IF(AND(F46="No cumple",O46="NO CUMPLE"),"Sigue fallando","Se mantiene"))))))))
A47: 34 | B47: 9 | C47: Seleccionar Tipo de movimiento Servicio Interno | D47: EL tipo Pedido se factura (validar posteriormente) | E47: Servicio Interno con esperado de Pedido. | F47: Cumple | O47: =IF(M47<>"",M47,IF(K47<>"",K47,IF(I47<>"",I47,""))) | P47: =IF(O47="","",IF(O47="PENDIENTE","Pendiente",IF(O47="NO EJECUTABLE","No ejecutable",IF(O47="VERIFICAR","Por verificar",IF(AND(F47="No cumple",O47="CUMPLE"),"Mejora",IF(AND(F47="No cumple",O47="PARCIAL"),"Mejora parcial",IF(AND(OR(F47="Cumple",F47="Sin ejecutar"),OR(O47="NO CUMPLE",O47="PARCIAL")),IF(F47="Cumple","Regresión","Falla nueva"),IF(AND(F47="No cumple",O47="NO CUMPLE"),"Sigue fallando","Se mantiene"))))))))
A48: 35 | B48: 10 | C48: En complejidad indicar que No Aplica | D48: Validar que para esta UN no aplica Complejidad (sólo muestra esa opción) | F48: Cumple | O48: =IF(M48<>"",M48,IF(K48<>"",K48,IF(I48<>"",I48,""))) | P48: =IF(O48="","",IF(O48="PENDIENTE","Pendiente",IF(O48="NO EJECUTABLE","No ejecutable",IF(O48="VERIFICAR","Por verificar",IF(AND(F48="No cumple",O48="CUMPLE"),"Mejora",IF(AND(F48="No cumple",O48="PARCIAL"),"Mejora parcial",IF(AND(OR(F48="Cumple",F48="Sin ejecutar"),OR(O48="NO CUMPLE",O48="PARCIAL")),IF(F48="Cumple","Regresión","Falla nueva"),IF(AND(F48="No cumple",O48="NO CUMPLE"),"Sigue fallando","Se mantiene"))))))))
A49: 36 | B49: 11 | C49: En el campo Permitir Cancelar, seleccionar NO | F49: Cumple | O49: =IF(M49<>"",M49,IF(K49<>"",K49,IF(I49<>"",I49,""))) | P49: =IF(O49="","",IF(O49="PENDIENTE","Pendiente",IF(O49="NO EJECUTABLE","No ejecutable",IF(O49="VERIFICAR","Por verificar",IF(AND(F49="No cumple",O49="CUMPLE"),"Mejora",IF(AND(F49="No cumple",O49="PARCIAL"),"Mejora parcial",IF(AND(OR(F49="Cumple",F49="Sin ejecutar"),OR(O49="NO CUMPLE",O49="PARCIAL")),IF(F49="Cumple","Regresión","Falla nueva"),IF(AND(F49="No cumple",O49="NO CUMPLE"),"Sigue fallando","Se mantiene"))))))))
A50: 37 | B50: 12 | C50: Pulsar Aceptar | D50: El sistema genera un número consecutivo de pedido. | F50: Cumple | O50: =IF(M50<>"",M50,IF(K50<>"",K50,IF(I50<>"",I50,""))) | P50: =IF(O50="","",IF(O50="PENDIENTE","Pendiente",IF(O50="NO EJECUTABLE","No ejecutable",IF(O50="VERIFICAR","Por verificar",IF(AND(F50="No cumple",O50="CUMPLE"),"Mejora",IF(AND(F50="No cumple",O50="PARCIAL"),"Mejora parcial",IF(AND(OR(F50="Cumple",F50="Sin ejecutar"),OR(O50="NO CUMPLE",O50="PARCIAL")),IF(F50="Cumple","Regresión","Falla nueva"),IF(AND(F50="No cumple",O50="NO CUMPLE"),"Sigue fallando","Se mantiene"))))))))
C51: Pedido Detalle
A52: 38 | B52: 13 | C52: Tipo de personal | D52: Validad que sólo se muestren Operativos al no tener complejidad | F52: Cumple | O52: =IF(M52<>"",M52,IF(K52<>"",K52,IF(I52<>"",I52,""))) | P52: =IF(O52="","",IF(O52="PENDIENTE","Pendiente",IF(O52="NO EJECUTABLE","No ejecutable",IF(O52="VERIFICAR","Por verificar",IF(AND(F52="No cumple",O52="CUMPLE"),"Mejora",IF(AND(F52="No cumple",O52="PARCIAL"),"Mejora parcial",IF(AND(OR(F52="Cumple",F52="Sin ejecutar"),OR(O52="NO CUMPLE",O52="PARCIAL")),IF(F52="Cumple","Regresión","Falla nueva"),IF(AND(F52="No cumple",O52="NO CUMPLE"),"Sigue fallando","Se mantiene"))))))))
A53: 39 | B53: 14 | C53: Seleccionar Operativo | F53: Cumple | O53: =IF(M53<>"",M53,IF(K53<>"",K53,IF(I53<>"",I53,""))) | P53: =IF(O53="","",IF(O53="PENDIENTE","Pendiente",IF(O53="NO EJECUTABLE","No ejecutable",IF(O53="VERIFICAR","Por verificar",IF(AND(F53="No cumple",O53="CUMPLE"),"Mejora",IF(AND(F53="No cumple",O53="PARCIAL"),"Mejora parcial",IF(AND(OR(F53="Cumple",F53="Sin ejecutar"),OR(O53="NO CUMPLE",O53="PARCIAL")),IF(F53="Cumple","Regresión","Falla nueva"),IF(AND(F53="No cumple",O53="NO CUMPLE"),"Sigue fallando","Se mantiene"))))))))
A54: 40 | B54: 15 | C54: Producto: Riger | D54: Validar que el catálogo mostrado es el de PRG | F54: Cumple | O54: =IF(M54<>"",M54,IF(K54<>"",K54,IF(I54<>"",I54,""))) | P54: =IF(O54="","",IF(O54="PENDIENTE","Pendiente",IF(O54="NO EJECUTABLE","No ejecutable",IF(O54="VERIFICAR","Por verificar",IF(AND(F54="No cumple",O54="CUMPLE"),"Mejora",IF(AND(F54="No cumple",O54="PARCIAL"),"Mejora parcial",IF(AND(OR(F54="Cumple",F54="Sin ejecutar"),OR(O54="NO CUMPLE",O54="PARCIAL")),IF(F54="Cumple","Regresión","Falla nueva"),IF(AND(F54="No cumple",O54="NO CUMPLE"),"Sigue fallando","Se mantiene"))))))))
A55: 41 | B55: 16 | C55: Cantidad 1 - Turno 1 | F55: Cumple | O55: =IF(M55<>"",M55,IF(K55<>"",K55,IF(I55<>"",I55,""))) | P55: =IF(O55="","",IF(O55="PENDIENTE","Pendiente",IF(O55="NO EJECUTABLE","No ejecutable",IF(O55="VERIFICAR","Por verificar",IF(AND(F55="No cumple",O55="CUMPLE"),"Mejora",IF(AND(F55="No cumple",O55="PARCIAL"),"Mejora parcial",IF(AND(OR(F55="Cumple",F55="Sin ejecutar"),OR(O55="NO CUMPLE",O55="PARCIAL")),IF(F55="Cumple","Regresión","Falla nueva"),IF(AND(F55="No cumple",O55="NO CUMPLE"),"Sigue fallando","Se mantiene"))))))))
A56: 42 | B56: 17 | C56: Validar la jornada | D56: Debe mostrar 1 turno por 12 horas | F56: Cumple | O56: =IF(M56<>"",M56,IF(K56<>"",K56,IF(I56<>"",I56,""))) | P56: =IF(O56="","",IF(O56="PENDIENTE","Pendiente",IF(O56="NO EJECUTABLE","No ejecutable",IF(O56="VERIFICAR","Por verificar",IF(AND(F56="No cumple",O56="CUMPLE"),"Mejora",IF(AND(F56="No cumple",O56="PARCIAL"),"Mejora parcial",IF(AND(OR(F56="Cumple",F56="Sin ejecutar"),OR(O56="NO CUMPLE",O56="PARCIAL")),IF(F56="Cumple","Regresión","Falla nueva"),IF(AND(F56="No cumple",O56="NO CUMPLE"),"Sigue fallando","Se mantiene"))))))))
A57: 43 | B57: 18 | C57: Seleccionar una fecha de cita (debe ser el miércoles que se canceló) y de liberación | F57: Cumple | O57: =IF(M57<>"",M57,IF(K57<>"",K57,IF(I57<>"",I57,""))) | P57: =IF(O57="","",IF(O57="PENDIENTE","Pendiente",IF(O57="NO EJECUTABLE","No ejecutable",IF(O57="VERIFICAR","Por verificar",IF(AND(F57="No cumple",O57="CUMPLE"),"Mejora",IF(AND(F57="No cumple",O57="PARCIAL"),"Mejora parcial",IF(AND(OR(F57="Cumple",F57="Sin ejecutar"),OR(O57="NO CUMPLE",O57="PARCIAL")),IF(F57="Cumple","Regresión","Falla nueva"),IF(AND(F57="No cumple",O57="NO CUMPLE"),"Sigue fallando","Se mantiene"))))))))
A58: 44 | B58: 19 | C58: Presentación por producto | D58: Validar que nos se muestran presentaciones | F58: Cumple | O58: =IF(M58<>"",M58,IF(K58<>"",K58,IF(I58<>"",I58,""))) | P58: =IF(O58="","",IF(O58="PENDIENTE","Pendiente",IF(O58="NO EJECUTABLE","No ejecutable",IF(O58="VERIFICAR","Por verificar",IF(AND(F58="No cumple",O58="CUMPLE"),"Mejora",IF(AND(F58="No cumple",O58="PARCIAL"),"Mejora parcial",IF(AND(OR(F58="Cumple",F58="Sin ejecutar"),OR(O58="NO CUMPLE",O58="PARCIAL")),IF(F58="Cumple","Regresión","Falla nueva"),IF(AND(F58="No cumple",O58="NO CUMPLE"),"Sigue fallando","Se mantiene"))))))))
A59: 45 | B59: 20 | C59: Fase del evento - Show | F59: Cumple | O59: =IF(M59<>"",M59,IF(K59<>"",K59,IF(I59<>"",I59,""))) | P59: =IF(O59="","",IF(O59="PENDIENTE","Pendiente",IF(O59="NO EJECUTABLE","No ejecutable",IF(O59="VERIFICAR","Por verificar",IF(AND(F59="No cumple",O59="CUMPLE"),"Mejora",IF(AND(F59="No cumple",O59="PARCIAL"),"Mejora parcial",IF(AND(OR(F59="Cumple",F59="Sin ejecutar"),OR(O59="NO CUMPLE",O59="PARCIAL")),IF(F59="Cumple","Regresión","Falla nueva"),IF(AND(F59="No cumple",O59="NO CUMPLE"),"Sigue fallando","Se mantiene"))))))))
A60: 46 | B60: 21 | C60: No poner Bloque | F60: Cumple | O60: =IF(M60<>"",M60,IF(K60<>"",K60,IF(I60<>"",I60,""))) | P60: =IF(O60="","",IF(O60="PENDIENTE","Pendiente",IF(O60="NO EJECUTABLE","No ejecutable",IF(O60="VERIFICAR","Por verificar",IF(AND(F60="No cumple",O60="CUMPLE"),"Mejora",IF(AND(F60="No cumple",O60="PARCIAL"),"Mejora parcial",IF(AND(OR(F60="Cumple",F60="Sin ejecutar"),OR(O60="NO CUMPLE",O60="PARCIAL")),IF(F60="Cumple","Regresión","Falla nueva"),IF(AND(F60="No cumple",O60="NO CUMPLE"),"Sigue fallando","Se mantiene"))))))))
A61: 47 | B61: 22 | C61: Forzar la asignación de la persona que confirmó el bloque anterior | D61: El sistema no debe de dejar la asignación (en función del Puesto) | F61: Sin ejecutar | O61: =IF(M61<>"",M61,IF(K61<>"",K61,IF(I61<>"",I61,""))) | P61: =IF(O61="","",IF(O61="PENDIENTE","Pendiente",IF(O61="NO EJECUTABLE","No ejecutable",IF(O61="VERIFICAR","Por verificar",IF(AND(F61="No cumple",O61="CUMPLE"),"Mejora",IF(AND(F61="No cumple",O61="PARCIAL"),"Mejora parcial",IF(AND(OR(F61="Cumple",F61="Sin ejecutar"),OR(O61="NO CUMPLE",O61="PARCIAL")),IF(F61="Cumple","Regresión","Falla nueva"),IF(AND(F61="No cumple",O61="NO CUMPLE"),"Sigue fallando","Se mantiene"))))))))
A62: 48 | C62: Realizar la misma prueba, cambiando la propiedad del puesto para que sí permita la confirmación entre seriados | F62: Sin ejecutar | O62: =IF(M62<>"",M62,IF(K62<>"",K62,IF(I62<>"",I62,""))) | P62: =IF(O62="","",IF(O62="PENDIENTE","Pendiente",IF(O62="NO EJECUTABLE","No ejecutable",IF(O62="VERIFICAR","Por verificar",IF(AND(F62="No cumple",O62="CUMPLE"),"Mejora",IF(AND(F62="No cumple",O62="PARCIAL"),"Mejora parcial",IF(AND(OR(F62="Cumple",F62="Sin ejecutar"),OR(O62="NO CUMPLE",O62="PARCIAL")),IF(F62="Cumple","Regresión","Falla nueva"),IF(AND(F62="No cumple",O62="NO CUMPLE"),"Sigue fallando","Se mantiene"))))))))

Sheet ESC-06
A1: ESC-06 — Pedido de Transporte con empalme de horario
A2: Núm. original | B2: Escenario 6 | I2: Pasos | J2: =COUNT(A13:A17)
A3: Módulo | B3: Pedidos | I3: Ejecutados (último) | J3: =COUNTIF(O13:O17,"?*")
A4: Objetivo (propuesto, validar) | B4: Validar la detección de empalme de horarios entre detalles de un pedido de Transporte. | I4: CUMPLE (último) | J4: =COUNTIF(O13:O17,"CUMPLE")
A5: Funcionalidades | B5: Medio turno · empalme · aviso con IDs en conflicto | I5: % cumplimiento | J5: =IF(J2=0,0,J4/J2)
A6: Dependencias / datos | B6: —
A7: Sesión sugerida | B7: S06
A8: ⚠ Calidad del caso | B8: —
A9: Notas originales | B9: —
F11: CORRIDA LEGADO (HUMANOS) | I11: CICLO CLAUDE CODE: probar → corregir → re-probar
A12: # | B12: Paso orig. | C12: Descripción | D12: Resultado esperado | E12: ⚠ Calidad | F12: Legado: Resultado | G12: Legado: Observación | H12: Legado: Corrección | I12: R1 Resultado | J12: R1 Hallazgo / Obs. | K12: R2 Resultado | L12: R2 Hallazgo / Obs. | M12: R3 Resultado | N12: R3 Hallazgo / Obs. | O12: Último resultado | P12: Comparativo
A13: 1 | C13: Crear un pedido con la UN Transportes | F13: Cumple | O13: =IF(M13<>"",M13,IF(K13<>"",K13,IF(I13<>"",I13,""))) | P13: =IF(O13="","",IF(O13="PENDIENTE","Pendiente",IF(O13="NO EJECUTABLE","No ejecutable",IF(O13="VERIFICAR","Por verificar",IF(AND(F13="No cumple",O13="CUMPLE"),"Mejora",IF(AND(F13="No cumple",O13="PARCIAL"),"Mejora parcial",IF(AND(OR(F13="Cumple",F13="Sin ejecutar"),OR(O13="NO CUMPLE",O13="PARCIAL")),IF(F13="Cumple","Regresión","Falla nueva"),IF(AND(F13="No cumple",O13="NO CUMPLE"),"Sigue fallando","Se mantiene"))))))))
A14: 2 | C14: Crear un detalle con fecha de cita un día laborable a las 9am, con medio turno | F14: Cumple | O14: =IF(M14<>"",M14,IF(K14<>"",K14,IF(I14<>"",I14,""))) | P14: =IF(O14="","",IF(O14="PENDIENTE","Pendiente",IF(O14="NO EJECUTABLE","No ejecutable",IF(O14="VERIFICAR","Por verificar",IF(AND(F14="No cumple",O14="CUMPLE"),"Mejora",IF(AND(F14="No cumple",O14="PARCIAL"),"Mejora parcial",IF(AND(OR(F14="Cumple",F14="Sin ejecutar"),OR(O14="NO CUMPLE",O14="PARCIAL")),IF(F14="Cumple","Regresión","Falla nueva"),IF(AND(F14="No cumple",O14="NO CUMPLE"),"Sigue fallando","Se mantiene"))))))))
A15: 3 | C15: Crear otro detalle con fecha de cita a las 10 am | F15: No cumple | G15: Se puede realizar sin nignún prblema | O15: =IF(M15<>"",M15,IF(K15<>"",K15,IF(I15<>"",I15,""))) | P15: =IF(O15="","",IF(O15="PENDIENTE","Pendiente",IF(O15="NO EJECUTABLE","No ejecutable",IF(O15="VERIFICAR","Por verificar",IF(AND(F15="No cumple",O15="CUMPLE"),"Mejora",IF(AND(F15="No cumple",O15="PARCIAL"),"Mejora parcial",IF(AND(OR(F15="Cumple",F15="Sin ejecutar"),OR(O15="NO CUMPLE",O15="PARCIAL")),IF(F15="Cumple","Regresión","Falla nueva"),IF(AND(F15="No cumple",O15="NO CUMPLE"),"Sigue fallando","Se mantiene"))))))))
A16: 4 | C16: Validar que el sistema no permite generar el segundo detalle ya que el turno para el primer detalle es de 4 horas | F16: No cumple | G16: El sistema no realiza ningún aviso | O16: =IF(M16<>"",M16,IF(K16<>"",K16,IF(I16<>"",I16,""))) | P16: =IF(O16="","",IF(O16="PENDIENTE","Pendiente",IF(O16="NO EJECUTABLE","No ejecutable",IF(O16="VERIFICAR","Por verificar",IF(AND(F16="No cumple",O16="CUMPLE"),"Mejora",IF(AND(F16="No cumple",O16="PARCIAL"),"Mejora parcial",IF(AND(OR(F16="Cumple",F16="Sin ejecutar"),OR(O16="NO CUMPLE",O16="PARCIAL")),IF(F16="Cumple","Regresión","Falla nueva"),IF(AND(F16="No cumple",O16="NO CUMPLE"),"Sigue fallando","Se mantiene"))))))))
A17: 5 | C17: Validar que el sistema avisa de los detalles (Ids) con los que se está empalmando. | F17: Sin ejecutar | O17: =IF(M17<>"",M17,IF(K17<>"",K17,IF(I17<>"",I17,""))) | P17: =IF(O17="","",IF(O17="PENDIENTE","Pendiente",IF(O17="NO EJECUTABLE","No ejecutable",IF(O17="VERIFICAR","Por verificar",IF(AND(F17="No cumple",O17="CUMPLE"),"Mejora",IF(AND(F17="No cumple",O17="PARCIAL"),"Mejora parcial",IF(AND(OR(F17="Cumple",F17="Sin ejecutar"),OR(O17="NO CUMPLE",O17="PARCIAL")),IF(F17="Cumple","Regresión","Falla nueva"),IF(AND(F17="No cumple",O17="NO CUMPLE"),"Sigue fallando","Se mantiene"))))))))

Sheet ESC-07
A1: ESC-07 — Comprobar fecha y hora de liberación
A2: Núm. original | B2: Escenario 7 | I2: Pasos | J2: =COUNT(A13:A17)
A3: Módulo | B3: Pedidos | I3: Ejecutados (último) | J3: =COUNTIF(O13:O17,"?*")
A4: Objetivo (propuesto, validar) | B4: Validar la liberación programada por fecha y hora, y la actualización del semáforo. | I4: CUMPLE (último) | J4: =COUNTIF(O13:O17,"CUMPLE")
A5: Funcionalidades | B5: Fecha/hora de liberación · reservaciones · semáforo de detalles | I5: % cumplimiento | J5: =IF(J2=0,0,J4/J2)
A6: Dependencias / datos | B6: Espera de 1 hora real
A7: Sesión sugerida | B7: S06
A8: ⚠ Calidad del caso | B8: Requiere esperar la hora programada; considerar mecanismo para simular tiempo.
A9: Notas originales | B9: —
F11: CORRIDA LEGADO (HUMANOS) | I11: CICLO CLAUDE CODE: probar → corregir → re-probar
A12: # | B12: Paso orig. | C12: Descripción | D12: Resultado esperado | E12: ⚠ Calidad | F12: Legado: Resultado | G12: Legado: Observación | H12: Legado: Corrección | I12: R1 Resultado | J12: R1 Hallazgo / Obs. | K12: R2 Resultado | L12: R2 Hallazgo / Obs. | M12: R3 Resultado | N12: R3 Hallazgo / Obs. | O12: Último resultado | P12: Comparativo
A13: 1 | C13: Crear un pedido de UN Seguridad | F13: Cumple | O13: =IF(M13<>"",M13,IF(K13<>"",K13,IF(I13<>"",I13,""))) | P13: =IF(O13="","",IF(O13="PENDIENTE","Pendiente",IF(O13="NO EJECUTABLE","No ejecutable",IF(O13="VERIFICAR","Por verificar",IF(AND(F13="No cumple",O13="CUMPLE"),"Mejora",IF(AND(F13="No cumple",O13="PARCIAL"),"Mejora parcial",IF(AND(OR(F13="Cumple",F13="Sin ejecutar"),OR(O13="NO CUMPLE",O13="PARCIAL")),IF(F13="Cumple","Regresión","Falla nueva"),IF(AND(F13="No cumple",O13="NO CUMPLE"),"Sigue fallando","Se mantiene"))))))))
A14: 2 | C14: Crear un detalle pedido con fecha de cita posterior al día en curso | F14: Cumple | O14: =IF(M14<>"",M14,IF(K14<>"",K14,IF(I14<>"",I14,""))) | P14: =IF(O14="","",IF(O14="PENDIENTE","Pendiente",IF(O14="NO EJECUTABLE","No ejecutable",IF(O14="VERIFICAR","Por verificar",IF(AND(F14="No cumple",O14="CUMPLE"),"Mejora",IF(AND(F14="No cumple",O14="PARCIAL"),"Mejora parcial",IF(AND(OR(F14="Cumple",F14="Sin ejecutar"),OR(O14="NO CUMPLE",O14="PARCIAL")),IF(F14="Cumple","Regresión","Falla nueva"),IF(AND(F14="No cumple",O14="NO CUMPLE"),"Sigue fallando","Se mantiene"))))))))
A15: 3 | C15: Agregar una fecha y hora de liberación del día en curso, con 1 hora posterior a la prueba | F15: Sin ejecutar | O15: =IF(M15<>"",M15,IF(K15<>"",K15,IF(I15<>"",I15,""))) | P15: =IF(O15="","",IF(O15="PENDIENTE","Pendiente",IF(O15="NO EJECUTABLE","No ejecutable",IF(O15="VERIFICAR","Por verificar",IF(AND(F15="No cumple",O15="CUMPLE"),"Mejora",IF(AND(F15="No cumple",O15="PARCIAL"),"Mejora parcial",IF(AND(OR(F15="Cumple",F15="Sin ejecutar"),OR(O15="NO CUMPLE",O15="PARCIAL")),IF(F15="Cumple","Regresión","Falla nueva"),IF(AND(F15="No cumple",O15="NO CUMPLE"),"Sigue fallando","Se mantiene"))))))))
A16: 4 | C16: Validar en la página de reservaciones que el pedido se liberó a la hora programada. | F16: Sin ejecutar | O16: =IF(M16<>"",M16,IF(K16<>"",K16,IF(I16<>"",I16,""))) | P16: =IF(O16="","",IF(O16="PENDIENTE","Pendiente",IF(O16="NO EJECUTABLE","No ejecutable",IF(O16="VERIFICAR","Por verificar",IF(AND(F16="No cumple",O16="CUMPLE"),"Mejora",IF(AND(F16="No cumple",O16="PARCIAL"),"Mejora parcial",IF(AND(OR(F16="Cumple",F16="Sin ejecutar"),OR(O16="NO CUMPLE",O16="PARCIAL")),IF(F16="Cumple","Regresión","Falla nueva"),IF(AND(F16="No cumple",O16="NO CUMPLE"),"Sigue fallando","Se mantiene"))))))))
A17: 5 | C17: Validar que el semáforo de los detalles de pedido se actualiza de color. | F17: Sin ejecutar | O17: =IF(M17<>"",M17,IF(K17<>"",K17,IF(I17<>"",I17,""))) | P17: =IF(O17="","",IF(O17="PENDIENTE","Pendiente",IF(O17="NO EJECUTABLE","No ejecutable",IF(O17="VERIFICAR","Por verificar",IF(AND(F17="No cumple",O17="CUMPLE"),"Mejora",IF(AND(F17="No cumple",O17="PARCIAL"),"Mejora parcial",IF(AND(OR(F17="Cumple",F17="Sin ejecutar"),OR(O17="NO CUMPLE",O17="PARCIAL")),IF(F17="Cumple","Regresión","Falla nueva"),IF(AND(F17="No cumple",O17="NO CUMPLE"),"Sigue fallando","Se mantiene"))))))))

Sheet ESC-08
A1: ESC-08 — Validación de plazas
A2: Núm. original | B2: Escenario 8 | I2: Pasos | J2: =COUNT(A13:A25)
A3: Módulo | B3: Asignaciones / Nómina | I3: Ejecutados (último) | J3: =COUNTIF(O13:O25,"?*")
A4: Objetivo (propuesto, validar) | B4: Validar el sueldo según plaza vigente en la fecha del evento y su recálculo al mover la fecha de inicio. | I4: CUMPLE (último) | J4: =COUNTIF(O13:O25,"CUMPLE")
A5: Funcionalidades | B5: Plazas por empleado · sueldo default por puesto · vigencia · recálculo en pagos & honorarios | I5: % cumplimiento | J5: =IF(J2=0,0,J4/J2)
A6: Dependencias / datos | B6: Empleado ID 54943; fechas 2019
A7: Sesión sugerida | B7: S07
A8: ⚠ Calidad del caso | B8: Usa fechas de 2019: confirmar si siguen siendo válidas en el sistema nuevo.
A9: Notas originales | B9: —
F11: CORRIDA LEGADO (HUMANOS) | I11: CICLO CLAUDE CODE: probar → corregir → re-probar
A12: # | B12: Paso orig. | C12: Descripción | D12: Resultado esperado | E12: ⚠ Calidad | F12: Legado: Resultado | G12: Legado: Observación | H12: Legado: Corrección | I12: R1 Resultado | J12: R1 Hallazgo / Obs. | K12: R2 Resultado | L12: R2 Hallazgo / Obs. | M12: R3 Resultado | N12: R3 Hallazgo / Obs. | O12: Último resultado | P12: Comparativo
A13: 1 | C13: Dar de alta un empleado de seguridad con fecha de incicio de puesto 15 de Febrero de 2019 ID(54943) | F13: Sin ejecutar | O13: =IF(M13<>"",M13,IF(K13<>"",K13,IF(I13<>"",I13,""))) | P13: =IF(O13="","",IF(O13="PENDIENTE","Pendiente",IF(O13="NO EJECUTABLE","No ejecutable",IF(O13="VERIFICAR","Por verificar",IF(AND(F13="No cumple",O13="CUMPLE"),"Mejora",IF(AND(F13="No cumple",O13="PARCIAL"),"Mejora parcial",IF(AND(OR(F13="Cumple",F13="Sin ejecutar"),OR(O13="NO CUMPLE",O13="PARCIAL")),IF(F13="Cumple","Regresión","Falla nueva"),IF(AND(F13="No cumple",O13="NO CUMPLE"),"Sigue fallando","Se mantiene"))))))))
A14: 2 | C14: Validar que el sistema le asigna el sueldo por default correspondiente a su puesto. ($285) | F14: Sin ejecutar | O14: =IF(M14<>"",M14,IF(K14<>"",K14,IF(I14<>"",I14,""))) | P14: =IF(O14="","",IF(O14="PENDIENTE","Pendiente",IF(O14="NO EJECUTABLE","No ejecutable",IF(O14="VERIFICAR","Por verificar",IF(AND(F14="No cumple",O14="CUMPLE"),"Mejora",IF(AND(F14="No cumple",O14="PARCIAL"),"Mejora parcial",IF(AND(OR(F14="Cumple",F14="Sin ejecutar"),OR(O14="NO CUMPLE",O14="PARCIAL")),IF(F14="Cumple","Regresión","Falla nueva"),IF(AND(F14="No cumple",O14="NO CUMPLE"),"Sigue fallando","Se mantiene"))))))))
A15: 3 | C15: Agregar al empleado otra plaza del mismo puesto con fecha inicial del 20 de Febrero 2019 con $300 pesos | F15: Sin ejecutar | O15: =IF(M15<>"",M15,IF(K15<>"",K15,IF(I15<>"",I15,""))) | P15: =IF(O15="","",IF(O15="PENDIENTE","Pendiente",IF(O15="NO EJECUTABLE","No ejecutable",IF(O15="VERIFICAR","Por verificar",IF(AND(F15="No cumple",O15="CUMPLE"),"Mejora",IF(AND(F15="No cumple",O15="PARCIAL"),"Mejora parcial",IF(AND(OR(F15="Cumple",F15="Sin ejecutar"),OR(O15="NO CUMPLE",O15="PARCIAL")),IF(F15="Cumple","Regresión","Falla nueva"),IF(AND(F15="No cumple",O15="NO CUMPLE"),"Sigue fallando","Se mantiene"))))))))
A16: 4 | C16: Crear un pedido de seguridad con dos detalles. | F16: Sin ejecutar | O16: =IF(M16<>"",M16,IF(K16<>"",K16,IF(I16<>"",I16,""))) | P16: =IF(O16="","",IF(O16="PENDIENTE","Pendiente",IF(O16="NO EJECUTABLE","No ejecutable",IF(O16="VERIFICAR","Por verificar",IF(AND(F16="No cumple",O16="CUMPLE"),"Mejora",IF(AND(F16="No cumple",O16="PARCIAL"),"Mejora parcial",IF(AND(OR(F16="Cumple",F16="Sin ejecutar"),OR(O16="NO CUMPLE",O16="PARCIAL")),IF(F16="Cumple","Regresión","Falla nueva"),IF(AND(F16="No cumple",O16="NO CUMPLE"),"Sigue fallando","Se mantiene"))))))))
A17: 5 | C17: El primer detalle ponerle fecha de cita 10 de Febero de 2019 | F17: Sin ejecutar | O17: =IF(M17<>"",M17,IF(K17<>"",K17,IF(I17<>"",I17,""))) | P17: =IF(O17="","",IF(O17="PENDIENTE","Pendiente",IF(O17="NO EJECUTABLE","No ejecutable",IF(O17="VERIFICAR","Por verificar",IF(AND(F17="No cumple",O17="CUMPLE"),"Mejora",IF(AND(F17="No cumple",O17="PARCIAL"),"Mejora parcial",IF(AND(OR(F17="Cumple",F17="Sin ejecutar"),OR(O17="NO CUMPLE",O17="PARCIAL")),IF(F17="Cumple","Regresión","Falla nueva"),IF(AND(F17="No cumple",O17="NO CUMPLE"),"Sigue fallando","Se mantiene"))))))))
A18: 6 | C18: El segundo detalle ponerle fecha de cita del 21 de Febrero del 2019 | F18: Sin ejecutar | O18: =IF(M18<>"",M18,IF(K18<>"",K18,IF(I18<>"",I18,""))) | P18: =IF(O18="","",IF(O18="PENDIENTE","Pendiente",IF(O18="NO EJECUTABLE","No ejecutable",IF(O18="VERIFICAR","Por verificar",IF(AND(F18="No cumple",O18="CUMPLE"),"Mejora",IF(AND(F18="No cumple",O18="PARCIAL"),"Mejora parcial",IF(AND(OR(F18="Cumple",F18="Sin ejecutar"),OR(O18="NO CUMPLE",O18="PARCIAL")),IF(F18="Cumple","Regresión","Falla nueva"),IF(AND(F18="No cumple",O18="NO CUMPLE"),"Sigue fallando","Se mantiene"))))))))
A19: 7 | C19: Liberar el Pedido | F19: Sin ejecutar | O19: =IF(M19<>"",M19,IF(K19<>"",K19,IF(I19<>"",I19,""))) | P19: =IF(O19="","",IF(O19="PENDIENTE","Pendiente",IF(O19="NO EJECUTABLE","No ejecutable",IF(O19="VERIFICAR","Por verificar",IF(AND(F19="No cumple",O19="CUMPLE"),"Mejora",IF(AND(F19="No cumple",O19="PARCIAL"),"Mejora parcial",IF(AND(OR(F19="Cumple",F19="Sin ejecutar"),OR(O19="NO CUMPLE",O19="PARCIAL")),IF(F19="Cumple","Regresión","Falla nueva"),IF(AND(F19="No cumple",O19="NO CUMPLE"),"Sigue fallando","Se mantiene"))))))))
A20: 8 | C20: El nuevo empleado, confirma el primer detalle del pedido | F20: Sin ejecutar | O20: =IF(M20<>"",M20,IF(K20<>"",K20,IF(I20<>"",I20,""))) | P20: =IF(O20="","",IF(O20="PENDIENTE","Pendiente",IF(O20="NO EJECUTABLE","No ejecutable",IF(O20="VERIFICAR","Por verificar",IF(AND(F20="No cumple",O20="CUMPLE"),"Mejora",IF(AND(F20="No cumple",O20="PARCIAL"),"Mejora parcial",IF(AND(OR(F20="Cumple",F20="Sin ejecutar"),OR(O20="NO CUMPLE",O20="PARCIAL")),IF(F20="Cumple","Regresión","Falla nueva"),IF(AND(F20="No cumple",O20="NO CUMPLE"),"Sigue fallando","Se mantiene"))))))))
A21: 9 | C21: Validar que el sueldo va a salir en cero (ya que no tiene plaza vigente para esa fecha) | F21: Sin ejecutar | O21: =IF(M21<>"",M21,IF(K21<>"",K21,IF(I21<>"",I21,""))) | P21: =IF(O21="","",IF(O21="PENDIENTE","Pendiente",IF(O21="NO EJECUTABLE","No ejecutable",IF(O21="VERIFICAR","Por verificar",IF(AND(F21="No cumple",O21="CUMPLE"),"Mejora",IF(AND(F21="No cumple",O21="PARCIAL"),"Mejora parcial",IF(AND(OR(F21="Cumple",F21="Sin ejecutar"),OR(O21="NO CUMPLE",O21="PARCIAL")),IF(F21="Cumple","Regresión","Falla nueva"),IF(AND(F21="No cumple",O21="NO CUMPLE"),"Sigue fallando","Se mantiene"))))))))
A22: 10 | C22: El nuevo emplealdo confirma el segundo detalle del pedido | F22: Sin ejecutar | O22: =IF(M22<>"",M22,IF(K22<>"",K22,IF(I22<>"",I22,""))) | P22: =IF(O22="","",IF(O22="PENDIENTE","Pendiente",IF(O22="NO EJECUTABLE","No ejecutable",IF(O22="VERIFICAR","Por verificar",IF(AND(F22="No cumple",O22="CUMPLE"),"Mejora",IF(AND(F22="No cumple",O22="PARCIAL"),"Mejora parcial",IF(AND(OR(F22="Cumple",F22="Sin ejecutar"),OR(O22="NO CUMPLE",O22="PARCIAL")),IF(F22="Cumple","Regresión","Falla nueva"),IF(AND(F22="No cumple",O22="NO CUMPLE"),"Sigue fallando","Se mantiene"))))))))
A23: 11 | C23: Validar que el sueldo sale en $300 pesos | F23: Sin ejecutar | O23: =IF(M23<>"",M23,IF(K23<>"",K23,IF(I23<>"",I23,""))) | P23: =IF(O23="","",IF(O23="PENDIENTE","Pendiente",IF(O23="NO EJECUTABLE","No ejecutable",IF(O23="VERIFICAR","Por verificar",IF(AND(F23="No cumple",O23="CUMPLE"),"Mejora",IF(AND(F23="No cumple",O23="PARCIAL"),"Mejora parcial",IF(AND(OR(F23="Cumple",F23="Sin ejecutar"),OR(O23="NO CUMPLE",O23="PARCIAL")),IF(F23="Cumple","Regresión","Falla nueva"),IF(AND(F23="No cumple",O23="NO CUMPLE"),"Sigue fallando","Se mantiene"))))))))
A24: 12 | C24: Entrar como administrador de nómina, y recorrer la fecha de inicio de puesto al 9 de Febrero | F24: Sin ejecutar | O24: =IF(M24<>"",M24,IF(K24<>"",K24,IF(I24<>"",I24,""))) | P24: =IF(O24="","",IF(O24="PENDIENTE","Pendiente",IF(O24="NO EJECUTABLE","No ejecutable",IF(O24="VERIFICAR","Por verificar",IF(AND(F24="No cumple",O24="CUMPLE"),"Mejora",IF(AND(F24="No cumple",O24="PARCIAL"),"Mejora parcial",IF(AND(OR(F24="Cumple",F24="Sin ejecutar"),OR(O24="NO CUMPLE",O24="PARCIAL")),IF(F24="Cumple","Regresión","Falla nueva"),IF(AND(F24="No cumple",O24="NO CUMPLE"),"Sigue fallando","Se mantiene"))))))))
A25: 13 | C25: Validar que en pagos & honorarios se recalculó el monto del empleado y ya sale los $285 | F25: Sin ejecutar | O25: =IF(M25<>"",M25,IF(K25<>"",K25,IF(I25<>"",I25,""))) | P25: =IF(O25="","",IF(O25="PENDIENTE","Pendiente",IF(O25="NO EJECUTABLE","No ejecutable",IF(O25="VERIFICAR","Por verificar",IF(AND(F25="No cumple",O25="CUMPLE"),"Mejora",IF(AND(F25="No cumple",O25="PARCIAL"),"Mejora parcial",IF(AND(OR(F25="Cumple",F25="Sin ejecutar"),OR(O25="NO CUMPLE",O25="PARCIAL")),IF(F25="Cumple","Regresión","Falla nueva"),IF(AND(F25="No cumple",O25="NO CUMPLE"),"Sigue fallando","Se mantiene"))))))))

Sheet ESC-09
A1: ESC-09 — Validación de certeza valor
A2: Núm. original | B2: Escenario 9 | I2: Pasos | J2: =COUNT(A13:A19)
A3: Módulo | B3: Asignaciones | I3: Ejecutados (último) | J3: =COUNTIF(O13:O19,"?*")
A4: Objetivo (propuesto, validar) | B4: Validar que la certeza valor del empleado restringe visibilidad y asignación forzada. | I4: CUMPLE (último) | J4: =COUNTIF(O13:O19,"CUMPLE")
A5: Funcionalidades | B5: Certeza valor por puesto · visibilidad en confirmación · bloqueo de asignación forzada | I5: % cumplimiento | J5: =IF(J2=0,0,J4/J2)
A6: Dependencias / datos | B6: Empleado ID 57231
A7: Sesión sugerida | B7: S07
A8: ⚠ Calidad del caso | B8: —
A9: Notas originales | B9: —
F11: CORRIDA LEGADO (HUMANOS) | I11: CICLO CLAUDE CODE: probar → corregir → re-probar
A12: # | B12: Paso orig. | C12: Descripción | D12: Resultado esperado | E12: ⚠ Calidad | F12: Legado: Resultado | G12: Legado: Observación | H12: Legado: Corrección | I12: R1 Resultado | J12: R1 Hallazgo / Obs. | K12: R2 Resultado | L12: R2 Hallazgo / Obs. | M12: R3 Resultado | N12: R3 Hallazgo / Obs. | O12: Último resultado | P12: Comparativo
A13: 1 | C13: Crear un nuevo empleado de seguridad ID(57231) | F13: Sin ejecutar | O13: =IF(M13<>"",M13,IF(K13<>"",K13,IF(I13<>"",I13,""))) | P13: =IF(O13="","",IF(O13="PENDIENTE","Pendiente",IF(O13="NO EJECUTABLE","No ejecutable",IF(O13="VERIFICAR","Por verificar",IF(AND(F13="No cumple",O13="CUMPLE"),"Mejora",IF(AND(F13="No cumple",O13="PARCIAL"),"Mejora parcial",IF(AND(OR(F13="Cumple",F13="Sin ejecutar"),OR(O13="NO CUMPLE",O13="PARCIAL")),IF(F13="Cumple","Regresión","Falla nueva"),IF(AND(F13="No cumple",O13="NO CUMPLE"),"Sigue fallando","Se mantiene"))))))))
A14: 2 | C14: Validar que su certeza valor es 0.9, que es la que tiene el puesto por default | F14: Sin ejecutar | O14: =IF(M14<>"",M14,IF(K14<>"",K14,IF(I14<>"",I14,""))) | P14: =IF(O14="","",IF(O14="PENDIENTE","Pendiente",IF(O14="NO EJECUTABLE","No ejecutable",IF(O14="VERIFICAR","Por verificar",IF(AND(F14="No cumple",O14="CUMPLE"),"Mejora",IF(AND(F14="No cumple",O14="PARCIAL"),"Mejora parcial",IF(AND(OR(F14="Cumple",F14="Sin ejecutar"),OR(O14="NO CUMPLE",O14="PARCIAL")),IF(F14="Cumple","Regresión","Falla nueva"),IF(AND(F14="No cumple",O14="NO CUMPLE"),"Sigue fallando","Se mantiene"))))))))
A15: 3 | C15: Crear un pedido de seguridad con un detalle con cantidad 1. | F15: Sin ejecutar | O15: =IF(M15<>"",M15,IF(K15<>"",K15,IF(I15<>"",I15,""))) | P15: =IF(O15="","",IF(O15="PENDIENTE","Pendiente",IF(O15="NO EJECUTABLE","No ejecutable",IF(O15="VERIFICAR","Por verificar",IF(AND(F15="No cumple",O15="CUMPLE"),"Mejora",IF(AND(F15="No cumple",O15="PARCIAL"),"Mejora parcial",IF(AND(OR(F15="Cumple",F15="Sin ejecutar"),OR(O15="NO CUMPLE",O15="PARCIAL")),IF(F15="Cumple","Regresión","Falla nueva"),IF(AND(F15="No cumple",O15="NO CUMPLE"),"Sigue fallando","Se mantiene"))))))))
A16: 4 | C16: Liberar el pedido | F16: Sin ejecutar | O16: =IF(M16<>"",M16,IF(K16<>"",K16,IF(I16<>"",I16,""))) | P16: =IF(O16="","",IF(O16="PENDIENTE","Pendiente",IF(O16="NO EJECUTABLE","No ejecutable",IF(O16="VERIFICAR","Por verificar",IF(AND(F16="No cumple",O16="CUMPLE"),"Mejora",IF(AND(F16="No cumple",O16="PARCIAL"),"Mejora parcial",IF(AND(OR(F16="Cumple",F16="Sin ejecutar"),OR(O16="NO CUMPLE",O16="PARCIAL")),IF(F16="Cumple","Regresión","Falla nueva"),IF(AND(F16="No cumple",O16="NO CUMPLE"),"Sigue fallando","Se mantiene"))))))))
A17: 5 | C17: Validar que en la página de confirmación del empleado no le aparezca el evento | F17: Sin ejecutar | O17: =IF(M17<>"",M17,IF(K17<>"",K17,IF(I17<>"",I17,""))) | P17: =IF(O17="","",IF(O17="PENDIENTE","Pendiente",IF(O17="NO EJECUTABLE","No ejecutable",IF(O17="VERIFICAR","Por verificar",IF(AND(F17="No cumple",O17="CUMPLE"),"Mejora",IF(AND(F17="No cumple",O17="PARCIAL"),"Mejora parcial",IF(AND(OR(F17="Cumple",F17="Sin ejecutar"),OR(O17="NO CUMPLE",O17="PARCIAL")),IF(F17="Cumple","Regresión","Falla nueva"),IF(AND(F17="No cumple",O17="NO CUMPLE"),"Sigue fallando","Se mantiene"))))))))
A18: 6 | C18: Volver a pedido y realizar una asignación forzada o preasignada del empleado. | F18: Sin ejecutar | O18: =IF(M18<>"",M18,IF(K18<>"",K18,IF(I18<>"",I18,""))) | P18: =IF(O18="","",IF(O18="PENDIENTE","Pendiente",IF(O18="NO EJECUTABLE","No ejecutable",IF(O18="VERIFICAR","Por verificar",IF(AND(F18="No cumple",O18="CUMPLE"),"Mejora",IF(AND(F18="No cumple",O18="PARCIAL"),"Mejora parcial",IF(AND(OR(F18="Cumple",F18="Sin ejecutar"),OR(O18="NO CUMPLE",O18="PARCIAL")),IF(F18="Cumple","Regresión","Falla nueva"),IF(AND(F18="No cumple",O18="NO CUMPLE"),"Sigue fallando","Se mantiene"))))))))
A19: 7 | C19: El sistema no debe dejar realizar la asignación forzada. | F19: Sin ejecutar | O19: =IF(M19<>"",M19,IF(K19<>"",K19,IF(I19<>"",I19,""))) | P19: =IF(O19="","",IF(O19="PENDIENTE","Pendiente",IF(O19="NO EJECUTABLE","No ejecutable",IF(O19="VERIFICAR","Por verificar",IF(AND(F19="No cumple",O19="CUMPLE"),"Mejora",IF(AND(F19="No cumple",O19="PARCIAL"),"Mejora parcial",IF(AND(OR(F19="Cumple",F19="Sin ejecutar"),OR(O19="NO CUMPLE",O19="PARCIAL")),IF(F19="Cumple","Regresión","Falla nueva"),IF(AND(F19="No cumple",O19="NO CUMPLE"),"Sigue fallando","Se mantiene"))))))))

Sheet ESC-10
A1: ESC-10 — Cancelación de preasignación forzada por no confirmación
A2: Núm. original | B2: Escenario 10 | I2: Pasos | J2: =COUNT(A13:A19)
A3: Módulo | B3: Asignaciones | I3: Ejecutados (último) | J3: =COUNTIF(O13:O19,"?*")
A4: Objetivo (propuesto, validar) | B4: Validar el proceso de cancelación de preasignaciones no confirmadas y la visibilidad posterior. | I4: CUMPLE (último) | J4: =COUNTIF(O13:O19,"CUMPLE")
A5: Funcionalidades | B5: Preasignación · visibilidad para no asignados · proceso de cancelación | I5: % cumplimiento | J5: =IF(J2=0,0,J4/J2)
A6: Dependencias / datos | B6: Empleados ID 3891, 16338, 33817, 46486, 54501
A7: Sesión sugerida | B7: S08
A8: ⚠ Calidad del caso | B8: Pide 4 personas pero lista 5 IDs.
A9: Notas originales | B9: —
F11: CORRIDA LEGADO (HUMANOS) | I11: CICLO CLAUDE CODE: probar → corregir → re-probar
A12: # | B12: Paso orig. | C12: Descripción | D12: Resultado esperado | E12: ⚠ Calidad | F12: Legado: Resultado | G12: Legado: Observación | H12: Legado: Corrección | I12: R1 Resultado | J12: R1 Hallazgo / Obs. | K12: R2 Resultado | L12: R2 Hallazgo / Obs. | M12: R3 Resultado | N12: R3 Hallazgo / Obs. | O12: Último resultado | P12: Comparativo
A13: 1 | C13: Crear un pedido de seguridad | F13: Cumple | O13: =IF(M13<>"",M13,IF(K13<>"",K13,IF(I13<>"",I13,""))) | P13: =IF(O13="","",IF(O13="PENDIENTE","Pendiente",IF(O13="NO EJECUTABLE","No ejecutable",IF(O13="VERIFICAR","Por verificar",IF(AND(F13="No cumple",O13="CUMPLE"),"Mejora",IF(AND(F13="No cumple",O13="PARCIAL"),"Mejora parcial",IF(AND(OR(F13="Cumple",F13="Sin ejecutar"),OR(O13="NO CUMPLE",O13="PARCIAL")),IF(F13="Cumple","Regresión","Falla nueva"),IF(AND(F13="No cumple",O13="NO CUMPLE"),"Sigue fallando","Se mantiene"))))))))
A14: 2 | C14: Crear un detalle de pedido con fecha del día siguiente a las 7pm solicitando 4 personas ID(3891,16338,33817,46486,54501) | F14: Sin ejecutar | O14: =IF(M14<>"",M14,IF(K14<>"",K14,IF(I14<>"",I14,""))) | P14: =IF(O14="","",IF(O14="PENDIENTE","Pendiente",IF(O14="NO EJECUTABLE","No ejecutable",IF(O14="VERIFICAR","Por verificar",IF(AND(F14="No cumple",O14="CUMPLE"),"Mejora",IF(AND(F14="No cumple",O14="PARCIAL"),"Mejora parcial",IF(AND(OR(F14="Cumple",F14="Sin ejecutar"),OR(O14="NO CUMPLE",O14="PARCIAL")),IF(F14="Cumple","Regresión","Falla nueva"),IF(AND(F14="No cumple",O14="NO CUMPLE"),"Sigue fallando","Se mantiene"))))))))
A15: 3 | C15: Preasignar a cuatro empleados al pedido | F15: Sin ejecutar | O15: =IF(M15<>"",M15,IF(K15<>"",K15,IF(I15<>"",I15,""))) | P15: =IF(O15="","",IF(O15="PENDIENTE","Pendiente",IF(O15="NO EJECUTABLE","No ejecutable",IF(O15="VERIFICAR","Por verificar",IF(AND(F15="No cumple",O15="CUMPLE"),"Mejora",IF(AND(F15="No cumple",O15="PARCIAL"),"Mejora parcial",IF(AND(OR(F15="Cumple",F15="Sin ejecutar"),OR(O15="NO CUMPLE",O15="PARCIAL")),IF(F15="Cumple","Regresión","Falla nueva"),IF(AND(F15="No cumple",O15="NO CUMPLE"),"Sigue fallando","Se mantiene"))))))))
A16: 4 | C16: Liberar el detalle | F16: Sin ejecutar | O16: =IF(M16<>"",M16,IF(K16<>"",K16,IF(I16<>"",I16,""))) | P16: =IF(O16="","",IF(O16="PENDIENTE","Pendiente",IF(O16="NO EJECUTABLE","No ejecutable",IF(O16="VERIFICAR","Por verificar",IF(AND(F16="No cumple",O16="CUMPLE"),"Mejora",IF(AND(F16="No cumple",O16="PARCIAL"),"Mejora parcial",IF(AND(OR(F16="Cumple",F16="Sin ejecutar"),OR(O16="NO CUMPLE",O16="PARCIAL")),IF(F16="Cumple","Regresión","Falla nueva"),IF(AND(F16="No cumple",O16="NO CUMPLE"),"Sigue fallando","Se mantiene"))))))))
A17: 5 | C17: Entrar a la página de reservaciones con otro empleado de seguridad (ninguno de los 4 asignados) y validar que no pueden ver el pedido | F17: Sin ejecutar | O17: =IF(M17<>"",M17,IF(K17<>"",K17,IF(I17<>"",I17,""))) | P17: =IF(O17="","",IF(O17="PENDIENTE","Pendiente",IF(O17="NO EJECUTABLE","No ejecutable",IF(O17="VERIFICAR","Por verificar",IF(AND(F17="No cumple",O17="CUMPLE"),"Mejora",IF(AND(F17="No cumple",O17="PARCIAL"),"Mejora parcial",IF(AND(OR(F17="Cumple",F17="Sin ejecutar"),OR(O17="NO CUMPLE",O17="PARCIAL")),IF(F17="Cumple","Regresión","Falla nueva"),IF(AND(F17="No cumple",O17="NO CUMPLE"),"Sigue fallando","Se mantiene"))))))))
A18: 6 | C18: Correr manualmente el proceso de cancelación de preasignados | F18: Sin ejecutar | O18: =IF(M18<>"",M18,IF(K18<>"",K18,IF(I18<>"",I18,""))) | P18: =IF(O18="","",IF(O18="PENDIENTE","Pendiente",IF(O18="NO EJECUTABLE","No ejecutable",IF(O18="VERIFICAR","Por verificar",IF(AND(F18="No cumple",O18="CUMPLE"),"Mejora",IF(AND(F18="No cumple",O18="PARCIAL"),"Mejora parcial",IF(AND(OR(F18="Cumple",F18="Sin ejecutar"),OR(O18="NO CUMPLE",O18="PARCIAL")),IF(F18="Cumple","Regresión","Falla nueva"),IF(AND(F18="No cumple",O18="NO CUMPLE"),"Sigue fallando","Se mantiene"))))))))
A19: 7 | C19: Validar que el otro empleado de seguridad ya pueda ver el pedido | F19: Sin ejecutar | O19: =IF(M19<>"",M19,IF(K19<>"",K19,IF(I19<>"",I19,""))) | P19: =IF(O19="","",IF(O19="PENDIENTE","Pendiente",IF(O19="NO EJECUTABLE","No ejecutable",IF(O19="VERIFICAR","Por verificar",IF(AND(F19="No cumple",O19="CUMPLE"),"Mejora",IF(AND(F19="No cumple",O19="PARCIAL"),"Mejora parcial",IF(AND(OR(F19="Cumple",F19="Sin ejecutar"),OR(O19="NO CUMPLE",O19="PARCIAL")),IF(F19="Cumple","Regresión","Falla nueva"),IF(AND(F19="No cumple",O19="NO CUMPLE"),"Sigue fallando","Se mantiene"))))))))

Sheet ESC-11
A1: ESC-11 — Confirmación de personal sin puesto asignado vigente
A2: Núm. original | B2: Escenario 11 | I2: Pasos | J2: =COUNT(A13:A19)
A3: Módulo | B3: Asignaciones | I3: Ejecutados (último) | J3: =COUNTIF(O13:O19,"?*")
A4: Objetivo (propuesto, validar) | B4: Validar que no se permita preasignar a un empleado sin puesto vigente. | I4: CUMPLE (último) | J4: =COUNTIF(O13:O19,"CUMPLE")
A5: Funcionalidades | B5: Puesto requerido · vigencia de puesto · mensajes de error | I5: % cumplimiento | J5: =IF(J2=0,0,J4/J2)
A6: Dependencias / datos | B6: Empleado ID 58172
A7: Sesión sugerida | B7: S07
A8: ⚠ Calidad del caso | B8: Legado: los mensajes emergentes no indican qué regla falló.
A9: Notas originales | B9: NOTA: Las pruebas de validación con pre-asignaciones se realizarán también en la página de reservaciones, ya que aplican las mismas reglas.
F11: CORRIDA LEGADO (HUMANOS) | I11: CICLO CLAUDE CODE: probar → corregir → re-probar
